Workbook

Sheet July 2023 
A1: Monthly Budget - July 2023
A4: Monthly Spending | G4: Monthly Overview | J4: Expenses over Time
A5: Category | B5: Budgeted | C5: Amount Spent | D5: Amount Remaining | E5: % Remaining | G5: Income
A6: Fixed | B6: 2500 | C6: =sumif($B$20:$C$100,A6,$C$20:$C$100) -> 2663.68 | D6: =B6-C6 -> -163.68 | E6: =D6/B6 -> -0.065472 | G6: Martin Paycheck | H6: ='MartinRachel Pay Stub'!B20*2 -> 3851.86
A7: Utilities | B7: 0 | C7: =sumif($B$20:$C$100,A7,$C$20:$C$100) -> 0 | D7: =B7-C7 -> 0 | E7: =D7/B7 -> #DIV/0! | G7: Rachel Paycheck | H7: ='MartinRachel Pay Stub'!E20*2 -> 5429.1
A8: Bills | B8: 250 | C8: =sumif($B$20:$C$100,A8,$C$20:$C$100) -> 413.77 | D8: =B8-C8 -> -163.77 | E8: =D8/B8 -> -0.65508
A9: Groceries | B9: 400 | C9: =sumif($B$20:$C$100,A9,$C$20:$C$100) -> 925.9 | D9: =B9-C9 -> -525.9 | E9: =D9/B9 -> -1.31475 | G9: Monthly Expenses
A10: Eating out | B10: 400 | C10: =sumif($B$20:$C$100,A10,$C$20:$C$100) -> 331.56 | D10: =B10-C10 -> 68.44 | E10: =D10/B10 -> 0.1711 | G10: Total Spent | H10: =sum(C16) -> 5549.63
A11: Household Goods | B11: 200 | C11: =sumif($B$20:$C$100,A11,$C$20:$C$100) -> 207.32 | D11: =B11-C11 -> -7.32 | E11: =D11/B11 -> -0.0366
A12: Travel Fund | B12: 500 | C12: 500 | D12: =B12-C12 -> 0 | E12: =D12/B12 -> 0 | G12: Recurring Expenses
A13: Gas | B13: 200 | C13: =sumif($B$20:$C$100,A13,$C$20:$C$100) -> 180.55 | D13: =B13-C13 -> 19.45 | E13: =D13/B13 -> 0.09725 | G13: Car Insurance
A14: Health | B14: 0 | D14: =B14-C14 -> 0 | E14: =D14/B14 -> #DIV/0!
A15: Fun / Misc | B15: 300 | C15: =sumif($B$20:$C$100,A15,$C$20:$C$100) -> 326.85 | D15: =B15-C15 -> -26.85 | E15: =D15/B15 -> -0.0895 | G15: Amount spent on Travel | H15: 0
A16: Total | B16: =SUM(B6:B15) -> 4750 | C16: =SUM(C6:C15) -> 5549.63 | D16: =SUM(D6:D15) -> -799.63 | E16: =D16/B16 -> -0.16834316 | G16: Amount in Travel Bank | H16: =500-SUMIF($B$20:$C$122,A12,$C$20:$C$122)+'July 2023 '!H15 -> 500
A19: Date | B19: Category | C19: Spent | D19: Note
A20: Monthly | B20: Fixed | C20: 2060 | D20: Rent
A21: Monthly | B21: Fixed | C21: 55 | D21: Internet
A22: Monthly | B22: Fixed | C22: 71.64 | D22: Electric
A23: Monthly | B23: Fixed | C23: 129.33 | D23: Exercise
A24: Monthly | B24: Fixed | C24: $9,86 | D24: Water
A25: Monthly | B25: Fixed | C25: =1133.34/6 -> 188.89 | D25: Car Insurance
A26: Monthly | B26: Fixed | C26: 2.87 | D26: Spotify - Martin
A27: Monthly | B27: Fixed | C27: 1.99 | D27: Google One
A28: Monthly | B28: Fixed | C28: 5.83 | D28: One Drive
A29: Monthly | B29: Fixed | C29: 148.13 | D29: Phone
A32: 45110 | B32: Bills | C32: 328.24 | D32: Car Registration
A33: 45110 | B33: Household Goods | C33: 90.28 | D33: Amazon Lamp
A34: 45110 | B34: Household Goods | C34: 2.89 | D34: phone case
A35: 45110 | B35: Gas | C35: 30 | D35: Rachel Gas
A36: 45110 | B36: Groceries | C36: 101.32 | D36: Costco
A37: 45110 | B37: Eating out | C37: 123.24 | D37: Kbbq with jiaqi
A38: 45109 | B38: Groceries | C38: 119.31 | D38: H mart
A39: 45108 | B39: Eating out | C39: 4.87 | D39: blk dog
A40: 45112 | B40: Fun / Misc | C40: 108 | D40: Gift for Martin's Mum
A41: 45115 | B41: Fun / Misc | C41: 103.97 | D41: Science Lab Donation
A42: 45115 | B42: Groceries | C42: 124.75 | D42: Costco
A43: 45115 | B43: Eating out | C43: 11.52 | D43: Costco food court
... A74: 45138 | B74: Eating out | C74: 17.4 | D74: Uber eats

Sheet Aug 2023
A4: Monthly Spending | G4: Monthly Overview | J4: Expenses over Time
A5: Category | B5: Budgeted | C5: Amount Spent | D5: Amount Remaining | E5: % Remaining | G5: Income
A6: Fixed | B6: 2663.68 | C6: =sumif($B$20:$C$122,A6,$C$20:$C$122) -> 2592.04 | D6: =B6-C6 -> 71.64 | E6: =D6/B6 -> 0.026895123 | G6: Martin Paycheck | H6: ='MartinRachel Pay Stub'!B20*2 -> 3851.86
A7: Utilities | B7: 0 | C7: =sumif($B$20:$C$122,A7,$C$20:$C$122) -> 0 | D7: =B7-C7 -> 0 | E7: =D7/B7 -> #DIV/0! | G7: Rachel Paycheck | H7: =2763*2 -> 5526
A8: Bills | B8: 250 | C8: =sumif($B$20:$C$122,A8,$C$20:$C$122) -> 86.59 | D8: =B8-C8 -> 163.41 | E8: =D8/B8 -> 0.65364
A9: Groceries | B9: 400 | C9: =sumif($B$20:$C$122,A9,$C$20:$C$122) -> 612.84 | D9: =B9-C9 -> -212.84 | E9: =D9/B9 -> -0.5321 | G9: Monthly Expenses
A10: Eating out | B10: 400 | C10: =sumif($B$20:$C$122,A10,$C$20:$C$122) -> 372.62 | D10: =B10-C10 -> 27.38 | E10: =D10/B10 -> 0.06845 | G10: Total Spent | H10: =sum(C16) -> 5352.45
A11: Household Goods | B11: 200 | C11: =sumif($B$20:$C$122,A11,$C$20:$C$122) -> 731.3 | D11: =B11-C11 -> -531.3 | E11: =D11/B11 -> -2.6565
A12: Travel | B12: 500 | C12: 500 | D12: =B12-C12 -> 0 | E12: =D12/B12 -> 0 | G12: Recurring Expenses
A13: Gas | B13: 200 | C13: =sumif($B$20:$C$122,A13,$C$20:$C$122) -> 126.23 | D13: =B13-C13 -> 73.77 | E13: =D13/B13 -> 0.36885 | G13: Car Insurance
A14: Health | B14: 0 | C14: =sumif($B$20:$C$122,A14,$C$20:$C$122) -> 23.85 | D14: =B14-C14 -> -23.85 | E14: =D14/B14 -> #DIV/0!
A15: Fun / Misc | B15: 300 | C15: =sumif($B$20:$C$122,A15,$C$20:$C$122) -> 306.98 | D15: =B15-C15 -> -6.98 | E15: =D15/B15 -> -0.023266667 | G15: Amount spent on Travel | H15: =SUMIF($B$20:$C$122,$A$12,$C$20:$C$122) -> 253.6
A16: Total | B16: =SUM(B6:B15) -> 4913.68 | C16: =SUM(C6:C15) -> 5352.45 | D16: =SUM(D6:D15) -> -438.77 | E16: =D16/B16 -> -0.089295599 | G16: Amount in Travel Bank | H16: =500-SUMIF($B$20:$C$122,A12,$C$20:$C$122)+'July 2023 '!H16 -> 746.4
A19: Date | B19: Category | C19: Spent | D19: Note
A20: Monthly | B20: Fixed | C20: 2060 | D20: Rent
A21: Monthly | B21: Fixed | C21: 55 | D21: Internet
A22: Monthly | B22: Fixed | C22: 0 | D22: Electric
A23: Monthly | B23: Fixed | C23: 129.33 | D23: Exercise
A24: Monthly | B24: Fixed | C24: $9,86 | D24: Water
A25: Monthly | B25: Fixed | C25: =1133.34/6 -> 188.89 | D25: Car Insurance
A26: Monthly | B26: Fixed | C26: 2.87 | D26: Spotify - Martin
A27: Monthly | B27: Fixed | C27: 1.99 | D27: Google One
A28: Monthly | B28: Fixed | C28: 5.83 | D28: One Drive
A29: Monthly | B29: Fixed | C29: 148.13 | D29: Phone
A32: 45139 | B32: Fun / Misc | C32: 60.62 | D32: Sephora
A33: 45139 | B33: Fun / Misc | C33: 27.04 | D33: Amazon makeup
A34: 45141 | B34: Gas | C34: 33.17 | D34: Gas
A35: 45141 | B35: Household Goods | C35: 70 | D35: Facecremas
A36: 45141 | B36: Groceries | C36: 123 | D36: Costco
A37: 45141 | B37: Health | C37: 10.87 | D37: Amazon
A38: 45142 | B38: Eating out | C38: 61.48 | D38: Truth BBQ
A39: 45143 | B39: Household Goods | C39: 155.87 | D39: WHBM -rsb
A40: 45143 | B40: Household Goods | C40: 119.06 | D40: Madewell - RSB
A41: 45143 | B41: Household Goods | C41: =214.89+96.34 -> 311.23 | D41: Club Monaco - RSB
A42: 45143 | B42: Eating out | C42: 16.72 | D42: Raising canes
A43: 45143 | B43: Fun / Misc | C43: 40.46 | D43: Gift for Eun & John
A44: 45144 | B44: Groceries | C44: 30.8 | D44: costco
A45: 45144 | B45: Groceries | C45: 82.01 | D45: central market
A46: 45147 | B46: Fun / Misc | C46: 10 | D46: Sprinkles cupcake
A47: 45147 | B47: Fun / Misc | C47: 44.19 | D47: Hatch Chiles
A48: 45149 | B48: Eating out | C48: 4.31 | D48: Costco Dogs
A49: 45149 | B49: Groceries | C49: 87.06 | D49: Costco
A50: 45149 | B50: Fun / Misc | C50: 75.72 | D50: Hatch Chiles
A51: 45150 | B51: Fun / Misc | C51: 26.95 | D51: Central Market
A52: 45151 | B52: Eating Out | C52: 1.32 | D52: Uber Eats
A53: 45152 | B53: Fun / Misc | C53: 6 | D53: Lottery
... A89: 45164 | B89: Groceries | C89: 18.49 | D89: WHoleFoods

Sheet Sept 2023
A4: Monthly Spending | G4: Monthly Overview | J4: Expenses over Time
A5: Category | B5: Budgeted | C5: Amount Spent | D5: Amount Remaining | E5: % Remaining | G5: Income
A6: Fixed | B6: 2663.68 | C6: =sumif($B$20:$C$101,A6,$C$20:$C$101) -> 2620.38 | D6: =B6-C6 -> 43.3 | E6: =D6/B6 -> 0.016255706 | G6: Martin Paycheck | H6: 3643
A7: Utilities | B7: 0 | C7: =sumif($B$20:$C$101,A7,$C$20:$C$101) -> 0 | D7: =B7-C7 -> 0 | E7: =D7/B7 -> #DIV/0! | G7: Rachel Paycheck | H7: =2763*2 -> 5526
A8: Bills | B8: 250 | C8: =sumif($B$20:$C$101,A8,$C$20:$C$101) -> 0 | D8: =B8-C8 -> 250 | E8: =D8/B8 -> 1
A9: Groceries | B9: 400 | C9: =sumif($B$20:$C$101,A9,$C$20:$C$101) -> 764.92 | D9: =B9-C9 -> -364.92 | E9: =D9/B9 -> -0.9123 | G9: Monthly Expenses
A10: Eating out | B10: 400 | C10: =sumif($B$20:$C$101,A10,$C$20:$C$101) -> 461.29 | D10: =B10-C10 -> -61.29 | E10: =D10/B10 -> -0.153225 | G10: Total Spent | H10: =sum(C16) -> 5661.46
A11: Household Goods | B11: 200 | C11: =sumif($B$20:$C$101,A11,$C$20:$C$101) -> 213.2 | D11: =B11-C11 -> -13.2 | E11: =D11/B11 -> -0.066
A12: Travel | B12: 500 | C12: 500 | D12: =B12-C12 -> 0 | E12: =D12/B12 -> 0 | G12: Recurring Expenses
A13: Gas | B13: 200 | C13: =sumif($B$20:$C$101,A13,$C$20:$C$101) -> 124.48 | D13: =B13-C13 -> 75.52 | E13: =D13/B13 -> 0.3776 | G13: Car Insurance
A14: Health | B14: 0 | C14: =sumif($B$20:$C$101,A14,$C$20:$C$101) -> 39.39 | D14: =B14-C14 -> -39.39 | E14: =D14/B14 -> #DIV/0!
A15: Fun / Misc | B15: 300 | C15: =sumif($B$20:$C$101,A15,$C$20:$C$101) -> 937.8 | D15: =B15-C15 -> -637.8 | E15: =D15/B15 -> -2.126 | G15: Amount spent on Travel | H15: =SUMIF($B$20:$C$123,$A$12,$C$20:$C$123) -> 20.6
A16: Total | B16: =SUM(B6:B15) -> 4913.68 | C16: =SUM(C6:C15) -> 5661.46 | D16: =SUM(D6:D15) -> -747.78 | E16: =D16/B16 -> -0.15218329 | G16: Amount in Travel Bank | H16: =500-SUMIF($B$20:$C$123,A12,$C$20:$C$123)+'Aug 2023'!H16 -> 1225.8
A19: Date | B19: Category | C19: Spent | D19: Note
A20: Monthly | B20: Fixed | C20: 2060 | D20: Rent
A21: Monthly | B21: Fixed | C21: 0 | D21: Internet
A22: Monthly | B22: Fixed | C22: 93.34 | D22: Electric
A23: Monthly | B23: Fixed | C23: 129.33 | D23: Exercise
A24: Monthly | B24: Fixed | C24: $9,86 | D24: Water
A25: Monthly | B25: Fixed | C25: =1133.34/6 -> 188.89 | D25: Car Insurance
A26: Monthly | B26: Fixed | C26: 2.87 | D26: Spotify - Martin
A27: Monthly | B27: Fixed | C27: 1.99 | D27: Google One
A28: Monthly | B28: Fixed | C28: 5.83 | D28: One Drive
A29: Monthly | B29: Fixed | C29: 138.13 | D29: Phone
A32: 45170 | B32: Eating out | C32: 72 | D32: Kim son
A33: 45170 | B33: Gas | C33: 45 | D33: Sam's club
A34: 45170 | B34: Eating out | C34: 5.9 | D34: Coffee
A35: 45171 | B35: Eating out | C35: $53,66 | D35: Aka Sushi
A36: 45171 | B36: Groceries | C36: 17.74 | D36: Hmart
A37: 45171 | B37: Eating Out | C37: 29.06 | D37: San Dong
A38: 45171 | B38: Groceries | C38: 8.71 | D38: HEB
A39: 45171 | B39: Eating out | C39: 9.34 | D39: Torchy's Tacos
A40: 45171 | B40: Eating out | C40: 5.68 | D40: Coco Crepes
A41: 45171 | B41: Fun / Misc | C41: 36 | D41: Birthday Cake
A42: 45171 | B42: Groceries | C42: 163.17 | D42: Costco
A43: 45171 | B43: Household Goods | C43: 21 | D43: Pillow
A44: 45172 | B44: Fun / Misc | C44: 127 | D44: rachel bday
A45: 45172 | B45: Household Goods | C45: 150 | D45: Kitchenaid
A46: 45174 | B46: Household Goods | C46: 19.99 | D46: Air Filter
A47: 45172 | B47: Eating out | C47: 24.9 | D47: Luna's
... A64: 45186 | B64: Groceries | C64: 123.37 | D64: Costco
A65: 45184 | B65: Eating out | C65: =59.22/2 -> 29.61 | D65: IWA ya
A66: 45183 | B66: Gas | C66: 46.89 | D66: Martin - Gas
A67: 45179 | B67: Groceries | C67: 51.09 | D67: HEB & Costco
A68: 45191 | B68: Health | C68: 7.99 | D68: Parking
A69: 45186 | B69: Groceries | C69: =24.83+4.31 -> 29.14 | D69: WHole foods
A70: 45192 | B70: Household Goods | C70: 22.21 | D70: Phone case & screen
A71: 45193 | B71: Groceries | C71: 24.56 | D71: HEB
A72: 45193 | B72: Groceries | C72: 182.39 | D72: Costco
A73: 45193 | B73: Gas | C73: 32.59 | D73: Costco
A74: 45199 | B74: Groceries | C74: 101.55 | D74: Hmart
A75: 45199 | B75: Eating out | C75: 37.89 | D75: Tacos | E75: `
A76: 45193 | B76: Groceries | C76: 14.42 | D76: Whole foods (9/24 and 27)
A77: 45194 | B77: Fun / Misc | C77: 160 | D77: Wedding Gift
A78: 45199 | B78: Travel | C78: 20.6 | D78: Travel mistake :(

Sheet Multiyear Plan
AI2: New Placeoff Option | AQ2: Quit Cutoff
H3: Month 1 | I3: Month 2 | J3: Month 3 | K3: Month 4 | L3: Month 5 | M3: Month 6 | N3: Month 7 | O3: Month 8 | P3: Month 9 | Q3: Month 10 | R3: Month 11 | S3: Month 12 | T3: Month 13 | U3: Month 14 | V3: Month 15 | W3: Month 16 | X3: Month 17 | Y3: Month 18 | Z3: Month 19 | AA3: Month 20 | AB3: Month 21 | AC3: Month 22 | AD3: Month 23 | AE3: Month 24 | AF3: Month 25 | AG3: Month 26 | AH3: Month 27 | AI3: Month 28 | AJ3: Month 29 | AK3: Month 30 | AL3: Month 31 | AM3: Month 32 | AN3: Month 33 | AO3: Month 34 | AP3: Month 35 | AQ3: Month 36
B4: 45323 | C4: 45352 | D4: 45383 | E4: 45413 | F4: 45444 | G4: 45474 | H4: 45505 | I4: 45536 | J4: 45566 | K4: 45597 | L4: 45627 | M4: 45658 | N4: 45689 | O4: 45717 | P4: 45748 | Q4: 45778 | R4: 45809 | S4: 45839 | T4: 45870 | U4: 45901 | V4: 45931 | W4: 45962 | X4: 45992 | Y4: 46023 | Z4: 46054 | AA4: 46082 | AB4: 46113 | AC4: 46143 | AD4: 46174 | AE4: 46204 | AF4: 46235 | AG4: 46266 | AH4: 46296 | AI4: 46327 | AJ4: 46357 | AK4: 46388 | AL4: 46419 | AM4: 46447 | AN4: 46478 | AO4: 46508 | AP4: 46539 | AQ4: 46569
A5: Rachel | C5: Rotation 2 Start | J5: R2 End | K5: Rotation 3 Start | R5: R3 End | S5: PO 1 | T5: PO2 | U5: PO 3 | V5: PO 4 | W5: PO 5 | X5: PO 6 | Y5: PO 7 | Z5: PO 8 | AA5: PO 9 | AB5: PO 10 | AC5: PO 11 | AD5: PO 12 | AE5: PO 13 | AF5: PO 14 | AG5: PO 15 | AH5: PO 16 | AI5: PO 17 | AJ5: PO 18 | AK5: PO 19 | AL5: PO 20 | AM5: PO 21 | AN5: PO 22 | AO5: PO 23 | AP5: PO 24 | AQ5: PO 25
A6: Rachel Location | C6: Houston | K6: NC | L6: NC | M6: NC | N6: NC | O6: NC | P6: NC | Q6: NC | R6: NC | S6: NC/Houston | T6: NC/Houston | U6: NC/Houston | V6: NC/Houston | W6: NC/Houston | X6: NC/Houston | Y6: NC/Houston | Z6: NC/Houston | AA6: NC/Houston | AB6: NC/Houston | AC6: NC/Houston | AD6: NC/Houston | AE6: NC/Houston | AF6: NC/Houston | AG6: NC/Houston | AH6: NC/Houston | AI6: NC/Houston | AJ6: NC/Houston | AK6: NC/Houston | AL6: NC/Houston | AM6: NC/Houston | AN6: NC/Houston | AO6: NC/Houston | AP6: NC/Houston
A7: Martin | H7: Business School Start | AE7: New Job Start
A8: Martin Location | C8: Houston | H8: Chicago / Boston / NY | AE8: NY/California/DC | AF8: NY/California/DC | AG8: NY/California/DC | AH8: NY/California/DC | AI8: NY/California/DC | AJ8: NY/California/DC | AK8: NY/California/DC | AL8: NY/California/DC | AM8: NY/California/DC | AN8: NY/California/DC | AO8: NY/California/DC | AP8: NY/California/DC | AQ8: NY/California/DC | AR8: NY/California/DC

Sheet Business School Fund
B7: Costs
B8: Category | C8: Amount (use all positive #s) | D8: Number of Times Billed | E8: Total Cost
B9: Tuition (total sticker amount across 2 years) | C9: 86550 | D9: 2 | E9: =C9*D9 -> 173100
B10: Booth Deposits & Fees Lost | C10: 3400 | D10: 1 | E10: =D10*C10 -> 3400
B11: Student Services Fee | C11: 406 | D11: 2 | E11: =C11*D11 -> 812
B12: Health Insurance | C12: 0 | E12: =C12*D12 -> 0
B13: Computer Allowance | C13: 1000 | D13: 1 | E13: =C13*D13 -> 1000
B14: Clothes | C14: 1000 | D14: 2 | E14: =C14*D14 -> 2000
B15: Clubs / Memberships | C15: 500 | D15: 2 | E15: =C15*D15 -> 1000
B16: Apartment rent/utilities | C16: 1668 | D16: 21 | E16: =C16*D16 -> 35028
B17: Groceries | C17: 400 | D17: 21 | E17: =C17*D17 -> 8400
B18: Transport | C18: 150 | D18: 21 | E18: =C18*D18 -> 3150
B19: Dining out | C19: 300 | D19: 21 | E19: =C19*D19 -> 6300
B20: Travel | C20: 3300 | D20: 6 | E20: =C20*D20 -> 19800
B21: Additional / miscellaneous | C21: 300 | D21: 21 | E21: =C21*D21 -> 6300
B22: Total | E22: =SUM(E8:E21) -> 260290
B29: Financing/Income | G29: Wei Wu Business School Option Fund | L29: Points Expenses | O29: Travel Expenses
B30: Category | C30: Total Available | D30: % Allocation | E30: Actual Allocation | G30: Date | H30: Amount Transferred | L30: 7500 | M30: Amex Points | O30: Amount | P30: Person | Q30: Date | R30: Type
B31: Funding from Mom | C31: 100000 | D31: 1 | E31: =D31*C31 -> 100000 | G31: July 4th | H31: 8500 | O31: 78 | P31: Rachel | Q31: Sept 2024 | R31: Flight
B32: Stocks / Investments - Schwab | C32: 73600 | D32: 0 | E32: =D32*C32 -> 0 | G32: 2024 Rent | H32: =2100*12 -> 25200 | O32: 72 | P32: Rachel | Q32: 45505 | R32: Flight
B33: Treasury MM Fund - VUSXX (Vanguard) | C33: 57000 | D33: 0.5 | E33: =D33*C33 -> 28500 | G33: June 6th | H33: 8500 | O33: 54 | P33: Rachel | Q33: 45566 | R33: Flight
B34: Treasury MM Fund - VUSXX (Chase) | C34: 72000 | D34: 1 | E34: =D34*C34 -> 72000 | G34: May | H34: 8500 | O34: 159 | P34: Martin | Q34: 45566 | R34: Flight | S34: Thanksgiving
B35: Crypto | C35: 16000 | D35: 0 | E35: =D35*C35 -> 0 | G35: April - Birthday | H35: 3000 | I35: Used for Booth Deposit | O35: 112 | P35: Rachel | Q35: 45566 | R35: Flight
B36: Rachel Income ($2k/Mo * 21) | C36: 42000 | D36: 1 | E36: =D36*C36 -> 42000 | G36: April | H36: 7000 | O36: 52 | P36: Rachel | Q36: 45566 | R36: Flight
B37: Internship Salary | C37: 15000 | D37: 1 | E37: =D37*C37 -> 15000 | G37: August | H37: 8000
B38: Total | C38: =SUM(C31:C37) -> 375600 | E38: =SUM(E31:E37) -> 257500 | P38: Rachel Uber
B39: Delta to make up | E39: =E22-E38 -> 2790 | P39: 60 | Q39: Sept 2024
P40: 60 | Q40: Sept 2024
B41: Business School Expenses | C41: Amount | D41: Within Monthly Budget?
B42: Booth Deposit | C42: 3000 | D42: Yes
B43: MIT Deposit | C43: 3500 | D43: No
B44: Random Walk Deposit | C44: 300 | D44: No
B45: Re Vera | C45: 100 | D45: No
B46: Apartment Application Fee | C46: 125 | D46: No
B47: Textbook - Discrete Math | C47: 24.81 | D47: No
B48: Rent (Aug - End of Jan) | C48: 8000 | D48: Yes
B49: Prefunction Trip | C49: 370
B50: Club Dues | C50: 285

Sheet Oct 2023
A4: Monthly Spending | G4: Monthly Overview | J4: Expenses over Time
A5: Category | B5: Budgeted | C5: Amount Spent | D5: Amount Remaining | E5: % Remaining | G5: Income
A6: Fixed | B6: 2663.68 | C6: =sumif($B$20:$C$123,A6,$C$20:$C$123) -> 2693.71 | D6: =B6-C6 -> -30.03 | E6: =D6/B6 -> -0.011273877 | G6: Martin Paycheck | H6: 4950
A7: Utilities | B7: 0 | C7: =sumif($B$20:$C$123,A7,$C$20:$C$123) -> 0 | D7: =B7-C7 -> 0 | E7: =D7/B7 -> #DIV/0! | G7: Rachel Paycheck | H7: ='MartinRachel Pay Stub'!L21 -> 5526
A8: Bills | B8: 250 | C8: =sumif($B$20:$C$123,A8,$C$20:$C$123) -> 0 | D8: =B8-C8 -> 250 | E8: =D8/B8 -> 1
A9: Groceries | B9: 400 | C9: =sumif($B$20:$C$123,A9,$C$20:$C$123) -> 627.85 | D9: =B9-C9 -> -227.85 | E9: =D9/B9 -> -0.569625 | G9: Monthly Expenses
A10: Eating out | B10: 400 | C10: =sumif($B$20:$C$123,A10,$C$20:$C$123) -> 556.37 | D10: =B10-C10 -> -156.37 | E10: =D10/B10 -> -0.390925 | G10: Total Spent | H10: =sum(C16) -> 6435.75
A11: Household Goods | B11: 200 | C11: =sumif($B$20:$C$123,A11,$C$20:$C$123) -> 100 | D11: =B11-C11 -> 100 | E11: =D11/B11 -> 0.5
A12: Travel Fund | B12: 500 | C12: 500 | D12: =B12-C12 -> 0 | E12: =D12/B12 -> 0 | G12: Recurring Expenses
A13: Gas | B13: 200 | C13: =sumif($B$20:$C$123,A13,$C$20:$C$123) -> 298.27 | D13: =B13-C13 -> -98.27 | E13: =D13/B13 -> -0.49135 | G13: Car Insurance
A14: Health | B14: 0 | C14: =sumif($B$20:$C$123,A14,$C$20:$C$123) -> 137 | D14: =B14-C14 -> -137 | E14: =D14/B14 -> #DIV/0!
A15: Fun / Misc | B15: 300 | C15: =sumif($B$20:$C$123,A15,$C$20:$C$123) -> 1522.55 | D15: =B15-C15 -> -1222.55 | E15: =D15/B15 -> -4.0751667 | G15: Amount spent on Travel | H15: =SUMIF($B$20:$C$145,"Travel",$C$20:$C$145) -> 1066.1
A16: Total | B16: =SUM(B6:B15) -> 4913.68 | C16: =SUM(C6:C15) -> 6435.75 | D16: =SUM(D6:D15) -> -1522.07 | E16: =D16/B16 -> -0.30976173 | G16: Amount in Travel Bank | H16: =500-SUMIF($B$20:$C$145,"Travel",$C$20:$C$145)+'Sept 2023'!H16 -> 659.7
A19: Date | B19: Category | C19: Spent | D19: Note
A20: Monthly | B20: Fixed | C20: 2060 | D20: Rent
A21: Monthly | B21: Fixed | C21: 35 | D21: Internet
A22: Monthly | B22: Fixed | C22: 96 | D22: Electric
A23: Monthly | B23: Fixed | C23: 155 | D23: Exercise
A24: Monthly | B24: Fixed | C24: $9,86 | D24: Water
A25: Monthly | B25: Fixed | C25: =1133.34/6 -> 188.89 | D25: Car Insurance
A26: Monthly | B26: Fixed | C26: 2.87 | D26: Spotify - Martin
A27: Monthly | B27: Fixed | C27: 1.99 | D27: Google One
A28: Monthly | B28: Fixed | C28: 5.83 | D28: One Drive
A29: Monthly | B29: Fixed | C29: 148.13 | D29: Phone
A32: 45218 | B32: Travel | C32: 108 | D32: IAH to RDU - RBL
A33: 45200 | B33: Gas | C33: 39.88 | D33: Costco
A34: 45200 | B34: Groceries | C34: 152 | D34: Costco
A35: 45200 | B35: Household Goods | C35: 100 | D35: Costco - air purifier
A36: 45205 | B36: Eating out | C36: 70 | D36: Maht gaek
A37: 45206 | B37: Fun / Misc | C37: 12 | D37: DART - round trip
A38: 45206 | B38: Fun / Misc | C38: =80+52 -> 132 | D38: State fair
A39: 45206 | B39: Eating out | C39: 30 | D39: Gopchangstory
A40: 45206 | B40: Eating out | C40: 32 | D40: Korean fried chicken
A41: 45206 | B41: Gas | C41: 52 | D41: Gas
A42: 45207 | B42: Gas | C42: 40.09 | D42: Costco gas
A43: 45207 | B43: Groceries | C43: 173.88 | D43: Costco
A44: 45206 | B44: Fun / Misc | C44: 3 | D44: Valet
A45: 45207 | B45: Eating out | C45: 14.7 | D45: Taco Bell
A46: 45207 | B46: Eating out | C46: 11.02 | D46: Wendys
A47: 45207 | B47: Groceries | C47: 15 | D47: Heb
A48: 45209 | B48: Fun / Misc | C48: 312 | D48: Skinceuticals
A49: 45210 | B49: Fun / Misc | C49: 60 | D49: Nintendo Switch
A50: 45211 | B50: Fun / Misc | C50: 28.5 | D50: Parking Spot
... A63: 45226 | B63: Eating out | C63: 11.35 | D63: Freebirds
A64: 45221 | B64: Fun / Misc | C64: $6,38 | D64: Bucee
A65: 45221 | B65: Gas | C65: 42.65 | D65: Bucees
A66: 45220 | B66: Eating out | C66: 11.38 | D66: 45118
A67: 45220 | B67: Eating out | C67: 49 | D67: Rainforest Cafe
A68: 45220 | B68: Eating out | C68: 20.02 | D68: Juiceland
A69: 45226 | B69: Groceries | C69: 58.22 | D69: Costco
A70: 45218 | B70: Gas | C70: 46.68 | D70: Gas - martin
A71: 45218 | B71: Groceries | C71: 10.49 | D71: costco
A72: 45202 | B72: Eating out | C72: 9.41 | D72: citiline
A73: 45205 | B73: Health | C73: 108 | D73: dentist
A74: 45210 | B74: Eating out | C74: 15.42 | D74: Lunch - rachel
A75: 45226 | B75: Fun / Misc | C75: =551+138 -> 689 | D75: Vegas trip - martin
A76: 45220 | B76: Eating out | C76: 70 | D76: BBQ
A77: 45221 | B77: Eating out | C77: 70 | D77: 1618 (Austin)
A78: 45227 | B78: Eating Out | C78: 2 | D78: Donut
A79: 45227 | B79: Eating out | C79: 61.03 | D79: Mala
A80: 45227 | B80: Fun / Misc | C80: 220.47 | D80: Korean Ginseng
A81: 45227 | B81: Fun / Misc | C81: 6.99 | D81: Gregmat
A82: 45227 | B82: Fun / Misc | C82: 2.04 | D82: Vocab App
A83: 45228 | B83: Groceries | C83: 64.62 | D83: 99 ranch
A84: 45228 | B84: Groceries | C84: 141.64 | D84: Costco
A85: 45228 | B85: Gas | C85: 34.51 | D85: Gas - martin
A86: 45229 | B86: Gas | C86: 42.46 | D86: Gas - Martin
A87: 10/30/ | B87: Fun / Misc | C87: 16.18 | D87: Audible
G102: martin | H102: Logan | I102: Howard | J102: Matt | K102: Greg
G103: 21.674 | H103: =20*1.0837 -> 21.674 | I103: =19*1.0837 -> 20.5903 | J103: =20*1.0837 -> 21.674 | L103: The Henry breakfast | M103: 85.62
G104: =73.81/5 -> 14.762 | H104: =G104 -> 14.762 | I104: =H104 -> 14.762 | J104: =I104 -> 14.762 | K104: =J104 -> 14.762 | L104: Groceries | M104: =K104*5 -> 73.81
G105: 14.51 | H105: =M105/5 -> 14.51 | J105: =H105 -> 14.51 | K105: =H105 -> 14.51 | L105: Liquor | M105: 72.55
G106: 104.1 | H106: =M106/5 -> 104.108 | J106: =H106 -> 104.108 | K106: =H106 -> 104.108 | L106: Bacchanal | M106: 520.54
G107: 40.61 | H107: =M107/5 -> 40.61 | J107: =H107 -> 40.61 | K107: =H107 -> 40.61 | L107: Fantasy | M107: 203.05
G108: =H108-280 -> 138.7275 | H108: =M108/8 -> 418.7275 | J108: =H108 -> 418.7275 | K108: =H108 -> 418.7275 | L108: Hotel | M108: =1674.91*2 -> 3349.82
G109: 204 | H109: =M109/5 -> 204.4 | J109: =H109 -> 204.4 | K109: =H109 -> 204.4 | L109: Yellowtail | M109: 1022
G110: 13 | H110: =M110/4 -> 13.25 | J110: -10 | K110: =H110 -> 13.25 | L110: Photbook | M110: 53
G111: 63.55 | H111: 63.55 | J111: 63.55 | K111: =H111 -> 63.55 | L111: Ka | M111: 317.75
G112: 75 | H112: =SUM(H103:H111) -> 895.5915 | J112: =SUM(J103:J111) -> 872.3415 | K112: =Sum(K104:K111) -> 873.9175

Sheet Nov 2023
A4: Monthly Spending | G4: Monthly Overview | J4: Expenses over Time
A5: Category | B5: Budgeted | C5: Amount Spent | D5: Amount Remaining | E5: % Remaining | G5: Income
A6: Fixed | B6: 2663.68 | C6: =sumif($B$20:$C$148,A6,$C$20:$C$148) -> 2710.12 | D6: =B6-C6 -> -46.44 | E6: =D6/B6 -> -0.017434527 | G6: Martin Paycheck | H6: =2716+2463+5018 -> 10197
A7: Utilities | B7: 0 | C7: =sumif($B$20:$C$148,A7,$C$20:$C$148) -> 0 | D7: =B7-C7 -> 0 | E7: =D7/B7 -> #DIV/0! | G7: Rachel Paycheck | H7: 5307
A8: Bills | B8: 250 | C8: =sumif($B$20:$C$148,A8,$C$20:$C$148) -> 0 | D8: =B8-C8 -> 250 | E8: =D8/B8 -> 1
A9: Groceries | B9: 400 | C9: =sumif($B$20:$C$148,A9,$C$20:$C$148) -> 265.24 | D9: =B9-C9 -> 134.76 | E9: =D9/B9 -> 0.3369 | G9: Monthly Expenses
A10: Eating out | B10: 400 | C10: =sumif($B$20:$C$148,A10,$C$20:$C$148) -> 2642.64 | D10: =B10-C10 -> -2242.64 | E10: =D10/B10 -> -5.6066 | G10: Total Spent | H10: =sum(C16) -> 10830.42
A11: Household Goods | B11: 200 | C11: =sumif($B$20:$C$148,A11,$C$20:$C$148) -> 902.51 | D11: =B11-C11 -> -702.51 | E11: =D11/B11 -> -3.51255
A12: Travel | B12: 500 | C12: 500 | D12: =B12-C12 -> 0 | E12: =D12/B12 -> 0 | G12: Recurring Expenses
A13: Gas | B13: 200 | C13: =sumif($B$20:$C$148,A13,$C$20:$C$148) -> 79.78 | D13: =B13-C13 -> 120.22 | E13: =D13/B13 -> 0.6011 | G13: Car Insurance
A14: Health | B14: 0 | C14: =sumif($B$20:$C$148,A14,$C$20:$C$148) -> 61 | D14: =B14-C14 -> -61 | E14: =D14/B14 -> #DIV/0!
A15: Fun / Misc | B15: 300 | C15: =sumif($B$20:$C$148,A15,$C$20:$C$148) -> 3669.13 | D15: =B15-C15 -> -3369.13 | E15: =D15/B15 -> -11.230433 | G15: Amount spent on Travel | H15: =SUMIF($B$20:$C$170,"Travel",$C$20:$C$170) -> 1774.04
A16: Total | B16: =SUM(B6:B15) -> 4913.68 | C16: =SUM(C6:C15) -> 10830.42 | D16: =SUM(D6:D15) -> -5916.74 | E16: =D16/B16 -> -1.2041362 | G16: Amount in Travel Bank | H16: =500-SUMIF($B$20:$C$170,"Travel",$C$20:$C$170)+'Oct 2023'!H16 -> -614.34
A19: Date | B19: Category | C19: Spent | D19: Note
A20: Monthly | B20: Fixed | C20: 2060 | D20: Rent
A21: Monthly | B21: Fixed | C21: 55 | D21: Internet
A22: Monthly | B22: Fixed | C22: 81.55 | D22: Electric
A23: Monthly | B23: Fixed | C23: 156 | D23: Exercise
A24: Monthly | B24: Fixed | C24: 9.86 | D24: Water
A25: Monthly | B25: Fixed | C25: =1133.34/6 -> 188.89 | D25: Car Insurance
A26: Monthly | B26: Fixed | C26: 2.87 | D26: Spotify - Martin
A27: Monthly | B27: Fixed | C27: 1.99 | D27: Google One
A28: Monthly | B28: Fixed | C28: 5.83 | D28: One Drive
A29: Monthly | B29: Fixed | C29: 148.13 | D29: Phone
A32: 45232 | B32: Travel | C32: =8.9*2+53.78+123.78+191.61 -> 386.97 | D32: Vegas FLight & Hotel
A33: 45241 | B33: Fun / Misc | C33: 89 | D33: Verizon Stuff
A34: 45247 | B34: Travel | C34: =542.5*2 -> 1085 | D34: Maldives
A35: 45236 | B35: Eating out | C35: 20.42 | D35: Lunch in Vegas
A36: 45239 | B36: Eating Out | C36: 9.73 | D36: Rachel Lunch
A37: 45247 | B37: Gas | C37: 11.68 | D37: Rachel Gas
A38: 45233 | B38: Eating Out | C38: 23.38 | D38: Panda Express
A39: 45235 | B39: Fun / Misc | C39: 1.5 | D39: parking
A40: 45235 | B40: Eating out | C40: 32 | D40: Travel Insurance
A41: 45250 | B41: Groceries | C41: 10.87 | D41: Great Wall Groceries
A42: 45251 | B42: Eating out | C42: 60.44 | D42: Mein
A43: 45252 | B43: Fun / Misc | C43: 54.54 | D43: Louve Tix
A44: 45253 | B44: Fun / Misc | C44: 160 | D44: GRE
A45: 45254 | B45: Groceries | C45: 34.98 | D45: HMart Groceries
A46: 45255 | B46: Eating out | C46: 45.08 | D46: Local Foods
... A54: 45237 | B54: Eating out | C54: 15.17 | D54: Cosmo Lunch
A55: 45238 | B55: Eating out | C55: =52.75 -> 52.75 | D55: Alcohol
A56: 45239 | B56: Eating out | C56: 207 | D56: Caesar's
A57: 45240 | B57: Eating out | C57: 5.09 | D57: Water
A58: 45241 | B58: Eating out | C58: 36.31 | D58: Eggslut
A59: 45249 | B59: Fun / Misc | C59: 8.65 | D59: Nintendo Subscription
A60: 45248 | B60: Gas | C60: 40.85 | D60: Martin Gas
A61: 45248 | B61: Eating out | C61: 18.25 | D61: 85 Degree Bakery
A62: 45249 | B62: Gas | C62: 27.25 | D62: Rachel gas
A63: 45237 | B63: Eating out | C63: 62.62 | D63: Bamboo House
A64: 45241 | B64: Groceries | C64: $175,74 | D64: Costco
A65: 45249 | B65: Groceries | C65: 75.35 | D65: Groceries
A66: 45242 | B66: Groceries | C66: 35.18 | D66: Whole foods
A67: 45244 | B67: Household Goods | C67: 34 | D67: Amazon Stuff
A68: 45249 | B68: Travel | C68: 206 | D68: Travel Insurance
A69: 45249 | B69: Fun / Misc | C69: 17 | D69: Sim card
A70: 45253 | B70: Fun / Misc | C70: 8.11 | D70: Audible
A71: 45250 | B71: Groceries | C71: 6.35 | D71: whole foods
A72: 45250 | B72: Fun / Misc | C72: 8.1 | D72: amazon Stuff
A73: 45251 | B73: Groceries | C73: 24.35 | D73: whole foods
A74: 45252 | B74: Travel | C74: 96.07 | D74: Baggage fees
A75: 45253 | B75: Eating out | C75: =IFERROR(__xludf.DUMMYFUNCTION("G75*-1"),73.0) -> 73 | D75: Bamboo House | G75: -73
A76: 45260 | B76: Fun / Misc | C76: =IFERROR(__xludf.DUMMYFUNCTION("G76*-1"),37.82) -> 37.82 | D76: RATP | G76: -37.82
A77: 45259 | B77: Eating out | C77: =IFERROR(__xludf.DUMMYFUNCTION("G77*-1"),23.21) -> 23.21 | D77: MCDONALDS 549 2402927 | G77: -23.21
A78: 45259 | B78: Eating out | C78: =IFERROR(__xludf.DUMMYFUNCTION("G78*-1"),559.01) -> 559.01 | D78: REST PHOENIX | G78: -559.01
A79: 45259 | B79: Eating out | C79: =IFERROR(__xludf.DUMMYFUNCTION("G79*-1"),59.19) -> 59.19 | D79: JFPM GLOBAL | G79: -59.19
A80: 45258 | B80: Fun / Misc | C80: =IFERROR(__xludf.DUMMYFUNCTION("G80*-1"),0.99) -> 0.99 | D80: APPLE.COM/BILL | G80: -0.99
A81: 45257 | B81: Fun / Misc | C81: =IFERROR(__xludf.DUMMYFUNCTION("G81*-1"),23.0) -> 23 | D81: BASILIQUE S C 4528229 | G81: -23
A82: 45257 | B82: Eating out | C82: =IFERROR(__xludf.DUMMYFUNCTION("G82*-1"),45.33) -> 45.33 | D82: TAVERNE DE ZHAO | G82: -45.33
A83: 45257 | B83: Household Goods | C83: =IFERROR(__xludf.DUMMYFUNCTION("G83*-1"),147.83) -> 147.83 | D83: PHARMACIE BADER 2038241 | G83: -147.83
A84: 45257 | B84: Eating out | C84: =IFERROR(__xludf.DUMMYFUNCTION("G84*-1"),31.97) -> 31.97 | D84: SC-GRENIER PAIN | G84: -31.97
A85: 45256 | B85: Household Goods | C85: =IFERROR(__xludf.DUMMYFUNCTION("G85*-1"),64.94) -> 64.94 | D85: CAUDALIE 775108 | G85: -64.94
A86: 45256 | B86: Fun / Misc | C86: =IFERROR(__xludf.DUMMYFUNCTION("G86*-1"),13.3) -> 13.3 | D86: SNCF | G86: -13.3
A87: 45256 | B87: Eating out | C87: =IFERROR(__xludf.DUMMYFUNCTION("G87*-1"),50.37) -> 50.37 | D87: SARL VIE | G87: -50.37
A88: 45256 | B88: Household Goods | C88: =IFERROR(__xludf.DUMMYFUNCTION("G88*-1"),17.49) -> 17.49 | D88: FRAGONARD OPERA | G88: -17.49
A89: 45256 | B89: Fun / Misc | C89: =IFERROR(__xludf.DUMMYFUNCTION("G89*-1"),13.3) -> 13.3 | D89: SNCF | G89: -13.3
A90: 45256 | B90: Household Goods | C90: =IFERROR(__xludf.DUMMYFUNCTION("G90*-1"),562.63) -> 562.63 | D90: PHARMACIE BADER 2038241 | G90: -562.63
A91: 45256 | B91: Fun / Misc | C91: =IFERROR(__xludf.DUMMYFUNCTION("G91*-1"),2667.72) -> 2667.72 | D91: Hotel du Louvre | G91: -2667.72
A92: 45254 | B92: Fun / Misc | C92: =IFERROR(__xludf.DUMMYFUNCTION("G92*-1"),61.94) -> 61.94 | D92: RATP | G92: -61.94
A93: 45253 | B93: Fun / Misc | C93: =IFERROR(__xludf.DUMMYFUNCTION("G93*-1"),37.67) -> 37.67 | D93: SNCF | G93: -37.67
A94: 45253 | B94: Fun / Misc | C94: =IFERROR(__xludf.DUMMYFUNCTION("G94*-1"),34.38) -> 34.38 | D94: RATP | G94: -34.38
A95: 45253 | B95: Eating out | C95: =IFERROR(__xludf.DUMMYFUNCTION("G95*-1"),53.08) -> 53.08 | D95: COM | G95: -53.08
A96: 45258 | B96: Fun / Misc | C96: 61.2 | D96: phone case gift
A97: 45260 | B97: Health | C97: 61 | D97: Dentist
A98: 45260 | B98: Eating out | C98: 16.66 | D98: AplPay CHICK-FIL-A #HOUSTON TX
A99: 45259 | B99: Eating out | C99: 29.16 | D99: GASTRONOMIE /CONFIS.TREMBLAY EN FRANCEFR
A100: 45258 | B100: Household Goods | C100: 75.62 | D100: ACABA PARIS
A101: 45258 | B101: Fun / Misc | C101: 56.22 | D101: PIERRE HERM OP RA PARIS
A102: 45257 | B102: Eating out | C102: 93.82 | D102: GALERIES LAFAYETTE GPARIS FR
A103: 45257 | B103: Eating out | C103: 85.39 | D103: RST BRONGNIART PARIS FR
A104: 45255 | B104: Fun / Misc | C104: 4.94 | D104: DELL INC ROUND ROCK TX
A105: 45255 | B105: Fun / Misc | C105: 131.36 | D105: DUCASSE VERSAILLE VERSAILLES FR
A106: 45254 | B106: Fun / Misc | C106: 1.07 | D106: AplPay NEWEGG TEXAS CITY OF INDUS CA
A107: 45254 | B107: Eating out | C107: 99.49 | D107: CHICOREE PARIS
... A113: 45250 | B113: Fun / Misc | C113: 12.75 | D113: AplPay AIRALO SINGAPORE SG

Sheet Dec 2023
A4: Monthly Spending | G4: Monthly Overview | J4: Expenses over Time
A5: Category | B5: Budgeted | C5: Amount Spent | D5: Amount Remaining | E5: % Remaining | G5: Income
A6: Fixed | B6: 2663.68 | C6: =sumif($B$20:$C$127,A6,$C$20:$C$127) -> 2710.12 | D6: =B6-C6 -> -46.44 | E6: =D6/B6 -> -0.017434527 | G6: Martin Paycheck | H6: ='MartinRachel Pay Stub'!B20*2 -> 3851.86
A7: Utilities | B7: 0 | C7: =sumif($B$20:$C$127,A7,$C$20:$C$127) -> 0 | D7: =B7-C7 -> 0 | E7: =D7/B7 -> #DIV/0! | G7: Rachel Paycheck | H7: ='MartinRachel Pay Stub'!E20*2 -> 5429.1
A8: Bills | B8: 250 | C8: =sumif($B$20:$C$127,A8,$C$20:$C$127) -> 0 | D8: =B8-C8 -> 250 | E8: =D8/B8 -> 1
A9: Groceries | B9: 400 | C9: =sumif($B$20:$C$127,A9,$C$20:$C$127) -> 802.61 | D9: =B9-C9 -> -402.61 | E9: =D9/B9 -> -1.006525 | G9: Monthly Expenses
A10: Eating out | B10: 400 | C10: =sumif($B$20:$C$127,A10,$C$20:$C$127) -> 843.17 | D10: =B10-C10 -> -443.17 | E10: =D10/B10 -> -1.107925 | G10: Total Spent | H10: =sum(C16) -> 7536.32
A11: Household Goods | B11: 200 | C11: =sumif($B$20:$C$127,A11,$C$20:$C$127) -> 488.22 | D11: =B11-C11 -> -288.22 | E11: =D11/B11 -> -1.4411
A12: Travel | B12: 500 | C12: 500 | D12: =B12-C12 -> 0 | E12: =D12/B12 -> 0 | G12: Recurring Expenses
A13: Gas | B13: 200 | C13: =sumif($B$20:$C$127,A13,$C$20:$C$127) -> 42.68 | D13: =B13-C13 -> 157.32 | E13: =D13/B13 -> 0.7866 | G13: Car Insurance
A14: Health | B14: 0 | C14: =sumif($B$20:$C$127,A14,$C$20:$C$127) -> 14.45 | D14: =B14-C14 -> -14.45 | E14: =D14/B14 -> #DIV/0!
A15: Fun / Misc | B15: 300 | C15: =sumif($B$20:$C$127,A15,$C$20:$C$127) -> 2135.07 | D15: =B15-C15 -> -1835.07 | E15: =D15/B15 -> -6.1169 | G15: Amount spent on Travel | H15: =SUMIF($B$20:$C$149,"Travel",$C$20:$C$149) -> 21
A16: Total | B16: =SUM(B6:B15) -> 4913.68 | C16: =SUM(C6:C15) -> 7536.32 | D16: =SUM(D6:D15) -> -2622.64 | E16: =D16/B16 -> -0.53374253 | G16: Amount in Travel Bank | H16: =500-SUMIF($B$20:$C$149,"Travel",$C$20:$C$149)+'Nov 2023'!H16 -> -135.34
A19: Date | B19: Category | C19: Spent | D19: Note
A20: Monthly | B20: Fixed | C20: 2060 | D20: Rent
A21: Monthly | B21: Fixed | C21: 55 | D21: Internet
A22: Monthly | B22: Fixed | C22: 81.55 | D22: Electric
A23: Monthly | B23: Fixed | C23: 156 | D23: Exercise
A24: Monthly | B24: Fixed | C24: 9.86 | D24: Water
A25: Monthly | B25: Fixed | C25: =1133.34/6 -> 188.89 | D25: Car Insurance
A26: Monthly | B26: Fixed | C26: 2.87 | D26: Spotify - Martin
A27: Monthly | B27: Fixed | C27: 1.99 | D27: Google One
A28: Monthly | B28: Fixed | C28: 5.83 | D28: One Drive
A29: Monthly | B29: Fixed | C29: 148.13 | D29: Phone
A32: 45270 | B32: Groceries | C32: 145.69 | D32: Costco
A33: 45262 | B33: Groceries | C33: 183.25 | D33: Costco
A34: 45268 | B34: Fun / Misc | C34: 8.55 | D34: PIrate Ship
A35: 45262 | B35: Groceries | C35: 30.55 | D35: Hmart
A36: 45270 | B36: Fun / Misc | C36: 113.68 | D36: Go-karting
A37: 45269 | B37: Fun / Misc | C37: 19.37 | D37: Book
A38: 45268 | B38: Eating out | C38: 24.01 | D38: Raising Canes
A39: 45269 | B39: Eating out | C39: 40.86 | D39: Dimsum
A40: 45270 | B40: Eating out | C40: 18 | D40: Tacos
A41: 45270 | B41: Fun / Misc | C41: 1923.7 | D41: Family Trip
A42: 45270 | B42: Fun / Misc | D42: Boat Rental
A43: 45262 | B43: Eating out | C43: =25.95*2/3 -> 17.3 | D43: Roostar
A44: 45268 | B44: Household Goods | C44: 207 | D44: Adidas
A45: 45266 | B45: Health | C45: 14.45 | D45: Mucinex
A46: 45262 | B46: Eating out | C46: =65-18 -> 47 | D46: Wings + pizza
A47: 45262 | B47: Household Goods | C47: -25 | D47: leather jackets
A48: 45653 | B48: Household Goods | C48: 22.56 | D48: Mom's iphone
A49: 45653 | B49: Household Goods | C49: 8 | D49: Audible
A50: 45647 | B50: Household Goods | C50: 12.97 | D50: Josh Blanket
A51: 45637 | B51: Groceries | C51: 17.42 | D51: Whole Foods
A52: 45651 | B52: Household Goods | C52: 48.6 | D52: Casetify
A53: 45645 | B53: Household Goods | C53: 30 | D53: Universal
A54: 45644 | B54: Eating out | C54: 25 | D54: Pho
A55: 45643 | B55: Eating out | C55: 8.66 | D55: T-shirt
A56: 45643 | B56: Eating out | C56: 2.16 | D56: Domino's
A57: 45641 | B57: Household Goods | C57: 120.07 | D57: J.crew
A58: 45641 | B58: Groceries | C58: 68.42 | D58: Costco
... A80: 45290 | B80: Groceries | C80: 91 | D80: Hmart

Sheet Jan 2024
A4: Monthly Spending | G4: Monthly Overview | J4: Expenses over Time
A5: Category | B5: Budgeted | C5: Amount Spent | D5: Amount Remaining | E5: % Remaining | G5: Income
A6: Fixed | B6: 2663.68 | C6: =sumif($B$20:$C$100,A6,$C$20:$C$100) -> 2660.12 | D6: =B6-C6 -> 3.56 | E6: =D6/B6 -> 0.0013364969 | G6: Martin Paycheck | H6: =1473*2 -> 2946
A7: Utilities | B7: 0 | C7: =sumif($B$20:$C$100,A7,$C$20:$C$100) -> 0 | D7: =B7-C7 -> 0 | E7: =D7/B7 -> #DIV/0! | G7: Rachel Paycheck | H7: ='MartinRachel Pay Stub'!E20*2 -> 5429.1
A8: Bills | B8: 250 | C8: =sumif($B$20:$C$100,A8,$C$20:$C$100) -> 1991.45 | D8: =B8-C8 -> -1741.45 | E8: =D8/B8 -> -6.9658
A9: Groceries | B9: 400 | C9: =sumif($B$20:$C$100,A9,$C$20:$C$100) -> 650.42 | D9: =B9-C9 -> -250.42 | E9: =D9/B9 -> -0.62605 | G9: Monthly Expenses
A10: Eating out | B10: 400 | C10: =sumif($B$20:$C$100,A10,$C$20:$C$100) -> 390.16 | D10: =B10-C10 -> 9.84 | E10: =D10/B10 -> 0.0246 | G10: Total Spent | H10: =sum(C16) -> 7230.99
A11: Household Goods | B11: 200 | C11: =sumif($B$20:$C$100,A11,$C$20:$C$100) -> 597.65 | D11: =B11-C11 -> -397.65 | E11: =D11/B11 -> -1.98825
A12: Travel | B12: 500 | C12: 500 | D12: =B12-C12 -> 0 | E12: =D12/B12 -> 0 | G12: Recurring Expenses
A13: Gas | B13: 200 | C13: =sumif($B$20:$C$100,A13,$C$20:$C$100) -> 64.19 | D13: =B13-C13 -> 135.81 | E13: =D13/B13 -> 0.67905 | G13: Car Insurance
A14: Health | B14: 0 | C14: =sumif($B$20:$C$100,A14,$C$20:$C$100) -> 112 | D14: =B14-C14 -> -112 | E14: =D14/B14 -> #DIV/0!
A15: Fun / Misc | B15: 300 | C15: =sumif($B$20:$C$100,A15,$C$20:$C$100) -> 265 | D15: =B15-C15 -> 35 | E15: =D15/B15 -> 0.11666667 | G15: Amount spent on Travel | H15: =SUMIF($B$20:$C$122,"Travel",$C$20:$C$122) -> 440
A16: Total | B16: =SUM(B6:B15) -> 4913.68 | C16: =SUM(C6:C15) -> 7230.99 | D16: =SUM(D6:D15) -> -2317.31 | E16: =D16/B16 -> -0.47160377 | G16: Amount in Travel Bank | H16: =500-SUMIF($B$20:$C$122,"Travel",$C$20:$C$122)+'Dec 2023'!H16 -> -75.34
A19: Date | B19: Category | C19: Spent | D19: Note
A20: Monthly | B20: Fixed | C20: 2060 | D20: Rent
A21: Monthly | B21: Fixed | C21: 5 | D21: Internet
A22: Monthly | B22: Fixed | C22: 81.55 | D22: Electric
A23: Monthly | B23: Fixed | C23: 156 | D23: Exercise
A24: Monthly | B24: Fixed | C24: 9.86 | D24: Water
A25: Monthly | B25: Fixed | C25: =1133.34/6 -> 188.89 | D25: Car Insurance
A26: Monthly | B26: Fixed | C26: 2.87 | D26: Spotify - Martin
A27: Monthly | B27: Fixed | C27: 1.99 | D27: Google One
A28: Monthly | B28: Fixed | C28: 5.83 | D28: One Drive
A29: Monthly | B29: Fixed | C29: 148.13 | D29: Phone
A32: 45304 | B32: Household Goods | C32: 295 | D32: Jcrew
A33: 45304 | B33: Household Goods | C33: 0 | D33: Jcrew - Caml Hair
A34: 45293 | B34: Eating out | C34: 9.73 | D34: Citiline
A35: 45298 | B35: Groceries | C35: 14.5 | D35: WF
A36: 45298 | B36: Groceries | C36: 31.51 | D36: HEB
A37: 45300 | B37: Bills | C37: 5.95 | D37: Parking
A38: 45297 | B38: Eating out | C38: 17.3 | D38: Domion's
A39: 45295 | B39: Gas | C39: 22.3 | D39: Rachel Gas
A40: 45295 | B40: Groceries | C40: 171.37 | D40: Costco
A41: 45295 | B41: Eating out | C41: 7.37 | D41: Costco
A42: 45294 | B42: Fun / Misc | C42: 5 | D42: Parking Drop off
A43: 45294 | B43: Fun / Misc | C43: 55 | D43: Rockets Tickets
... A74: 45318 | B74: Groceries | C74: 4 | D74: whole foods
A75: 45319 | B75: Fun / Misc

Sheet Feb 2024
A4: Monthly Spending | G4: Monthly Overview | J4: Expenses over Time
A5: Category | B5: Budgeted | C5: Amount Spent | D5: Amount Remaining | E5: % Remaining | G5: Income
A6: Fixed | B6: 2663.68 | C6: =sumif($B$20:$C$103,A6,$C$20:$C$103) -> 2732.67 | D6: =B6-C6 -> -68.99 | E6: =D6/B6 -> -0.025900258 | G6: Martin Paycheck | H6: =1881+2005 -> 3886
A7: Utilities | B7: 0 | C7: =sumif($B$20:$C$103,A7,$C$20:$C$103) -> 0 | D7: =B7-C7 -> 0 | E7: =D7/B7 -> #DIV/0! | G7: Rachel Paycheck | H7: 4400
A8: Bills | B8: 250 | C8: =sumif($B$20:$C$103,A8,$C$20:$C$103) -> 658.62 | D8: =B8-C8 -> -408.62 | E8: =D8/B8 -> -1.63448 | G8: Total | H8: =SUM(H6:H7) -> 8286
A9: Groceries | B9: 400 | C9: =sumif($B$20:$C$103,A9,$C$20:$C$103) -> 344.74 | D9: =B9-C9 -> 55.26 | E9: =D9/B9 -> 0.13815
A10: Eating out | B10: 400 | C10: =sumif($B$20:$C$103,A10,$C$20:$C$103) -> 456.54 | D10: =B10-C10 -> -56.54 | E10: =D10/B10 -> -0.14135 | G10: Monthly Expenses
A11: Household Goods | B11: 200 | C11: =sumif($B$20:$C$103,A11,$C$20:$C$103) -> 16.35 | D11: =B11-C11 -> 183.65 | E11: =D11/B11 -> 0.91825 | G11: Total Spent | H11: =sum(C16) -> 6377.04
A12: Travel | B12: 500 | C12: 500 | D12: =B12-C12 -> 0 | E12: =D12/B12 -> 0
A13: Gas | B13: 200 | C13: =sumif($B$20:$C$103,A13,$C$20:$C$103) -> 101.47 | D13: =B13-C13 -> 98.53 | E13: =D13/B13 -> 0.49265 | G13: Recurring Expenses
A14: Health | B14: 0 | C14: =sumif($B$20:$C$103,A14,$C$20:$C$103) -> 480 | D14: =B14-C14 -> -480 | E14: =D14/B14 -> #DIV/0! | G14: Car Insurance
A15: Fun / Misc | B15: 300 | C15: =sumif($B$20:$C$103,A15,$C$20:$C$103) -> 1086.65 | D15: =B15-C15 -> -786.65 | E15: =D15/B15 -> -2.6221667
A16: Total | B16: =SUM(B6:B15) -> 4913.68 | C16: =SUM(C6:C15) -> 6377.04 | D16: =SUM(D6:D15) -> -1463.36 | E16: =D16/B16 -> -0.29781345 | G16: Amount spent on Travel | H16: =SUMIF($B$20:$C$125,"Travel",$C$20:$C$125) -> 274.2
G17: Amount in Travel Bank | H17: =500-SUMIF($B$20:$C$125,"Travel",$C$20:$C$125)+'Jan 2024'!H16 -> 150.46
A19: Date | B19: Category | C19: Spent | D19: Note
A20: Monthly | B20: Fixed | C20: 2060 | D20: Rent
A21: Monthly | B21: Fixed | C21: 55 | D21: Internet
A22: Monthly | B22: Fixed | C22: 97.85 | D22: Electric
A23: Monthly | B23: Fixed | C23: 156 | D23: Exercise
A24: Monthly | B24: Fixed | C24: 9.86 | D24: Water
A25: Monthly | B25: Fixed | C25: =1133.34/6 -> 188.89 | D25: Car Insurance
A26: Monthly | B26: Fixed | C26: 2.87 | D26: Spotify - Martin
A27: Monthly | B27: Fixed | C27: 1.99 | D27: Google One
A28: Monthly | B28: Fixed | C28: 5.83 | D28: One Drive
A29: Monthly | B29: Fixed | C29: 6.25 | D29: MSFT
A30: Monthly | B30: Fixed | C30: 148.13 | D30: Phone
A33: 45337 | B33: Bills | C33: 48 | D33: Airport Parking
A34: 45327 | B34: Eating out | C34: 22 | D34: Chipotle
A35: 45337 | B35: Bills | C35: 551 | D35: Flight to RDU - Duke Interview
B36: Eating out | C36: 24.9 | D36: LUNA PIZZERIA - KIRBY
B37: Travel | C37: 40 | D37: AAA H GALLERIA-R
B38: Eating out | C38: 3.25 | D38: Dinner Parking
B39: Groceries | C39: 123 | D39: COSTCO WHSE #1018
B40: Groceries | C40: 20.52 | D40: H-E-B #630
B41: Eating out | C41: 24.32 | D41: TST* BURGER JOINT MONTROS
B42: Gas | C42: 39.37 | D42: Gas - Martin
B43: Fun / Misc | C43: 184.01 | D43: Valentines Gift
B44: Travel | C44: 36.78 | D44: Passport Photos
B45: Travel | C45: 143 | D45: Costco
B46: Fun / Misc | C46: =93.65*2/3 -> 62.433333 | D46: Italy Tickets
B47: Fun / Misc | C47: =64.57*2/3 -> 43.046667 | D47: Italy Tickets
B48: Fun / Misc | C48: 395.11 | D48: Earrings
B49: Gas | C49: 29.84 | D49: Gas - Rachel
B50: Fun / Misc | C50: 21.65 | D50: Toyota Center
B51: Fun / Misc | C51: 62 | D51: Bombas
B52: Health | C52: 480 | D52: Rachel Contacts
B53: Eating out | C53: 8.11 | D53: Whataburger
B54: Bills | C54: 16.62 | D54: Duke Visit Misc Expenses
B55: Groceries | C55: 74 | D55: Whole Foods
B56: Groceries | C56: 8 | D56: HEB
B57: Bills | C57: 43 | D57: Oil Change
B58: Fun / Misc | C58: 5.75 | D58: Parking
B59: Groceries | C59: 4.49 | D59: WF
... B64: Fun / Misc | C64: 60 | D64: Hair Product
A65: 45342 | B65: Groceries | C65: 16.02 | D65: whole foods
A66: 45339 | B66: Eating out | C66: 8.05 | D66: chickfila
B67: Eating out | C67: 30.44 | D67: giordanos deep dish
A68: 45342 | B68: Fun / Misc | C68: 58 | D68: chicago ubers
A69: 45343 | B69: Eating out | C69: 17.89 | D69: pho
B70: Groceries | C70: 30.57 | D70: costco
A71: 45351 | B71: Eating out | C71: 19 | D71: rodeo - food
B72: Travel | C72: 44.46 | D72: airport lyft
B73: Eating out | C73: 153 | D73: crawfish cafe
B74: Eating out | C74: 13.02 | D74: moge tea
B75: Fun / Misc | C75: 75 | D75: microsoft store
B76: Groceries | C76: 33 | D76: costco
B77: Fun / Misc | C77: 25 | D77: college board
B78: Household Goods | C78: 16.35 | D78: walgreens
B79: Eating out | C79: 21.69 | D79: shangs noodles
B80: Eating out | C80: 36 | D80: airport food
B81: Groceries | C81: 25.2 | D81: HEB
B82: Gas | C82: 32.26 | D82: gas
B83: Groceries | C83: 9.94 | D83: HEB
... B85: Travel | C85: 9.96 | D85: uber

Sheet March 2024
A4: Monthly Spending | G4: Monthly Overview | J4: Expenses over Time
A5: Category | B5: Budgeted | C5: Amount Spent | D5: Amount Remaining | E5: % Remaining | G5: Income
A6: Fixed | B6: 2663.68 | C6: =sumif($B$20:$C$102,A6,$C$20:$C$102) -> 4184.1967 | D6: =B6-C6 -> -1520.5167 | E6: =D6/B6 -> -0.57083308 | G6: Martin Paycheck | H6: =2002*2 -> 4004
A7: Utilities | B7: 0 | C7: =sumif($B$20:$C$102,A7,$C$20:$C$102) -> 0 | D7: =B7-C7 -> 0 | E7: =D7/B7 -> #DIV/0! | G7: Rachel Paycheck | H7: =2024+805+2035 -> 4864
A8: Bills | B8: 250 | C8: =sumif($B$20:$C$102,A8,$C$20:$C$102) -> 66 | D8: =B8-C8 -> 184 | E8: =D8/B8 -> 0.736 | G8: Total | H8: =SUM(H6:H7) -> 8868
A9: Groceries | B9: 400 | C9: =sumif($B$20:$C$102,A9,$C$20:$C$102) -> 244.79 | D9: =B9-C9 -> 155.21 | E9: =D9/B9 -> 0.388025
A10: Eating out | B10: 400 | C10: =sumif($B$20:$C$102,A10,$C$20:$C$102) -> 520.56 | D10: =B10-C10 -> -120.56 | E10: =D10/B10 -> -0.3014 | G10: Monthly Expenses
A11: Household Goods | B11: 200 | C11: =sumif($B$20:$C$102,A11,$C$20:$C$102) -> 1369.11 | D11: =B11-C11 -> -1169.11 | E11: =D11/B11 -> -5.84555 | G11: Total Spent | H11: =sum(C16) -> 9041.8767
A12: Travel | B12: 500 | C12: 500 | D12: =B12-C12 -> 0 | E12: =D12/B12 -> 0
A13: Gas | B13: 200 | C13: =sumif($B$20:$C$102,A13,$C$20:$C$102) -> 390.02 | D13: =B13-C13 -> -190.02 | E13: =D13/B13 -> -0.9501 | G13: Recurring Expenses
A14: Health | B14: 0 | C14: =sumif($B$20:$C$102,A14,$C$20:$C$102) -> 0 | D14: =B14-C14 -> 0 | E14: =D14/B14 -> #DIV/0! | G14: Car Insurance
A15: Fun / Misc | B15: 300 | C15: =sumif($B$20:$C$102,A15,$C$20:$C$102) -> 1767.2 | D15: =B15-C15 -> -1467.2 | E15: =D15/B15 -> -4.8906667
A16: Total | B16: =SUM(B6:B15) -> 4913.68 | C16: =SUM(C6:C15) -> 9041.8767 | D16: =SUM(D6:D15) -> -4128.1967 | E16: =D16/B16 -> -0.84014357 | G16: Amount spent on Travel | H16: =SUMIF($B$20:$C$124,"Travel",$C$20:$C$124) -> 469.18
G17: Amount in Travel Bank | H17: =500-SUMIF($B$20:$C$124,"Travel",$C$20:$C$124)+'Feb 2024'!H17 -> 181.28
A19: Date | B19: Category | C19: Spent | D19: Note
A20: Monthly | B20: Fixed | C20: =3720 -> 3720 | D20: Rent
A21: Monthly | B21: Fixed | C21: 40 | D21: Internet
A22: Monthly | B22: Fixed | C22: 97.85 | D22: Electric
A23: Monthly | B23: Fixed | D23: Exercise
A24: Monthly | B24: Fixed | C24: 9.86 | D24: Water
A25: Monthly | B25: Fixed | C25: =77/12 -> 6.4166667 | D25: Renters insurance
A26: Monthly | B26: Fixed | C26: 144 | D26: Car Insurance
A27: Monthly | B27: Fixed | C27: 2.87 | D27: Spotify - Martin
A28: Monthly | B28: Fixed | C28: 2.99 | D28: Google One
A29: Monthly | B29: Fixed | C29: 5.83 | D29: One Drive
A30: Monthly | B30: Fixed | C30: 6.25 | D30: MSFT
A31: Monthly | B31: Fixed | C31: 148.13 | D31: Phone
A34: 45363 | B34: Groceries | C34: 18.78 | D34: whole foods
A35: 45368 | B35: Household Goods | C35: 19.61 | D35: amazon
A36: 45367 | B36: Household Goods | C36: 35.51 | D36: amazon
A37: 45370 | B37: Groceries | C37: 55.01 | D37: gin and tonic
A38: 45360 | B38: Fun / Misc | C38: 172.66 | D38: glass gifts
A39: 45362 | B39: Fun / Misc | C39: 5.75 | D39: office parking
B40: Travel | C40: 247.78 | D40: italy train tickets
B41: Eating out | C41: 28.01 | D41: burger joint
B42: Eating out | C42: 67.07 | D42: cooking girl
B43: Eating out | C43: 35.75 | D43: travel meals
B44: Fun / Misc | C44: 27.79 | D44: sim cards
B45: Fun / Misc | C45: 800 | D45: italy pt 1
B46: Fun / Misc | C46: 380 | D46: italy p2
B47: Eating out | C47: 30 | D47: premoving misc
B48: Gas | C48: 38 | D48: airport uber
B49: Fun / Misc | C49: 30 | D49: movies
B50: Gas | C50: 16 | D50: uber
B51: Fun / Misc | C51: 45 | D51: haircut
... B72: Eating out | C72: 11.27 | D72: Taco Bell
A73: 45375 | B73: Eating out | C73: 60 | D73: Sankalp
A74: 45376 | B74: Household Goods | C74: 5 | D74: Plunger
B75: Bills | C75: 66 | D75: Electric Bill
B76: Groceries | C76: -100 | D76: Costco Refund
B77: Household Goods | C77: 6 | D77: Walmart
B78: Groceries | C78: 271 | D78: Costco
B80: Eating out | C80: 7 | D80: Costco
B81: Eating out | C81: 12.66 | D81: Taco Bell
B82: Eating out | C82: 14.73 | D82: Beer
B83: Travel | C83: 54.8 | D83: Gas - MD Trip
B84: Eating out | C84: 28 | D84: Ekiben
B85: Eating out | C85: 4.71 | D85: Bagerls
B86: Household Goods | C86: 6.99 | D86: CVS
B87: Eating out | C87: 65 | D87: Bakery
... B91: Eating out | C91: 8.48 | D91: Wendeez Nuts

Sheet April 2024
A4: Monthly Spending | G4: Monthly Overview | J4: Expenses over Time
A5: Category | B5: Budgeted | C5: Amount Spent | D5: Amount Remaining | E5: % Remaining | G5: Income
A6: Fixed | B6: 2663.68 | C6: =sumif($B$20:$C$102,A6,$C$20:$C$102) -> 3387.9767 | D6: =B6-C6 -> -724.29667 | E6: =D6/B6 -> -0.2719158 | G6: Martin Paycheck | H6: 5000
A7: Utilities | B7: 0 | C7: =sumif($B$20:$C$102,A7,$C$20:$C$102) -> 0 | D7: =B7-C7 -> 0 | E7: =D7/B7 -> #DIV/0! | G7: Rachel Paycheck | H7: 4200
A8: Bills | B8: 250 | C8: =sumif($B$20:$C$102,A8,$C$20:$C$102) -> 2110.47 | D8: =B8-C8 -> -1860.47 | E8: =D8/B8 -> -7.44188 | G8: Total | H8: =SUM(H6:H7) -> 9200
A9: Groceries | B9: 400 | C9: =sumif($B$20:$C$102,A9,$C$20:$C$102) -> 1097.74 | D9: =B9-C9 -> -697.74 | E9: =D9/B9 -> -1.74435
A10: Eating out | B10: 400 | C10: =sumif($B$20:$C$102,A10,$C$20:$C$102) -> 431.61 | D10: =B10-C10 -> -31.61 | E10: =D10/B10 -> -0.079025 | G10: Monthly Expenses
A11: Household Goods | B11: 200 | C11: =sumif($B$20:$C$102,A11,$C$20:$C$102) -> 511.78 | D11: =B11-C11 -> -311.78 | E11: =D11/B11 -> -1.5589 | G11: Total Spent | H11: =sum(C17) -> 13059.367
A12: Travel | B12: 500 | C12: 500 | D12: =B12-C12 -> 0 | E12: =D12/B12 -> 0
A13: Gas | B13: 200 | C13: =sumif($B$20:$C$102,A13,$C$20:$C$102) -> 44.74 | D13: =B13-C13 -> 155.26 | E13: =D13/B13 -> 0.7763 | G13: Recurring Expenses
A14: Health | B14: 0 | C14: =sumif($B$20:$C$102,A14,$C$20:$C$102) -> 380.69 | D14: =B14-C14 -> -380.69 | E14: =D14/B14 -> #DIV/0! | G14: Car Insurance
A15: Fun / Misc | B15: 300 | C15: =sumif($B$20:$C$102,A15,$C$20:$C$102) -> 215.36 | D15: =B15-C15 -> 84.64 | E15: =D15/B15 -> 0.28213333
A16: Business School | B16: 0 | C16: =sumif($B$20:$C$102,A16,$C$20:$C$102) -> 4379 | D16: =B16-C16 -> -4379 | E16: =D16/B16 -> #DIV/0! | G16: Amount spent on Travel | H16: =SUMIF($B$20:$C$124,"Travel",$C$20:$C$124) -> 178.04
A17: Total | B17: =SUM(B6:B16) -> 4913.68 | C17: =SUM(C6:C16) -> 13059.367 | D17: =SUM(D6:D15) -> -3766.6867 | E17: =D17/B17 -> -0.76657142 | G17: Amount in Travel Bank | H17: =500-SUMIF($B$20:$C$124,"Travel",$C$20:$C$124)+'March 2024'!H17 -> 503.24
A19: Date | B19: Category | C19: Spent | D19: Note
A20: Monthly | B20: Fixed | C20: 2900 | D20: Rent
A21: Monthly | B21: Fixed | C21: 40 | D21: Internet
A22: Monthly | B22: Fixed | C22: 40 | D22: Electric
A23: Monthly | B23: Fixed | C23: 42.62 | D23: Exercise
A24: Monthly | B24: Fixed | C24: 87 | D24: Gas
A25: Monthly | B25: Fixed | C25: =77/12 -> 6.4166667 | D25: Renters insurance
A26: Monthly | B26: Fixed | C26: 144 | D26: Car Insurance
A27: Monthly | B27: Fixed | C27: 2.87 | D27: Spotify - Martin
A28: Monthly | B28: Fixed | C28: 2.99 | D28: Google One
A29: Monthly | B29: Fixed | C29: 5.83 | D29: One Drive
A30: Monthly | B30: Fixed | C30: 6.25 | D30: MSFT
A31: Monthly | B31: Fixed | C31: 110 | D31: Phone
A34: 45384 | B34: Health | C34: 40.69 | D34: Theraband
B35: Fun / Misc | C35: 75 | D35: Josh Present
B36: Eating out | C36: 33.25 | D36: Bakery
B37: Groceries | C37: 161.45 | D37: Asia Grocery Store
B38: Household Goods | C38: 121.28 | D38: Dry Cleaning
B39: Bills | C39: 7.64 | D39: Rhythm
B40: Groceries | C40: 143.93 | D40: Costco
B41: Groceries | C41: 180.58 | D41: Costco
B42: Groceries | C42: -12.8 | D42: Costco Refund
B43: Groceries | C43: 6.92 | D43: Costco
B44: Groceries | C44: -160 | D44: Costco
B45: Eating out | C45: 276 | D45: Lingo
B46: Fun / Misc | C46: 8.61 | D46: NY Uber
B47: Fun / Misc | C47: =2.9*15 -> 43.5 | D47: NY Trist
B48: Fun / Misc | C48: 56 | D48: NJ Transit
B49: Eating out | C49: 6.52 | D49: Hot doggo
B50: Household Goods | C50: 41.42 | D50: Candle
B51: Groceries | C51: 19.64 | D51: Wegmans
B52: Fun / Misc | C52: 9 | D52: Uber
B53: Eating out | C53: 20 | D53: ihop
B54: Groceries | C54: 276.58 | D54: Costco
B55: Groceries | C55: 4.8 | D55: Costco
B56: Fun / Misc | C56: 1.5 | D56: Parking
B57: Health | C57: 340 | D57: Shoes
B58: Household Goods | C58: 44.41 | D58: Caudalie
B59: Bills | C59: 15.99 | D59: Taxes
... B92: Eating out | C92: 19.56 | D92: Hangry Joes

Sheet May 2024
A4: Monthly Spending | G4: Monthly Overview | J4: Expenses over Time
A5: Category | B5: Budgeted | C5: Amount Spent | D5: Amount Remaining | E5: % Remaining | G5: Income
A6: Fixed | B6: 2663.68 | C6: =sumif($B$20:$C$101,A6,$C$20:$C$101) -> 3397.9767 | D6: =B6-C6 -> -734.29667 | E6: =D6/B6 -> -0.27567 | G6: Martin Paycheck | H6: =3223+2061 -> 5284
A7: Utilities | B7: 0 | C7: =sumif($B$20:$C$101,A7,$C$20:$C$101) -> 0 | D7: =B7-C7 -> 0 | E7: =D7/B7 -> #DIV/0! | G7: Rachel Paycheck | H7: =3370*2 -> 6740
A8: Bills | B8: 250 | C8: =sumif($B$20:$C$101,A8,$C$20:$C$101) -> 404.6 | D8: =B8-C8 -> -154.6 | E8: =D8/B8 -> -0.6184 | G8: Total | H8: =SUM(H6:H7) -> 12024
A9: Groceries | B9: 400 | C9: =sumif($B$20:$C$101,A9,$C$20:$C$101) -> 407.21 | D9: =B9-C9 -> -7.21 | E9: =D9/B9 -> -0.018025
A10: Eating out | B10: 400 | C10: =sumif($B$20:$C$101,A10,$C$20:$C$101) -> 392.61 | D10: =B10-C10 -> 7.39 | E10: =D10/B10 -> 0.018475 | G10: Monthly Expenses
A11: Household Goods | B11: 200 | C11: =sumif($B$20:$C$101,A11,$C$20:$C$101) -> 68.85 | D11: =B11-C11 -> 131.15 | E11: =D11/B11 -> 0.65575 | G11: Total Spent | H11: =sum(C17) -> 6570.3467
A12: Travel | B12: 500 | C12: 500 | D12: =B12-C12 -> 0 | E12: =D12/B12 -> 0
A13: Gas | B13: 200 | C13: =sumif($B$20:$C$101,A13,$C$20:$C$101) -> 110.11 | D13: =B13-C13 -> 89.89 | E13: =D13/B13 -> 0.44945 | G13: Recurring Expenses
A14: Health | B14: 0 | C14: =sumif($B$20:$C$101,A14,$C$20:$C$101) -> 15.64 | D14: =B14-C14 -> -15.64 | E14: =D14/B14 -> #DIV/0! | G14: Car Insurance
A15: Fun / Misc | B15: 300 | C15: =sumif($B$20:$C$101,A15,$C$20:$C$101) -> 1066.14 | D15: =B15-C15 -> -766.14 | E15: =D15/B15 -> -2.5538
A16: Business School | B16: 0 | C16: =sumif($B$20:$C$101,A16,$C$20:$C$101) -> 207.21 | D16: =B16-C16 -> -207.21 | E16: =D16/B16 -> #DIV/0! | G16: Amount spent on Travel | H16: =SUMIF($B$20:$C$123,"Travel",$C$20:$C$123) -> 643.79
A17: Total | B17: =SUM(B6:B16) -> 4913.68 | C17: =SUM(C6:C16) -> 6570.3467 | D17: =SUM(D6:D15) -> -1449.4567 | E17: =D17/B17 -> -0.29498394 | G17: Amount in Travel Bank | H17: =500-SUMIF($B$20:$C$123,"Travel",$C$20:$C$123)+'April 2024'!H17 -> 359.45
A19: Date | B19: Category | C19: Spent | D19: Note
A20: Monthly | B20: Fixed | C20: 2900 | D20: Rent
A21: Monthly | B21: Fixed | C21: 40 | D21: Internet
A22: Monthly | B22: Fixed | C22: 50 | D22: Electric
A23: Monthly | B23: Fixed | C23: 42.62 | D23: Exercise
A24: Monthly | B24: Fixed | C24: 87 | D24: Gas
A25: Monthly | B25: Fixed | C25: =77/12 -> 6.4166667 | D25: Renters insurance
A26: Monthly | B26: Fixed | C26: 144 | D26: Car Insurance
A27: Monthly | B27: Fixed | C27: 2.87 | D27: Spotify - Martin
A28: Monthly | B28: Fixed | C28: 2.99 | D28: Google One
A29: Monthly | B29: Fixed | C29: 5.83 | D29: One Drive
A30: Monthly | B30: Fixed | C30: 6.25 | D30: MSFT
A31: Monthly | B31: Fixed | C31: 110 | D31: Phone
A34: 45433 | B34: Eating out | C34: 8.68 | D34: BASF Lunch
A35: 45416 | B35: Fun / Misc | C35: =4*2.9+2.9*2 -> 17.4 | D35: MTA
A36: 45416 | B36: Fun / Misc | C36: 12.24 | D36: Walmart
A37: 45416 | B37: Fun / Misc | C37: 7.7 | D37: Morristown Parking
A38: 45416 | B38: Eating out | C38: 101 | D38: Samwoojang Korean Lunch
A39: 45417 | B39: Eating out | C39: 21.26 | D39: Tiki Chick
A40: 45417 | B40: Groceries | C40: 56.12 | D40: Kan Mam
A41: 45417 | B41: Groceries | C41: 96.74 | D41: Costco
A43: 45420 | B43: Travel | C43: 24 | D43: Airalo-Esim
A44: 45421 | B44: Eating out | C44: 13.41 | D44: Deez nuts
A45: 45421 | B45: Eating out | C45: 4 | D45: EWR Water
A46: 45421 | B46: Fun / Misc | C46: 324 | D46: Costa Rica ATM Pull
A47: 45421 | B47: Groceries | C47: 3.48 | D47: Costco
A48: 45421 | B48: Travel | C48: 258 | D48: Car Rental - CR
... A68: 45433 | B68: Fun / Misc | C68: 52.15 | D68: Lyft
A69: 45436 | B69: Bills | C69: =131.3*2 -> 262.6 | D69: Car Registration | F69: Amazon Filters | G69: 36.3
A70: 45436 | B70: Eating out | C70: 10.66 | D70: Mcds
A71: 45437 | B71: Household Goods | C71: 68.85 | D71: Wedding Gift - Registry
A72: 45439 | B72: Fun / Misc | C72: 12.12 | D72: Uber
A73: 45439 | B73: Eating out | C73: 21.15 | D73: Uber eats
A74: 45439 | B74: Travel | C74: 116 | D74: Flight to RDU
A75: 45441 | B75: Bills | C75: 130 | D75: Passport Renewal
A76: 45427 | B76: Fun / Misc | C76: 8.65 | D76: Nintendo
A77: 45418 | B77: Eating out | C77: 20.93 | D77: Tiki Chick
A78: 45417 | B78: Fun / Misc | C78: 56 | D78: Ticket to city
A79: 45417 | B79: Eating out | C79: 5.25 | D79: Levain Bakery
A80: 45441 | B80: Eating out | C80: 15.17 | D80: BASF Lunch
A81: 45440 | B81: Groceries | C81: 92.11 | D81: Costco
... A93: 45432 | B93: Business School | C93: 77.21 | D93: MPP App Fee

Sheet June 2024
A4: Monthly Spending | G4: Monthly Overview | J4: Expenses over Time
A5: Category | B5: Budgeted | C5: Amount Spent | D5: Amount Remaining | E5: % Remaining | G5: Income
A6: Fixed | B6: 2663.68 | C6: =sumif($B$20:$C$101,A6,$C$20:$C$101) -> 3432.9767 | D6: =B6-C6 -> -769.29667 | E6: =D6/B6 -> -0.28880972 | G6: Martin Paycheck | H6: =3061+3061 -> 6122
A7: Utilities | B7: 0 | C7: =sumif($B$20:$C$101,A7,$C$20:$C$101) -> 0 | D7: =B7-C7 -> 0 | E7: =D7/B7 -> #DIV/0! | G7: Rachel Paycheck | H7: =3410+3395 -> 6805
A8: Bills | B8: 250 | C8: =sumif($B$20:$C$101,A8,$C$20:$C$101) -> 0 | D8: =B8-C8 -> 250 | E8: =D8/B8 -> 1 | G8: Total | H8: =SUM(H6:H7) -> 12927
A9: Groceries | B9: 400 | C9: =sumif($B$20:$C$101,A9,$C$20:$C$101) -> 658.35 | D9: =B9-C9 -> -258.35 | E9: =D9/B9 -> -0.645875
A10: Eating out | B10: 400 | C10: =sumif($B$20:$C$101,A10,$C$20:$C$101) -> 746.7 | D10: =B10-C10 -> -346.7 | E10: =D10/B10 -> -0.86675 | G10: Monthly Expenses
A11: Household Goods | B11: 200 | C11: =sumif($B$20:$C$101,A11,$C$20:$C$101) -> 213.67 | D11: =B11-C11 -> -13.67 | E11: =D11/B11 -> -0.06835 | G11: Total Spent | H11: =sum(C17) -> 8363.7167
A12: Travel | B12: 500 | C12: 500 | D12: =B12-C12 -> 0 | E12: =D12/B12 -> 0
A13: Gas | B13: 200 | C13: =sumif($B$20:$C$101,A13,$C$20:$C$101) -> 60 | D13: =B13-C13 -> 140 | E13: =D13/B13 -> 0.7 | G13: Recurring Expenses
A14: Health | B14: 0 | C14: =sumif($B$20:$C$101,A14,$C$20:$C$101) -> 0 | D14: =B14-C14 -> 0 | E14: =D14/B14 -> #DIV/0! | G14: Car Insurance
A15: Fun / Misc | B15: 300 | C15: =sumif($B$20:$C$101,A15,$C$20:$C$101) -> 2752.02 | D15: =B15-C15 -> -2452.02 | E15: =D15/B15 -> -8.1734
A16: Business School | B16: 0 | C16: =sumif($B$20:$C$101,A16,$C$20:$C$101) -> 0 | D16: =B16-C16 -> 0 | E16: =D16/B16 -> #DIV/0! | G16: Amount spent on Travel | H16: =SUMIF($B$20:$C$123,"Travel",$C$20:$C$123) -> 0
A17: Total | B17: =SUM(B6:B16) -> 4913.68 | C17: =SUM(C6:C16) -> 8363.7167 | D17: =SUM(D6:D15) -> -3450.0367 | E17: =D17/B17 -> -0.70212889 | G17: Amount in Travel Bank | H17: =500-SUMIF($B$20:$C$123,"Travel",$C$20:$C$123)+'May 2024'!H17 -> 859.45
A19: Date | B19: Category | C19: Spent | D19: Note
A20: Monthly | B20: Fixed | C20: 2900 | D20: Rent
A21: Monthly | B21: Fixed | C21: 40 | D21: Internet
A22: Monthly | B22: Fixed | C22: 85 | D22: Electric
A23: Monthly | B23: Fixed | C23: 42.62 | D23: Exercise
A24: Monthly | B24: Fixed | C24: 87 | D24: Gas
A25: Monthly | B25: Fixed | C25: =77/12 -> 6.4166667 | D25: Renters insurance
A26: Monthly | B26: Fixed | C26: 144 | D26: Car Insurance
A27: Monthly | B27: Fixed | C27: 2.87 | D27: Spotify - Martin
A28: Monthly | B28: Fixed | C28: 2.99 | D28: Google One
A29: Monthly | B29: Fixed | C29: 5.83 | D29: One Drive
A30: Monthly | B30: Fixed | C30: 6.25 | D30: MSFT
A31: Monthly | B31: Fixed | C31: 110 | D31: Phone
A34: 45444 | B34: Fun / Misc | C34: 56 | D34: Train to NY
A35: 45444 | B35: Fun / Misc | C35: 995 | D35: Hamilton Tickets
A36: 45445 | B36: Fun / Misc | C36: 14.7 | D36: Morristown Station Parking
A37: 45468 | B37: Fun / Misc | C37: 826 | D37: Croissant Bag
A38: 45472 | B38: Groceries | C38: 46.82 | D38: HMART
A39: 45473 | B39: Fun / Misc | C39: =196-28 -> 168 | D39: Train to NY
A40: 45473 | B40: Eating out | C40: 3.4 | D40: Mackyd
A41: 45470 | B41: Eating out | C41: 8.02 | D41: Coffee and Bagel
A42: 45445 | B42: Fun / Misc | C42: =8*2.9 -> 23.2 | D42: Subway
A43: 45445 | B43: Household Goods | C43: 111.32 | D43: J-Crew
A44: 45445 | B44: Household Goods | C44: 18.36 | D44: JCREW
A45: 45463 | B45: Eating out | C45: 8.2 | D45: Office Lunch
A46: 45462 | B46: Eating Out | C46: 17.05 | D46: Lunch
A47: 45471 | B47: Fun / Misc | C47: 14.02 | D47: Walmart +
A48: 45466 | B48: Eating out | C48: 6.39 | D48: Wendeez Nuts
A49: 45460 | B49: Groceries | C49: 4.77 | D49: ice cream
A50: 45473 | B50: Eating out | C50: 5.33 | D50: McDonald's
A51: 45469 | B51: Eating out | C51: 10.82 | D51: Mcdonald's
A52: 45468 | B52: Eating out | C52: 5.46 | D52: BASF Lunch
A53: 45467 | B53: Eating out | C53: 24.67 | D53: Lunch
A54: 45467 | B54: Eating out | C54: 50 | D54: Gift Card for Katherine
... A61: 45464 | B61: Eating out | C61: 12.79 | D61: Bagel
A62: 45461 | B62: Groceries | C62: 162.56 | D62: Costco | E62: 907 | F62: 2516 Insurance
A63: 45459 | B63: Eating out | C63: 19.62 | D63: Panda Express
A64: 45457 | B64: Eating out | C64: 61 | D64: Mcdonalds+Sushi
A65: 45455 | B65: Groceries | C65: 160 | D65: Costco
A66: 45454 | B66: Eating out | C66: 4.25 | D66: mcmuffin
A67: 45454 | B67: Household Goods | C67: 24.81 | D67: Textbook
A68: 45453 | B68: Groceries | C68: 31.62 | D68: KaMAMAN
A69: 45453 | B69: Groceries | C69: 90.15 | D69: COSTO
A70: 45451 | B70: Eating out | C70: 73.09 | D70: Tim ho wan
A71: 45451 | B71: Fun / Misc | C71: =8*2.9 -> 23.2 | D71: SUBWAY
A72: 45451 | B72: Fun / Misc | C72: 91.7 | D72: Morristown Train +
A73: 45451 | B73: Eating out | C73: 24 | D73: Pizza
A74: 45451 | B74: Fun / Misc | C74: 435 | D74: Wicked
A75: 45451 | B75: Household Goods | C75: 6.18 | D75: CVS Drinks
A76: 45448 | B76: Groceries | C76: 5.49 | D76: Shoprite
A77: 45447 | B77: Gas | C77: 60 | D77: Quick Check
A78: 45446 | B78: Groceries | C78: 156.94 | D78: Costco + Kam man
A79: 45445 | B79: Eating out | C79: 14 | D79: Pizza
A80: 45445 | B80: Fun / Misc | C80: 50 | D80: Edibles
A81: 45444 | B81: Eating out | C81: 16.41 | D81: tTacobel
A82: 45444 | B82: Eating out | C82: 104.52 | D82: Sugarfish
A83: 45459 | B83: Household Goods | C83: 53 | D83: Bra

Sheet July 2024
A4: Monthly Spending | G4: Monthly Overview | J4: Expenses over Time
A5: Category | B5: Budgeted | C5: Amount Spent | D5: Amount Remaining | E5: % Remaining | G5: Income
A6: Fixed | B6: 2663.68 | C6: =sumif($B$20:$C$101,A6,$C$20:$C$101) -> 3366.0767 | D6: =B6-C6 -> -702.39667 | E6: =D6/B6 -> -0.26369409 | G6: Martin Paycheck | H6: =3080*2 -> 6160
A7: Utilities | B7: 0 | C7: =sumif($B$20:$C$101,A7,$C$20:$C$101) -> 0 | D7: =B7-C7 -> 0 | E7: =D7/B7 -> #DIV/0! | G7: Rachel Paycheck | H7: =3370*2 -> 6740
A8: Bills | B8: 250 | C8: =sumif($B$20:$C$101,A8,$C$20:$C$101) -> 0 | D8: =B8-C8 -> 250 | E8: =D8/B8 -> 1 | G8: Total | H8: =SUM(H6:H7) -> 12900
A9: Groceries | B9: 400 | C9: =sumif($B$20:$C$101,A9,$C$20:$C$101) -> 985.76333 | D9: =B9-C9 -> -585.76333 | E9: =D9/B9 -> -1.4644083
A10: Eating out | B10: 400 | C10: =sumif($B$20:$C$101,A10,$C$20:$C$101) -> 551.75333 | D10: =B10-C10 -> -151.75333 | E10: =D10/B10 -> -0.37938333 | G10: Monthly Expenses
A11: Household Goods | B11: 200 | C11: =sumif($B$20:$C$101,A11,$C$20:$C$101) -> 513.22 | D11: =B11-C11 -> -313.22 | E11: =D11/B11 -> -1.5661 | G11: Total Spent | H11: =sum(C17) -> 6564.97
A12: Travel | B12: 500 | C12: 500 | D12: =B12-C12 -> 0 | E12: =D12/B12 -> 0
A13: Gas | B13: 200 | C13: =sumif($B$20:$C$101,A13,$C$20:$C$101) -> 150.49 | D13: =B13-C13 -> 49.51 | E13: =D13/B13 -> 0.24755 | G13: Recurring Expenses
A14: Health | B14: 0 | C14: =sumif($B$20:$C$101,A14,$C$20:$C$101) -> 176.39 | D14: =B14-C14 -> -176.39 | E14: =D14/B14 -> #DIV/0! | G14: Car Insurance
A15: Fun / Misc | B15: 300 | C15: =sumif($B$20:$C$101,A15,$C$20:$C$101) -> 321.27667 | D15: =B15-C15 -> -21.276667 | E15: =D15/B15 -> -0.070922222
A16: Business School | B16: 0 | C16: =sumif($B$20:$C$101,A16,$C$20:$C$101) -> 0 | D16: =B16-C16 -> 0 | E16: =D16/B16 -> #DIV/0! | G16: Amount spent on Travel | H16: =SUMIF($B$20:$C$123,"Travel",$C$20:$C$123) -> 609.96
A17: Total | B17: =SUM(B6:B16) -> 4913.68 | C17: =SUM(C6:C16) -> 6564.97 | D17: =SUM(D6:D15) -> -1651.29 | E17: =D17/B17 -> -0.33605974 | G17: Amount in Travel Bank | H17: =500-SUMIF($B$20:$C$123,"Travel",$C$20:$C$123)+'June 2024'!H17 -> 749.49
A19: Date | B19: Category | C19: Spent | D19: Note
A20: Monthly | B20: Fixed | C20: 2900 | D20: Rent
A21: Monthly | B21: Fixed | C21: 40 | D21: Internet
A22: Monthly | B22: Fixed | C22: 85.61 | D22: Electric
A23: Monthly | B23: Fixed | C23: 42.62 | D23: Exercise
A24: Monthly | B24: Fixed | C24: 19.49 | D24: Gas
A25: Monthly | B25: Fixed | C25: =77/12 -> 6.4166667 | D25: Renters insurance
A26: Monthly | B26: Fixed | C26: 144 | D26: Car Insurance
A27: Monthly | B27: Fixed | C27: 2.87 | D27: Spotify - Martin
A28: Monthly | B28: Fixed | C28: 2.99 | D28: Google One
A29: Monthly | B29: Fixed | C29: 5.83 | D29: One Drive
A30: Monthly | B30: Fixed | C30: 6.25 | D30: MSFT
A31: Monthly | B31: Fixed | C31: 110 | D31: Phone
A34: 45474 | B34: Groceries | C34: 76.49 | D34: Costco
A35: 45475 | B35: Eating Out | C35: 7.84 | D35: BASF Lunch
A36: 45480 | B36: Health | C36: 56.39 | D36: Duke Health Visit
A37: 45479 | B37: Household Goods | C37: 19.26 | D37: Hygeiene
A38: 45474 | B38: Eating out | C38: 1.6 | D38: Costo dog
A39: 45479 | B39: Eating out | C39: 23.61 | D39: Chick Fil a
A40: 45477 | B40: Eating out | C40: 24.52 | D40: Panda Express
A41: 45479 | B41: Household Goods | C41: 6 | D41: Paper
A42: 45481 | B42: Gas | C42: 43 | D42: Quickcheck
A43: 45486 | B43: Fun / Misc | C43: 10.5 | D43: EWR parking
A44: 45487 | B44: Eating out | C44: 21 | D44: Pizza
A45: 45487 | B45: Fun / Misc | C45: =2.9*6 -> 17.4 | D45: MTA
A46: 45491 | B46: Fun / Misc | C46: 60 | D46: Golf with matt
A47: 45491 | B47: Household Goods | C47: 15.47 | D47: Amazon something
A48: 45491 | B48: Eating out | C48: =122 -> 122 | D48: Sugar Fish
A49: 45491 | B49: Eating out | C49: 12.5 | D49: Pizza
A50: 45492 | B50: Fun / Misc | C50: =7.7*2/3 -> 5.1333333 | D50: Parking
A51: 45493 | B51: Gas | C51: 61.32 | D51: Martin - Gas
A52: 45495 | B52: Eating out | C52: 8.53 | D52: MCds
A53: 45498 | B53: Eating out | C53: 16.4 | D53: Taco Bell
A54: 45500 | B54: Eating out | C54: 11 | D54: Dominic Ansel
A55: 45500 | B55: Fun / Misc | C55: =64.4/2 -> 32.2 | D55: NJ Transit
A56: 45504 | B56: Travel | C56: 10 | D56: United flight Change
A57: 45504 | B57: Household Goods | C57: =362-237 -> 125 | D57: Jcrew
A58: 45486 | B58: Groceries | C58: 14.6 | D58: Shoprite
A59: 45485 | B59: Eating out | C59: 2.12 | D59: Costco Hot dog
A60: 45491 | B60: Eating out | C60: 6.67 | D60: BASF Lunch
A61: 45489 | B61: Eating out | C61: 2.14 | D61: Taco Bell
A62: 45488 | B62: Fun / Misc | C62: =2.9*(1+3+2+1) -> 20.3 | D62: MTA
A63: 45482 | B63: Groceries | C63: 26.81 | D63: Shoprite
A64: 45481 | B64: Eating out | C64: 1.6 | D64: Costco
A65: 45504 | B65: Groceries | C65: 20.5 | D65: Kam man
A66: 45504 | B66: Groceries | C66: 222.4 | D66: Costco
A67: 45503 | B67: Travel | C67: =164.98*2 -> 329.96 | D67: Jetblue SJU to RDU
A68: 45502 | B68: Groceries | C68: 159.98 | D68: Costco
A69: 45501 | B69: Groceries | C69: 38.37 | D69: Shop Rite | F69: Amazon Filters | G69: 36.3
A70: 45501 | B70: Eating out | C70: 22.92 | D70: Panda
A71: 45500 | B71: Fun / Misc | C71: 32.3 | D71: NJ Transit
A72: 45500 | B72: Eating out | C72: 99 | D72: Zaab
A73: 45500 | B73: Fun / Misc | C73: =7.7*2/3 -> 5.1333333 | D73: Parking
A74: 45500 | B74: Fun / Misc | C74: 3.81 | D74: HIDE AND SEEK
A75: 45500 | B75: Groceries | C75: =9.21+24.93 -> 34.14 | D75: Costco
A76: 45499 | B76: Eating out | C76: =158.21*2/3 -> 105.47333 | D76: Asahi
A77: 45499 | B77: Household Goods | C77: 113.37 | D77: Toothbrush
A78: 45499 | B78: Eating out | C78: 6.24 | D78: KFT
A79: 45497 | B79: Gas | C79: 46.17 | D79: Quickcheck
A80: 45496 | B80: Household Goods | C80: 107.12 | D80: Costco
A81: 45495 | B81: Groceries | C81: =51.32*2/3 -> 34.213333 | D81: Kam man
A82: 45495 | B82: Groceries | C82: =196.5*2/3 -> 131 | D82: Costco
A83: 45493 | B83: Eating out | C83: 4.4 | D83: Wawa starbucks
A84: 45493 | B84: Fun / Misc | C84: 74 | D84: Guggenheim
A85: 45493 | B85: Eating out | C85: 4.19 | D85: Sweetgreen
A86: 45488 | B86: Fun / Misc | C86: 42.8 | D86: IU Parking
A87: 45487 | B87: Fun / Misc | C87: 7.7 | D87: Morristown parking
A88: 45486 | B88: Groceries | C88: 15.96 | D88: Shoprite
A89: 45485 | B89: Health | C89: 120 | D89: Haircut
A90: 45485 | B90: Groceries | C90: 47.17 | D90: Weggies
A91: 45485 | B91: Groceries | C91: 84.13 | D91: Costco
A92: 45483 | B92: Household Goods | C92: 127 | D92: Costco Membership
A93: 45483 | B93: Fun / Misc | C93: 10 | D93: Movie tickets
A94: 45481 | B94: Groceries | C94: 80 | D94: Costco + kam man
A95: 45501 | B95: Eating out | C95: 48 | D95: Lunch
A96: 45486 | B96: Travel | C96: =260*2 -> 520 | D96: Atlantic City
A97: 45486 | B97: Travel | C97: -250 | D97: Gambling Winnings

Sheet Aug 2024
A4: Monthly Spending | G4: Monthly Overview | J4: Expenses over Time
A5: Category | B5: Budgeted | C5: Amount Spent | D5: Amount Remaining | E5: % Remaining | G5: Income
A6: Fixed | B6: 2663.68 | C6: =sumif($B$20:$C$101,A6,$C$20:$C$101) -> 4848.4767 | D6: =B6-C6 -> -2184.7967 | E6: =D6/B6 -> -0.82021739 | G6: Martin Paycheck | H6: =3080*2 -> 6160
A7: Utilities | B7: 0 | C7: =sumif($B$20:$C$101,A7,$C$20:$C$101) -> 0 | D7: =B7-C7 -> 0 | E7: =D7/B7 -> #DIV/0! | G7: Rachel Paycheck | H7: =3370*2 -> 6740
A8: Bills | B8: 250 | C8: =sumif($B$20:$C$101,A8,$C$20:$C$101) -> 155.65 | D8: =B8-C8 -> 94.35 | E8: =D8/B8 -> 0.3774 | G8: Total | H8: =SUM(H6:H7) -> 12900
A9: Groceries | B9: 400 | C9: =sumif($B$20:$C$101,A9,$C$20:$C$101) -> 1085.31 | D9: =B9-C9 -> -685.31 | E9: =D9/B9 -> -1.713275
A10: Eating out | B10: 400 | C10: =sumif($B$20:$C$101,A10,$C$20:$C$101) -> 695.20286 | D10: =B10-C10 -> -295.20286 | E10: =D10/B10 -> -0.73800714 | G10: Monthly Expenses
A11: Household Goods | B11: 200 | C11: =sumif($B$20:$C$101,A11,$C$20:$C$101) -> 440.07 | D11: =B11-C11 -> -240.07 | E11: =D11/B11 -> -1.20035 | G11: Total Spent | H11: =sum(C17) -> 8643.1595
A12: Travel | B12: 500 | C12: 500 | D12: =B12-C12 -> 0 | E12: =D12/B12 -> 0
A13: Gas | B13: 200 | C13: =sumif($B$20:$C$101,A13,$C$20:$C$101) -> 134.8 | D13: =B13-C13 -> 65.2 | E13: =D13/B13 -> 0.326 | G13: Recurring Expenses
A14: Health | B14: 0 | C14: =sumif($B$20:$C$101,A14,$C$20:$C$101) -> 386.22 | D14: =B14-C14 -> -386.22 | E14: =D14/B14 -> #DIV/0! | G14: Car Insurance
A15: Fun / Misc | B15: 300 | C15: =sumif($B$20:$C$101,A15,$C$20:$C$101) -> 397.43 | D15: =B15-C15 -> -97.43 | E15: =D15/B15 -> -0.32476667
A16: Business School | B16: 0 | C16: =sumif($B$20:$C$101,A16,$C$20:$C$101) -> 0 | D16: =B16-C16 -> 0 | E16: =D16/B16 -> #DIV/0! | G16: Amount spent on Travel | H16: =SUMIF($B$20:$C$123,"Travel",$C$20:$C$123) -> 618
A17: Total | B17: =SUM(B6:B16) -> 4913.68 | C17: =SUM(C6:C16) -> 8643.1595 | D17: =SUM(D6:D15) -> -3729.4795 | E17: =D17/B17 -> -0.75899927 | G17: Amount in Travel Bank | H17: =500-SUMIF($B$20:$C$123,"Travel",$C$20:$C$123)+'July 2024'!H17 -> 631.49
A19: Date | B19: Category | C19: Spent | D19: Note
A20: Monthly | B20: Fixed | C20: =2900+1476 -> 4376 | D20: Rent
A21: Monthly | B21: Fixed | C21: 40 | D21: Internet
A22: Monthly | B22: Fixed | C22: 89 | D22: Electric
A23: Monthly | B23: Fixed | C23: 42.62 | D23: Exercise
A24: Monthly | B24: Fixed | C24: 20.5 | D24: Gas
A25: Monthly | B25: Fixed | C25: =77/12 -> 6.4166667 | D25: Renters insurance
A26: Monthly | B26: Fixed | C26: 144 | D26: Car Insurance
A27: Monthly | B27: Fixed | C27: 2.87 | D27: Spotify - Martin
A28: Monthly | B28: Fixed | C28: 2.99 | D28: Google One
A29: Monthly | B29: Fixed | C29: 5.83 | D29: One Drive
A30: Monthly | B30: Fixed | C30: 6.25 | D30: MSFT
A31: Monthly | B31: Fixed | C31: 112 | D31: Phone
A34: 45506 | B34: Fun / Misc | C34: 10.75 | D34: Spothero Parking
A35: 45507 | B35: Groceries | C35: 26.67 | D35: Whole Foods
A36: 45507 | B36: Gas | C36: 59.8 | D36: Gas
A37: 45507 | B37: Eating out | C37: 7.47 | D37: Mcdonalds
A38: 45507 | B38: Household Goods | C38: 5.99 | D38: Amazon
A39: 45509 | B39: Household Goods | C39: 3.19 | D39: Best Buy
A40: 45509 | B40: Eating out | C40: 4.47 | D40: Mcdonalds
A41: 45512 | B41: Eating out | C41: 3.47 | D41: Chick fil a
A42: 45514 | B42: Eating out | C42: 14.49 | D42: Mcdonalds
A44: 45515 | B44: Health | C44: 99.1 | D44: Vision
A45: 45505 | B45: Health | C45: 179.12 | D45: Glasses
A46: 45515 | B46: Groceries | C46: 85.58 | D46: Costco
... A51: 45513 | B51: Travel | C51: 540 | D51: Delta Airlines
A52: 45508 | B52: Fun / Misc | C52: =66.59*2 -> 133.18 | D52: Monster Jam
A53: 45512 | B53: Eating out | C53: 27.75 | D53: Millie's meatballs
A54: 45516 | B54: Travel | C54: 78 | D54: Flight - Rachel
A55: 45521 | B55: Eating out | C55: 98 | D55: Zaab Zaab
A56: 45527 | B56: Eating out | C56: 83 | D56: Pizza
A57: 45523 | C57: 20 | D57: Labor day Dinner | E57: ML
A58: 45530 | C58: 20 | D58: Uber | E58: ML
A59: 45533 | C59: 350 | D59: Pre function trip
A60: 45535 | B60: Household Goods | C60: 96.89 | D60: August Amazon
A61: 45535 | B61: Gas | C61: 75 | D61: Gas
A62: 45528 | B62: Household Goods | C62: 14 | D62: Costco
A63: 45532 | B63: Household Goods | C63: 50 | D63: NJ Ez pass
A64: 45528 | B64: Groceries | C64: 270 | D64: move-in groceries
A65: 45528 | B65: Household Goods | C65: 270 | D65: Move in household
A66: 45535 | B66: Eating out | C66: 114 | D66: August Restuarants
A67: 45520 | B67: Groceries | C67: 45.19 | D67: Protein
A68: 45522 | B68: Fun / Misc | C68: 80 | D68: Slaon Groups
A69: 45523 | B69: Bills | C69: 73 | D69: Oil Change | F69: Amazon Filters | G69: 36.3
A70: 45535 | B70: Groceries | C70: 117 | D70: Kam Man
A71: 45535 | B71: Bills | C71: 56 | D71: Parking
A72: 45528 | B72: Bills | C72: 26.65 | D72: Travel Hiccup
A73: 45529 | B73: Fun / Misc | C73: 25.99 | D73: Liquor store
A74: 45529 | B74: Health | C74: 108 | D74: Zbiotic
A75: 45529 | B75: Eating out | C75: 260.35 | D75: August Restaurants
A76: 45535 | C76: 10 | D76: LIRR
A77: 45521 | B77: Eating out | C77: 29.39 | D77: Crepes
A78: 45517 | C78: 8.65
A79: 45523 | B79: Groceries | C79: =127+473+244 -> 844 | D79: Costco
A80: 45532 | B80: Fun / Misc | C80: 53.92 | D80: blue bike membership
A81: 45532 | B81: Eating out | C81: =148/7 -> 21.142857 | D81: si cara | E81: ML
A82: 45533 | B82: Fun / Misc | C82: 25 | D82: mass ave wine
A83: 45535 | B83: Fun / Misc | C83: =32.66+16.33+19.6 -> 68.59 | D83: concert funsies
A84: 45535 | B84: Groceries | C84: 1041 | D84: Costco
A85: 45535 | B85: Groceries | C85: -1362 | D85: Split

Sheet Sept 2024
A4: Monthly Spending | G4: Monthly Overview | J4: Expenses over Time
A5: Category | B5: Budgeted | C5: Amount Spent | D5: Amount Remaining | E5: % Remaining | G5: Income
A6: Fixed | B6: 2663.68 | C6: =sumif($B$20:$C$102,A6,$C$20:$C$102) -> 4747.0267 | D6: =B6-C6 -> -2083.3467 | E6: =D6/B6 -> -0.78213099 | G6: Martin Paycheck | H6: 5000
A7: Utilities | B7: 0 | C7: =sumif($B$20:$C$102,A7,$C$20:$C$102) -> 0 | D7: =B7-C7 -> 0 | E7: =D7/B7 -> #DIV/0! | G7: Rachel Paycheck | H7: 4200
A8: Bills | B8: 250 | C8: =sumif($B$20:$C$102,A8,$C$20:$C$102) -> 11 | D8: =B8-C8 -> 239 | E8: =D8/B8 -> 0.956 | G8: Total | H8: =SUM(H6:H7) -> 9200
A9: Groceries | B9: 400 | C9: =sumif($B$20:$C$102,A9,$C$20:$C$102) -> 1281.1 | D9: =B9-C9 -> -881.1 | E9: =D9/B9 -> -2.20275
A10: Eating out | B10: 400 | C10: =sumif($B$20:$C$102,A10,$C$20:$C$102) -> 673.3 | D10: =B10-C10 -> -273.3 | E10: =D10/B10 -> -0.68325 | G10: Monthly Expenses
A11: Household Goods | B11: 200 | C11: =sumif($B$20:$C$102,A11,$C$20:$C$102) -> 166.77 | D11: =B11-C11 -> 33.23 | E11: =D11/B11 -> 0.16615 | G11: Total Spent | H11: =sum(C17) -> 8077.7067
A12: Travel | B12: 500 | C12: 500 | D12: =B12-C12 -> 0 | E12: =D12/B12 -> 0
A13: Gas | B13: 200 | C13: =sumif($B$20:$C$102,A13,$C$20:$C$102) -> 0 | D13: =B13-C13 -> 200 | E13: =D13/B13 -> 1 | G13: Recurring Expenses
A14: Health | B14: 0 | C14: =sumif($B$20:$C$102,A14,$C$20:$C$102) -> 93.55 | D14: =B14-C14 -> -93.55 | E14: =D14/B14 -> #DIV/0! | G14: Car Insurance
A15: Fun / Misc | B15: 300 | C15: =sumif($B$20:$C$102,A15,$C$20:$C$102) -> 319.96 | D15: =B15-C15 -> -19.96 | E15: =D15/B15 -> -0.066533333
A16: Business School | B16: 0 | C16: =sumif($B$20:$C$102,A16,$C$20:$C$102) -> 285 | D16: =B16-C16 -> -285 | E16: =D16/B16 -> #DIV/0! | G16: Amount spent on Travel | H16: =SUMIF($B$20:$C$174,"Travel",$C$20:$C$174) -> 556.98
A17: Total | B17: =SUM(B6:B16) -> 4913.68 | C17: =SUM(C6:C16) -> 8077.7067 | D17: =SUM(D6:D15) -> -2879.0267 | E17: =D17/B17 -> -0.58592067 | G17: Amount in Travel Bank | H17: =500-SUMIF($B$20:$C$174,"Travel",$C$20:$C$174)+'April 2024'!H17 -> 446.26
A19: Date | B19: Category | C19: Spent | D19: Note
A20: Monthly | B20: Fixed | C20: =2900+1476 -> 4376 | D20: Rent
A21: Monthly | B21: Fixed | C21: 40 | D21: Internet
A22: Monthly | B22: Fixed | C22: 40 | D22: Electric
A23: Monthly | B23: Fixed | C23: 42.62 | D23: Exercise
A24: Monthly | B24: Fixed | C24: 16.55 | D24: Gas | G24: Credit balance (9/29)
A25: Monthly | B25: Fixed | C25: =77/12 -> 6.4166667 | D25: Renters insurance | F25: RSB Chase | G25: =8.62+3758.03 -> 3766.65 | H25: 6k from 4668 card
A26: Monthly | B26: Fixed | C26: =585/6 -> 97.5 | D26: Car Insurance | F26: RSB Amex | G26: 0
A27: Monthly | B27: Fixed | C27: 2.87 | D27: Spotify - Martin | F27: RSB Barclay | G27: 965.33
A28: Monthly | B28: Fixed | C28: 2.99 | D28: Google One | F28: ML Chase | G28: =274.97+19.17+184.41+1077.59+1829.28 -> 3385.42
A29: Monthly | B29: Fixed | C29: 5.83 | D29: One Drive | F29: ML Amex | G29: =27.87 -> 27.87 | H29: only amex gold
A30: Monthly | B30: Fixed | C30: 6.25 | D30: MSFT | F30: ML Barclay | G30: 1388.4
A31: Monthly | B31: Fixed | C31: 110 | D31: Phone | F31: TOTAL | G31: =SUM(G25:G30) -> 9533.67
F32: Rent | G32: 2900
G33: 8000
A34: 45555 | B34: Eating out | C34: 42.44 | D34: Dinner & Drinks | E34: ML
A35: 45537 | B35: Fun / Misc | C35: 25 | D35: Danielle Wedding Gift
A36: 45544 | B36: Fun / Misc | C36: 16 | D36: SO event
A37: 45538 | B37: Household Goods | C37: 130 | D37: Amazon
A38: 45541 | B38: Household Goods | C38: 5 | D38: Laundry
A39: 45540 | B39: Eating out | C39: =10.11*2 -> 20.22 | D39: Chipotle
A40: 45540 | B40: Health | C40: 5.88 | D40: Walgreens
A41: 45540 | B41: Fun / Misc | C41: 4.5 | D41: Blue bike
A42: 45540 | B42: Eating out | C42: 15.3 | D42: Drinks
A43: 45540 | B43: Fun / Misc | C43: 4.87 | D43: Pirate Ship
A44: 45539 | B44: Fun / Misc | C44: 30.92 | D44: Going
A45: 45536 | B45: Fun / Misc | C45: 31 | D45: NJ Transit
A46: 45537 | B46: Fun / Misc | C46: 26 | D46: Uber
A47: 45542 | B47: Eating out | C47: 100.68 | D47: Restaurants
A48: 45542 | B48: Business School | C48: 285 | D48: Club Dues
A49: 45542 | B49: Fun / Misc | C49: 4.8 | D49: Alewife travel
B50: Household Goods | D50: Laundry
B51: Bills | C51: 11 | D51: DL License
A52: 45549 | B52: Household Goods | C52: 1.25 | D52: Laundry
A53: 45537 | B53: Eating out | C53: 10 | D53: chipotle | E53: ML
A54: 45537 | B54: Eating out | C54: 34.3 | D54: wendys ewr | E54: RB
A55: 45537 | B55: Household Goods | C55: 4.66 | D55: target
A56: 45537 | B56: Groceries | C56: 51.32 | D56: trader joes
A57: 45538 | B57: Groceries | C57: 569.67 | D57: costco
A58: 45541 | B58: Health | C58: =10+45 -> 55 | D58: shipping glasses + extra protection
A59: 45541 | B59: Eating out | C59: 26.65 | D59: pad thai cafe
A60: 45542 | B60: Eating out | C60: =137.29 -> 137.29 | D60: qiao lin hotpot
A61: 45544 | B61: Health | C61: 16.13 | D61: RSB MIT gym
A62: 45547 | B62: Eating out | C62: 17.39 | D62: flour bakery
A63: 45548 | B63: Eating out | C63: =224.76/6*2 -> 74.92 | D63: qiao lin hotpot
A64: 45549 | B64: Groceries | C64: =5.12+25+17 -> 47.12 | D64: costco
A65: 45549 | B65: Household Goods | C65: 2.5 | D65: laundry
A66: 45550 | B66: Health | C66: 11.78 | D66: CVS
A67: 45550 | B67: Health | C67: 4.76 | D67: target
A68: 45550 | B68: Eating out | C68: 12.63 | D68: cisco brewers | E68: RB
A69: 45550 | B69: Groceries | C69: 98.81 | D69: costco
A70: 45550 | B70: Household Goods | C70: 1.25 | D70: laundry | F70: Amazon Filters | G70: 36.3
A71: 45552 | B71: Eating out | C71: 7.87 | D71: BASF lunch
A72: 45553 | B72: Eating out | C72: 10.11 | D72: chipotle
A73: 45553 | B73: Eating out | C73: 21.89 | D73: hidden chickpea
A74: 45540 | B74: Groceries | C74: -185 | D74: Costco
A75: 45556 | B75: Groceries | C75: 407 | D75: Paid by Davide
A76: 45557 | B76: Groceries | C76: 48 | D76: Whole Foods
A77: 45557 | B77: Groceries | C77: 120 | D77: Whole Foods
A78: 45563 | B78: Eating out | C78: 10.58 | D78: Root Beer
A79: 45565 | B79: Household Goods | C79: 10.65 | D79: Nail gel
A80: 45562 | B80: Eating out | C80: 74 | D80: Qiao lin
A81: 45562 | B81: Travel | C81: 54 | D81: Spirit Flight
A82: 45563 | B82: Fun / Misc | C82: 4.56 | D82: Target
A83: 45561 | B83: Eating out | C83: 12.23 | D83: Brother lunch | E83: ML
A84: 45559 | B84: Household Goods | C84: 5 | D84: Laundry
A85: 45559 | B85: Eating out | C85: 8.29 | D85: Blue Bottle
A86: 45556 | B86: Travel | C86: 42.98 | D86: Lyft
A87: 45556 | B87: Eating out | C87: 21.38 | D87: Depth N Green | E87: ML
A88: 45554 | B88: Eating out | C88: 6.13 | D88: Starbucks
A89: 45554 | B89: Eating out | C89: 9 | D89: Dominos
A90: 45189 | B90: Fun / Misc | C90: 12.33 | D90: Uber
A91: 45555 | B91: Fun / Misc | C91: 159.98 | D91: Uber GC - Costco
A92: 45553 | B92: Travel | C92: 460 | D92: Scuba Certification
A93: 45565 | B93: Groceries | C93: 84.72 | D93: Groceries
A94: 45565 | B94: Groceries | C94: 39.46 | D94: Groceries
A95: 45564 | B95: Household Goods | C95: 6.46 | D95: Batteries

Sheet Oct 2024
A4: Monthly Spending | G4: Monthly Overview | J4: Expenses over Time
A5: Category | B5: Budgeted | C5: Amount Spent | D5: Amount Remaining | E5: % Remaining | G5: Income
A6: Fixed | B6: 2663.68 | C6: =sumif($B$20:$C$501,A6,$C$20:$C$501) -> 4730.4767 | D6: =B6-C6 -> -2066.7967 | E6: =D6/B6 -> -0.77591778 | G6: Martin Paycheck | H6: 0
A7: Utilities | B7: 0 | C7: =sumif($B$20:$C$501,A7,$C$20:$C$501) -> 0 | D7: =B7-C7 -> 0 | E7: =D7/B7 -> #DIV/0! | G7: Rachel Paycheck | H7: 4200
A8: Bills | B8: 250 | C8: =sumif($B$20:$C$501,A8,$C$20:$C$501) -> 217.3 | D8: =B8-C8 -> 32.7 | E8: =D8/B8 -> 0.1308 | G8: Total | H8: =SUM(H6:H7) -> 4200
A9: Groceries | B9: 400 | C9: =sumif($B$20:$C$501,A9,$C$20:$C$501) -> 647.84 | D9: =B9-C9 -> -247.84 | E9: =D9/B9 -> -0.6196
A10: Eating out | B10: 400 | C10: =sumif($B$20:$C$501,A10,$C$20:$C$501) -> 648.9 | D10: =B10-C10 -> -248.9 | E10: =D10/B10 -> -0.62225 | G10: Monthly Expenses
A11: Household Goods | B11: 200 | C11: =sumif($B$20:$C$501,A11,$C$20:$C$501) -> 818.45 | D11: =B11-C11 -> -618.45 | E11: =D11/B11 -> -3.09225 | G11: Total Spent | H11: =sum(C17) -> 8794.2167
A12: Travel | B12: 500 | C12: =sumif($B$20:$C$501,A12,$C$20:$C$501) -> 244.12 | D12: =B12-C12 -> 255.88 | E12: =D12/B12 -> 0.51176
A13: Gas | B13: 200 | C13: =sumif($B$20:$C$501,A13,$C$20:$C$501) -> 430.95 | D13: =B13-C13 -> -230.95 | E13: =D13/B13 -> -1.15475 | G13: Recurring Expenses
A14: Health | B14: 0 | C14: =sumif($B$20:$C$501,A14,$C$20:$C$501) -> 34.55 | D14: =B14-C14 -> -34.55 | E14: =D14/B14 -> #DIV/0! | G14: Car Insurance
A15: Fun / Misc | B15: 300 | C15: =sumif($B$20:$C$501,A15,$C$20:$C$501) -> 830.81 | D15: =B15-C15 -> -530.81 | E15: =D15/B15 -> -1.7693667
A16: Business School | B16: 0 | C16: =sumif($B$20:$C$501,A16,$C$20:$C$501) -> 190.82 | D16: =B16-C16 -> -190.82 | E16: =D16/B16 -> #DIV/0! | G16: Amount spent on Travel | H16: =SUMIF($B$20:$C$215,"Travel",$C$20:$C$215) -> 244.12
A17: Total | B17: =SUM(B6:B16) -> 4913.68 | C17: =SUM(C6:C16) -> 8794.2167 | D17: =SUM(D6:D15) -> -3689.7167 | E17: =D17/B17 -> -0.75090699 | G17: Amount in Travel Bank | H17: =500-SUMIF($B$20:$C$215,"Travel",$C$20:$C$215)+'April 2024'!H17 -> 759.12
A19: Date | B19: Category | C19: Spent | D19: Note
A20: Monthly | B20: Fixed | C20: =2900+1476 -> 4376 | D20: Rent
A21: Monthly | B21: Fixed | C21: 40 | D21: Internet
A22: Monthly | B22: Fixed | C22: 40 | D22: Electric
A23: Monthly | B23: Fixed | C23: 42.62 | D23: Exercise
G24: Credit balance (9/29)
A25: Monthly | B25: Fixed | C25: =77/12 -> 6.4166667 | D25: Renters insurance | F25: RSB Chase | G25: =8.62+3758.03 -> 3766.65 | H25: 6k from 4668 card
A26: Monthly | B26: Fixed | C26: =585/6 -> 97.5 | D26: Car Insurance | F26: RSB Amex | G26: 0
A27: Monthly | B27: Fixed | C27: 2.87 | D27: Spotify - Martin | F27: RSB Barclay | G27: 965.33
A28: Monthly | B28: Fixed | C28: 2.99 | D28: Google One | F28: ML Chase | G28: =274.97+19.17+184.41+1077.59+1829.28 -> 3385.42
A29: Monthly | B29: Fixed | C29: 5.83 | D29: One Drive | F29: ML Amex | G29: =27.87 -> 27.87 | H29: only amex gold
A30: Monthly | B30: Fixed | C30: 6.25 | D30: MSFT | F30: ML Barclay | G30: 1388.4
A31: Monthly | B31: Fixed | C31: 110 | D31: Phone | F31: TOTAL | G31: =SUM(G25:G30) -> 9533.67
F32: Rent | G32: 2900
G33: 8000
A34: 45555 | B34: Eating out | C34: 24 | D34: Tall Ship Shot | E34: ML
B35: Eating out | C35: 16 | D35: BBQ Chicken | E35: ML
B36: Gas | C36: 19 | D36: Lyft to and from | E36: ML
B37: Fun / Misc | C37: 20 | D37: Salem Signup | E37: ML
B38: Fun / Misc | C38: 28.8 | D38: Apple Picking | E38: ML
A39: 45589 | B39: Household Goods | C39: 3.75 | D39: Laundry
B40: Travel | C40: 35 | D40: Checked Bag - Maldives
B41: Groceries | C41: 65 | D41: Whole Foods
B42: Groceries | C42: 1.99 | D42: Lowes
A43: 45586 | B43: Groceries | C43: =IFERROR(__xludf.DUMMYFUNCTION("E43*-1"),201.48) -> 201.48 | D43: COSTCO WHSE #1206 | E43: -201.48
A44: 45586 | B44: Gas | C44: =IFERROR(__xludf.DUMMYFUNCTION("E44*-1"),159.98) -> 159.98 | D44: COSTCO WHSE #1206 | E44: -159.98
A45: 45586 | B45: Household Goods | C45: =IFERROR(__xludf.DUMMYFUNCTION("E45*-1"),1.25) -> 1.25 | D45: FC FOWLER LAUNDRY ULTRA | E45: -1.25
A46: 45586 | B46: Eating out | C46: =IFERROR(__xludf.DUMMYFUNCTION("E46*-1"),21.27) -> 21.27 | D46: 4033 ZAROS BAKERY | E46: -21.27
A47: 45586 | B47: Eating out | C47: =IFERROR(__xludf.DUMMYFUNCTION("E47*-1"),15.14) -> 15.14 | D47: STARBUCKS STORE 56775 | E47: -15.14
A48: 45586 | B48: Household Goods | C48: =IFERROR(__xludf.DUMMYFUNCTION("E48*-1"),1.25) -> 1.25 | D48: FC FOWLER LAUNDRY ULTRA | E48: -1.25
A49: 45586 | B49: Household Goods | C49: =IFERROR(__xludf.DUMMYFUNCTION("E49*-1"),1.75) -> 1.75 | D49: FC FOWLER LAUNDRY ULTRA | E49: -1.75
A50: 45586 | B50: Household Goods | C50: =IFERROR(__xludf.DUMMYFUNCTION("E50*-1"),1.75) -> 1.75 | D50: FC FOWLER LAUNDRY ULTRA | E50: -1.75
A51: 45585 | B51: Fun / Misc | C51: =IFERROR(__xludf.DUMMYFUNCTION("E51*-1"),40.0) -> 40 | D51: UNITED 0164442446922 | E51: -40
A52: 45585 | B52: Gas | C52: =IFERROR(__xludf.DUMMYFUNCTION("E52*-1"),23.99) -> 23.99 | D52: UBER *TRIP | E52: -23.99
A53: 45585 | B53: Eating out | C53: 20 | D53: SALEM'S RETREAT LLC | E53: -184.85
A54: 45582 | B54: Gas | C54: =IFERROR(__xludf.DUMMYFUNCTION("E54*-1"),2.4) -> 2.4 | D54: MBTA-550005057785-7570 | E54: -2.4
A55: 45582 | B55: Gas | C55: =IFERROR(__xludf.DUMMYFUNCTION("E55*-1"),159.98) -> 159.98 | D55: WWW COSTCO COM | E55: -159.98
A56: 45582 | B56: Gas | C56: =IFERROR(__xludf.DUMMYFUNCTION("E56*-1"),47.5) -> 47.5 | D56: UBER *TRIP | E56: -47.5
A57: 45581 | B57: Groceries | C57: =IFERROR(__xludf.DUMMYFUNCTION("E57*-1"),20.99) -> 20.99 | D57: H MART CAMBRIDGE LLC | E57: -20.99
A58: 45581 | B58: Fun / Misc | C58: =IFERROR(__xludf.DUMMYFUNCTION("E58*-1"),153.99) -> 153.99 | D58: FRONTIER AI ID37MM | E58: -153.99
A59: 45579 | B59: Eating out | C59: =IFERROR(__xludf.DUMMYFUNCTION("E59*-1"),9.08) -> 9.08 | D59: CHICK-FIL-A #04205 | E59: -9.08
A60: 45579 | B60: Eating out | C60: =IFERROR(__xludf.DUMMYFUNCTION("E60*-1"),25.44) -> 25.44 | D60: CHICK-FIL-A #04205 | E60: -25.44
A61: 45579 | B61: Eating out | C61: 19 | D61: TST* TATTE BAKERY | E61: -28.09
A62: 45579 | B62: Bills | C62: =IFERROR(__xludf.DUMMYFUNCTION("E62*-1"),1.1) -> 1.1 | D62: USPS CHANGE OF ADDRESS | E62: -1.1
A63: 45579 | B63: Fun / Misc | C63: 20 | D63: HARVARD MUSEUM OF NATU | E63: -30
A64: 45578 | B64: Eating out | C64: =IFERROR(__xludf.DUMMYFUNCTION("E64*-1"),10.69) -> 10.69 | D64: RAISING CANES 0726 | E64: -10.69
A65: 45578 | B65: Fun / Misc | C65: =IFERROR(__xludf.DUMMYFUNCTION("E65*-1"),81.99) -> 81.99 | D65: SPIRIT AIRL 4870412031362 | E65: -81.99 | F65: Amazon Filters | G65: 36.3
A66: 45578 | B66: Eating out | C66: 60 | D66: TST* KAJU TOFU HOUSE | E66: -91.44
A67: 45578 | B67: Groceries | C67: =IFERROR(__xludf.DUMMYFUNCTION("E67*-1"),79.99) -> 79.99 | D67: WWW COSTCO COM | E67: -79.99
A68: 45578 | B68: Fun / Misc | C68: =IFERROR(__xludf.DUMMYFUNCTION("E68*-1"),120.75) -> 120.75 | D68: SP 260ONLINE | E68: -120.75
A69: 45576 | B69: Household Goods | C69: =IFERROR(__xludf.DUMMYFUNCTION("E69*-1"),1.75) -> 1.75 | D69: FC FOWLER LAUNDRY ULTRA | E69: -1.75
A70: 45576 | B70: Household Goods | C70: =IFERROR(__xludf.DUMMYFUNCTION("E70*-1"),1.25) -> 1.25 | D70: FC FOWLER LAUNDRY ULTRA | E70: -1.25
A71: 45576 | B71: Household Goods | C71: =IFERROR(__xludf.DUMMYFUNCTION("E71*-1"),1.25) -> 1.25 | D71: FC FOWLER LAUNDRY ULTRA | E71: -1.25
A72: 45576 | B72: Eating out | C72: =IFERROR(__xludf.DUMMYFUNCTION("E72*-1"),9.6) -> 9.6 | D72: COSTCO WHSE #0333 | E72: -9.6
A73: 45576 | B73: Household Goods | C73: =IFERROR(__xludf.DUMMYFUNCTION("E73*-1"),1.25) -> 1.25 | D73: FC FOWLER LAUNDRY ULTRA | E73: -1.25
A74: 45576 | B74: Household Goods | C74: =IFERROR(__xludf.DUMMYFUNCTION("E74*-1"),1.25) -> 1.25 | D74: FC FOWLER LAUNDRY ULTRA | E74: -1.25
A75: 45573 | B75: Gas | C75: =IFERROR(__xludf.DUMMYFUNCTION("E75*-1"),2.9) -> 2.9 | D75: MTA*NYCT PAYGO | E75: -2.9
A76: 45573 | B76: Fun / Misc | C76: =IFERROR(__xludf.DUMMYFUNCTION("E76*-1"),30.0) -> 30 | D76: SPIRIT AIRL 4870411449615 | E76: -30
A77: 45573 | B77: Gas | C77: =IFERROR(__xludf.DUMMYFUNCTION("E77*-1"),2.9) -> 2.9 | D77: MTA*NYCT PAYGO | E77: -2.9
A78: 45573 | B78: Gas | C78: =IFERROR(__xludf.DUMMYFUNCTION("E78*-1"),2.75) -> 2.75 | D78: PATH TAPP PAYGO CP | E78: -2.75
A79: 45572 | B79: Gas | C79: =IFERROR(__xludf.DUMMYFUNCTION("E79*-1"),2.9) -> 2.9 | D79: MTA*NYCT PAYGO | E79: -2.9
A80: 45572 | B80: Gas | C80: =IFERROR(__xludf.DUMMYFUNCTION("E80*-1"),2.75) -> 2.75 | D80: PATH TAPP PAYGO CP | E80: -2.75
A81: 45572 | B81: Eating out | C81: =IFERROR(__xludf.DUMMYFUNCTION("E81*-1"),13.25) -> 13.25 | D81: SQ *PUEBLO QUERIDO COFFEE | E81: -13.25
A82: 45572 | B82: Household Goods | C82: =IFERROR(__xludf.DUMMYFUNCTION("E82*-1"),28.27) -> 28.27 | D82: T.J. MAXX #1569 | E82: -28.27
A83: 45571 | B83: Travel | C83: =IFERROR(__xludf.DUMMYFUNCTION("E83*-1"),51.99) -> 51.99 | D83: SPIRIT AIRL 4870411218226 | E83: -51.99
A84: 45571 | B84: Eating out | C84: 15.5 | D84: TST* BB.Q CHICKEN USA - C | E84: -31.03
A85: 45571 | B85: Eating out | C85: =IFERROR(__xludf.DUMMYFUNCTION("E85*-1"),53.58) -> 53.58 | D85: SQ *LIV BREADS BAKERY | E85: -53.58
A86: 45571 | B86: Gas | C86: =IFERROR(__xludf.DUMMYFUNCTION("E86*-1"),1.5) -> 1.5 | D86: MILLBURN TOWNSHIP | E86: -1.5
A87: 45571 | B87: Eating out | C87: =IFERROR(__xludf.DUMMYFUNCTION("E87*-1"),12.84) -> 12.84 | D87: CACTUS GRILL | E87: -12.84
A88: 45569 | B88: Gas | C88: =IFERROR(__xludf.DUMMYFUNCTION("E88*-1"),2.4) -> 2.4 | D88: MBTA-550005057785-7570 | E88: -2.4
A89: 45568 | B89: Household Goods | C89: =IFERROR(__xludf.DUMMYFUNCTION("E89*-1"),1.25) -> 1.25 | D89: FC FOWLER LAUNDRY ULTRA | E89: -1.25
A90: 45568 | B90: Health | C90: =IFERROR(__xludf.DUMMYFUNCTION("E90*-1"),25.95) -> 25.95 | D90: MIT RECREATION -ONLINE | E90: -25.95
A91: 45568 | B91: Household Goods | C91: =IFERROR(__xludf.DUMMYFUNCTION("E91*-1"),1.25) -> 1.25 | D91: FC FOWLER LAUNDRY ULTRA | E91: -1.25
A92: 45568 | B92: Health | C92: =IFERROR(__xludf.DUMMYFUNCTION("E92*-1"),3.95) -> 3.95 | D92: MIT RECREATION -ONLINE | E92: -3.95
A93: 45568 | B93: Household Goods | C93: =IFERROR(__xludf.DUMMYFUNCTION("E93*-1"),1.25) -> 1.25 | D93: FC FOWLER LAUNDRY ULTRA | E93: -1.25
A94: 45568 | B94: Eating out | C94: =IFERROR(__xludf.DUMMYFUNCTION("E94*-1"),55.88) -> 55.88 | D94: TST*WAYPOINT | E94: -55.88
A95: 45567 | B95: Eating out | C95: =IFERROR(__xludf.DUMMYFUNCTION("E95*-1"),25.02) -> 25.02 | D95: CHICK-FIL-A #04205 | E95: -25.02
A96: 45567 | B96: Bills | C96: =IFERROR(__xludf.DUMMYFUNCTION("E96*-1"),81.2) -> 81.2 | D96: MIT PARKING &amp; TRANS | E96: -81.2
A97: 45589 | B97: Household Goods | C97: 26.47 | D97: AMAZON MKTPL*AM1162X63
A98: 45588 | B98: Household Goods | C98: 78.87 | D98: AMAZON MKTPL*YE9JZ5E63
A99: 45587 | B99: Business School | C99: 25.82 | D99: Amazon.com*IO8E11KO3
A100: 45585 | B100: Fun / Misc | C100: 5.2 | D100: Amazon.com*8I3656JB3
A101: 45585 | B101: Health | C101: 4.65 | D101: Amazon.com*W155A77R3
A102: 45583 | B102: Fun / Misc | C102: 41.4 | D102: Amazon.com*ZA7FZ1DP3
A103: 45582 | B103: Travel | C103: 54.28 | D103: Amazon.com*XR1269FL3
A104: 45582 | B104: Fun / Misc | C104: 55.68 | D104: Amazon.com*LH48J3YG3
...

Sheet November 2024
A4: Monthly Spending | G4: Monthly Overview | J4: Expenses over Time
A5: Category | B5: Budgeted | C5: Amount Spent | D5: Amount Remaining | E5: % Remaining | G5: Income
A6: Fixed | B6: 2663.68 | C6: =sumif($B$20:$C$461,A6,$C$20:$C$461) -> 1666.94 | D6: =B6-C6 -> 996.74 | E6: =D6/B6 -> 0.3741966 | G6: Martin Paycheck | H6: 0
A7: Utilities | B7: 0 | C7: =sumif($B$20:$C$461,A7,$C$20:$C$461) -> 0 | D7: =B7-C7 -> 0 | E7: =D7/B7 -> #DIV/0! | G7: Rachel Paycheck | H7: 4200
A8: Bills | B8: 250 | C8: =sumif($B$20:$C$461,A8,$C$20:$C$461) -> 130 | D8: =B8-C8 -> 120 | E8: =D8/B8 -> 0.48 | G8: Total | H8: =SUM(H6:H7) -> 4200
A9: Groceries | B9: 400 | C9: =sumif($B$20:$C$461,A9,$C$20:$C$461) -> 925.26 | D9: =B9-C9 -> -525.26 | E9: =D9/B9 -> -1.31315
A10: Eating out | B10: 400 | C10: =sumif($B$20:$C$461,A10,$C$20:$C$461) -> 716.97 | D10: =B10-C10 -> -316.97 | E10: =D10/B10 -> -0.792425 | G10: Monthly Expenses
A11: Household Goods | B11: 200 | C11: =sumif($B$20:$C$461,A11,$C$20:$C$461) -> 872.2 | D11: =B11-C11 -> -672.2 | E11: =D11/B11 -> -3.361 | G11: Total Spent | H11: =sum(C17) -> 10759.47
A12: Travel | B12: 500 | C12: =sumif($B$20:$C$461,A12,$C$20:$C$461) -> 5242 | D12: =B12-C12 -> -4742 | E12: =D12/B12 -> -9.484
A13: Gas | B13: 200 | C13: =sumif($B$20:$C$461,A13,$C$20:$C$461) -> 59.04 | D13: =B13-C13 -> 140.96 | E13: =D13/B13 -> 0.7048 | G13: Recurring Expenses
A14: Health | B14: 0 | C14: =sumif($B$20:$C$461,A14,$C$20:$C$461) -> 123 | D14: =B14-C14 -> -123 | E14: =D14/B14 -> #DIV/0! | G14: Car Insurance
A15: Fun / Misc | B15: 300 | C15: =sumif($B$20:$C$461,A15,$C$20:$C$461) -> 1024.06 | D15: =B15-C15 -> -724.06 | E15: =D15/B15 -> -2.4135333
A16: Business School | B16: 0 | C16: =sumif($B$20:$C$461,A16,$C$20:$C$461) -> 0 | D16: =B16-C16 -> 0 | E16: =D16/B16 -> #DIV/0! | G16: Amount spent on Travel | H16: =SUMIF($B$20:$C$175,"Travel",$C$20:$C$175) -> 5242
A17: Total | B17: =SUM(B6:B16) -> 4913.68 | C17: =SUM(C6:C16) -> 10759.47 | D17: =SUM(D6:D15) -> -5845.79 | E17: =D17/B17 -> -1.1896969 | G17: Amount in Travel Bank | H17: =500-SUMIF($B$20:$C$175,"Travel",$C$20:$C$175)+'April 2024'!H17 -> -4238.76
A19: Date | B19: Category | C19: Spent | D19: Note
A20: Monthly | B20: Fixed | C20: 1476 | D20: Rent
A23: Monthly | B23: Fixed | C23: 21 | D23: Exercise
A24: Monthly | B24: Fixed | C24: 40 | D24: Car Insurance | G24: Credit balance (9/29)
A25: Monthly | B25: Fixed | C25: 2.87 | D25: Spotify - Martin | F25: RSB Chase | G25: =8.62+3758.03 -> 3766.65 | H25: 6k from 4668 card
A26: Monthly | B26: Fixed | C26: 2.99 | D26: Google One | F26: RSB Amex | G26: 0
A27: Monthly | B27: Fixed | C27: 5.83 | D27: One Drive | F27: RSB Barclay | G27: 965.33
A28: Monthly | B28: Fixed | C28: 6.25 | D28: MSFT | F28: ML Chase | G28: =274.97+19.17+184.41+1077.59+1829.28 -> 3385.42
A29: Monthly | B29: Fixed | C29: 112 | D29: Phone | F29: ML Amex | G29: =27.87 -> 27.87 | H29: only amex gold
F30: ML Barclay | G30: 1388.4
F31: TOTAL | G31: =SUM(G25:G30) -> 9533.67
F32: Rent | G32: 2900
G33: 8000
A34: 45597 | B34: Fun / Misc | C34: 29 | D34: maldives souveniors | E34: -3.95
A35: 45597 | B35: Eating out | C35: 19.45 | D35: five spice | E35: -1.25
A36: 45597 | B36: Gas | C36: 12.81 | D36: lyft | E36: -55.88
A37: 45597 | B37: Fun / Misc | C37: 300 | D37: acadia trip | E37: -25.02
A38: 45597 | B38: Travel | C38: =556*2 -> 1112 | D38: spain flights | E38: -81.2
A39: 45597 | B39: Household Goods | C39: 7.5 | D39: laundry
A40: 45597 | B40: Eating out | C40: 40 | D40: qiao lin
A41: 45597 | B41: Eating out | C41: 42.84 | D41: bars
A42: 45597 | B42: Gas | C42: 44.3 | D42: lyft
A43: 45597 | B43: Household Goods | C43: 35 | D43: rei
A44: 45597 | B44: Groceries | C44: 10 | D44: hmart
A45: 45597 | B45: Health | C45: 123 | D45: costco glasses
A46: 45597 | B46: Groceries | C46: 202 | D46: costco
A47: 45597 | B47: Eating out | C47: 5.36 | D47: basf lunch
A48: 45597 | B48: Eating out | C48: 5 | D48: mcds
A49: 45597 | B49: Eating out | C49: 7.18 | D49: basf lunch
A50: 45597 | B50: Eating out | C50: 35 | D50: core team lunch pizza
... A77: 45610 | B77: Fun / Misc | C77: 45 | D77: SLOANGROUP* MITSLOANCAMBRIDGE MA
A78: 45611 | C78: 160.88 | D78: BLANTONS AIR PLUMB EFAYETTEVILLE NC
A79: 45611 | B79: Eating out | C79: 98 | D79: NUMBER 1 PHO L.L.C CARY NC
A80: 45611 | B80: Eating out | C80: 20.98 | D80: CHICK-FIL-A #00678 GARNER NC
A81: 45611 | B81: Fun / Misc | C81: 3.21 | D81: GOIN POSTAL - CARY 0CARY NC
A82: 45611 | B82: Household Goods | C82: 10.53 | D82: AMAZON MKTPL*4L5QB4DV3 | E82: Rental Property
A83: 45612 | B83: Household Goods | C83: 71.86 | D83: SEPHORA.COM 877-SEPHORA CA
A84: 45612 | B84: Eating out | C84: 13.7 | D84: ASALI DESSERTS & CAFCary NC
A85: 45612 | B85: Gas | C85: 1.93 | D85: EXXONMOBIL 9903 CARY NC
A86: 45613 | B86: Household Goods | C86: 1.25 | D86: AplPay FC FOWLER LAUUNION NJ
A87: 45614 | B87: Household Goods | C87: 32.16 | D87: AMAZON MKTPL*8B32M1P43
A88: 45615 | B88: Household Goods | C88: 10.71 | D88: AMAZON MARKEPLACE NA PA
A89: 45615 | B89: Household Goods | C89: 6.38 | D89: AMAZON MKTPL*T53X244F3
A90: 45617 | B90: Fun / Misc | C90: 12 | D90: SLOANGROUP* MITSLOANCAMBRIDGE MA
A91: 45617 | B91: Eating out | C91: 10 | D91: AplPay CHIPOTLE 1615CAMBRIDGE MA
A92: 45618 | B92: Household Goods | C92: 33.19 | D92: AMAZON MARKEPLACE NA PA
A93: 45618 | B93: Household Goods | C93: 8.86 | D93: AMZN Mktp US*H96T47F53
A94: 45619 | B94: Household Goods | C94: 39.79 | D94: Dell Bose Speaker
... A114: 45625 | B114: Eating out | C114: 16 | D114: BBQ Chicken
B115: Travel | C115: 35 | D115: Checked Bag - Maldives
B116: Groceries | C116: 65 | D116: Whole Foods
B117: Groceries | C117: 1.99 | D117: Lowes

Sheet December 2024
A4: Monthly Spending | G4: Monthly Overview | J4: Expenses over Time
A5: Category | B5: Budgeted | C5: Amount Spent | D5: Amount Remaining | E5: % Remaining | G5: Income
A6: Fixed | B6: 2663.68 | C6: =sumif($B$20:$C$508,A6,$C$20:$C$508) -> 1666.94 | D6: =B6-C6 -> 996.74 | E6: =D6/B6 -> 0.3741966 | G6: Martin Paycheck | H6: 0
A7: Utilities | B7: 0 | C7: =sumif($B$20:$C$508,A7,$C$20:$C$508) -> 0 | D7: =B7-C7 -> 0 | E7: =D7/B7 -> #DIV/0! | G7: Rachel Paycheck | H7: 4200
A8: Bills | B8: 250 | C8: =sumif($B$20:$C$508,A8,$C$20:$C$508) -> 216.2 | D8: =B8-C8 -> 33.8 | E8: =D8/B8 -> 0.1352 | G8: Total | H8: =SUM(H6:H7) -> 4200
A9: Groceries | B9: 400 | C9: =sumif($B$20:$C$508,A9,$C$20:$C$508) -> 768.13 | D9: =B9-C9 -> -368.13 | E9: =D9/B9 -> -0.920325
A10: Eating out | B10: 400 | C10: =sumif($B$20:$C$508,A10,$C$20:$C$508) -> 1057.36 | D10: =B10-C10 -> -657.36 | E10: =D10/B10 -> -1.6434 | G10: Monthly Expenses
A11: Household Goods | B11: 200 | C11: =sumif($B$20:$C$508,A11,$C$20:$C$508) -> 388.88 | D11: =B11-C11 -> -188.88 | E11: =D11/B11 -> -0.9444 | G11: Total Spent | H11: =sum(C17) -> 5513.97
A12: Travel | B12: 500 | C12: =sumif($B$20:$C$508,A12,$C$20:$C$508) -> 170.98 | D12: =B12-C12 -> 329.02 | E12: =D12/B12 -> 0.65804
A13: Gas | B13: 200 | C13: =sumif($B$20:$C$508,A13,$C$20:$C$508) -> 18.1 | D13: =B13-C13 -> 181.9 | E13: =D13/B13 -> 0.9095 | G13: Recurring Expenses
A14: Health | B14: 0 | C14: =sumif($B$20:$C$508,A14,$C$20:$C$508) -> 34.55 | D14: =B14-C14 -> -34.55 | E14: =D14/B14 -> #DIV/0! | G14: Car Insurance
A15: Fun / Misc | B15: 300 | C15: =sumif($B$20:$C$508,A15,$C$20:$C$508) -> 384.11 | D15: =B15-C15 -> -84.11 | E15: =D15/B15 -> -0.28036667
A16: Business School | B16: 0 | C16: =sumif($B$20:$C$508,A16,$C$20:$C$508) -> 808.72 | D16: =B16-C16 -> -808.72 | E16: =D16/B16 -> #DIV/0! | G16: Amount spent on Travel | H16: =SUMIF($B$20:$C$222,"Travel",$C$20:$C$222) -> 170.98
A17: Total | B17: =SUM(B6:B16) -> 4913.68 | C17: =SUM(C6:C16) -> 5513.97 | D17: =SUM(D6:D15) -> 208.43 | E17: =D17/B17 -> 0.04241831 | G17: Amount in Travel Bank | H17: =500-SUMIF($B$20:$C$222,"Travel",$C$20:$C$222)+'April 2024'!H17 -> 832.26
A19: Date | B19: Category | C19: Spent | D19: Note
A20: Monthly | B20: Fixed | C20: 1476 | D20: Rent
A23: Monthly | B23: Fixed | C23: 21 | D23: Exercise
A24: Monthly | B24: Fixed | C24: 40 | D24: Car Insurance | G24: Credit balance (9/29)
A25: Monthly | B25: Fixed | C25: 2.87 | D25: Spotify - Martin | F25: RSB Chase | G25: =8.62+3758.03 -> 3766.65 | H25: 6k from 4668 card
A26: Monthly | B26: Fixed | C26: 2.99 | D26: Google One | F26: RSB Amex | G26: 0
A27: Monthly | B27: Fixed | C27: 5.83 | D27: One Drive | F27: RSB Barclay | G27: 965.33
A28: Monthly | B28: Fixed | C28: 6.25 | D28: MSFT | F28: ML Chase | G28: =274.97+19.17+184.41+1077.59+1829.28 -> 3385.42
A29: Monthly | B29: Fixed | C29: 112 | D29: Phone | F29: ML Amex | G29: =27.87 -> 27.87 | H29: only amex gold
F30: ML Barclay | G30: 1388.4
F31: TOTAL | G31: =SUM(G25:G30) -> 9533.67
F32: Rent | G32: 2900
G33: 8000
A34: 45627 | B34: Eating out | C34: 38.42 | D34: AplPay ALPACA-APEX 6APEX NC | E34: -1.25
A35: 45627 | B35: Eating out | C35: 10.28 | D35: AplPay ASALI DESSERTCary NC | E35: -21.27
A36: 45627 | B36: Household Goods | C36: 25.7 | D36: AMAZON MKTPL*Z30568ET1 | E36: -15.14
A37: 45627 | B37: Groceries | C37: 9.99 | D37: Amazon Grocery Subscri
A38: 45627 | B38: Household Goods | C38: 26.35 | D38: Amazon.com*Z39471DS0
A39: 45627 | B39: Groceries | C39: 160 | D39: costco
A40: 45627 | B40: Eating out | C40: 47.73 | D40: colombian lunch
A41: 45628 | B41: Household Goods | C41: 11.35 | D41: SAKSFIFTHAVENUE.COM https://www.saksfiftMD
A42: 45629 | B42: Eating out | C42: 5.36 | D42: AplPay BASF CORPORATRESEARCH TRIA NC
A43: 45629 | B43: Household Goods | C43: 1.25 | D43: AplPay FC FOWLER LAUUNION NJ
A44: 45629 | B44: Household Goods | C44: 1.25 | D44: AplPay FC FOWLER LAUUNION NJ
A45: 45629 | B45: Groceries | C45: -7.29 | D45: Amazon.com
A46: 45629 | B46: Groceries | C46: 57.29 | D46: Amazon.com*ZL9J870M2
A47: 45630 | C47: 107.25 | D47: JOE COOL HVAC OF NC RALEIGH NC | E47: Rental Property
A48: 45630 | B48: Groceries | C48: 62.44 | D48: LOWES FOODS #1262 00CARY NC
A49: 45632 | B49: Eating out | C49: 15.8 | D49: AplPay TST* MERA CORMORRISVILLE NC | E49: -25.44
A50: 45633 | C50: 138.73 | D50: Heaters for Tenants | E50: Rental Property
A51: 45648 | B51: Groceries | C51: 15.05 | D51: Instacart | E51: -1.1
A52: 45643 | B52: Eating out | C52: 90 | D52: Rachel dinner - venmo | E52: -30
A53: 45578 | B53: Eating out | C53: =IFERROR(__xludf.DUMMYFUNCTION("E53*-1"),10.69) -> 10.69 | D53: RAISING CANES 0726 | E53: -10.69
A54: 45642 | B54: Household Goods | C54: 11.79 | D54: 32 degree shirts | E54: -81.99
A55: 45578 | B55: Eating out | C55: 60 | D55: TST* KAJU TOFU HOUSE | E55: -91.44
A56: 45578 | B56: Groceries | C56: =IFERROR(__xludf.DUMMYFUNCTION("E56*-1"),79.99) -> 79.99 | D56: WWW COSTCO COM | E56: -79.99
A57: 45654 | B57: Eating out | C57: 100.14 | D57: C&T | E57: -120.75
A58: 45656 | B58: Eating out | C58: 2.27 | D58: water | E58: -1.75
A59: 45656 | B59: Fun / Misc | C59: 141.53 | D59: pimsleur - 1 year | E59: -1.25
A60: 45656 | B60: Business School | C60: 42.9 | D60: PM conference | E60: -1.25
A61: 45576 | B61: Eating out | C61: =IFERROR(__xludf.DUMMYFUNCTION("E61*-1"),9.6) -> 9.6 | D61: COSTCO WHSE #0333 | E61: -9.6
A62: 46018 | B62: Household Goods | C62: 92.12 | D62: michaels - pokemon crafting | E62: -1.25
A63: 46018 | B63: Household Goods | C63: 80.75 | D63: gh bass | E63: -1.25
A64: 45573 | B64: Gas | C64: =IFERROR(__xludf.DUMMYFUNCTION("E64*-1"),2.9) -> 2.9 | D64: MTA*NYCT PAYGO | E64: -2.9
A65: 46017 | B65: Travel | C65: 13.05 | D65: UK visa - RB | E65: -30
A66: 45573 | B66: Gas | C66: =IFERROR(__xludf.DUMMYFUNCTION("E66*-1"),2.9) -> 2.9 | D66: MTA*NYCT PAYGO | E66: -2.9
A67: 45573 | B67: Gas | C67: =IFERROR(__xludf.DUMMYFUNCTION("E67*-1"),2.75) -> 2.75 | D67: PATH TAPP PAYGO CP | E67: -2.75
A68: 45572 | B68: Gas | C68: =IFERROR(__xludf.DUMMYFUNCTION("E68*-1"),2.9) -> 2.9 | D68: MTA*NYCT PAYGO | E68: -2.9
A69: 45572 | B69: Gas | C69: =IFERROR(__xludf.DUMMYFUNCTION("E69*-1"),2.75) -> 2.75 | D69: PATH TAPP PAYGO CP | E69: -2.75
A70: 45572 | B70: Eating out | C70: =IFERROR(__xludf.DUMMYFUNCTION("E70*-1"),13.25) -> 13.25 | D70: SQ *PUEBLO QUERIDO COFFEE | E70: -13.25
A71: 46017 | B71: Travel | C71: 12 | D71: UK visa - ML | E71: -28.27
A72: 45571 | B72: Travel | C72: =IFERROR(__xludf.DUMMYFUNCTION("E72*-1"),51.99) -> 51.99 | D72: SPIRIT AIRL 4870411218226 | E72: -51.99
A73: 45571 | B73: Eating out | C73: 15.5 | D73: TST* BB.Q CHICKEN USA - C | E73: -31.03
A74: 45571 | B74: Eating out | C74: =IFERROR(__xludf.DUMMYFUNCTION("E74*-1"),53.58) -> 53.58 | D74: SQ *LIV BREADS BAKERY | E74: -53.58
A75: 45571 | B75: Gas | C75: =IFERROR(__xludf.DUMMYFUNCTION("E75*-1"),1.5) -> 1.5 | D75: MILLBURN TOWNSHIP | E75: -1.5
A76: 45571 | B76: Eating out | C76: =IFERROR(__xludf.DUMMYFUNCTION("E76*-1"),12.84) -> 12.84 | D76: CACTUS GRILL | E76: -12.84
A77: 45569 | B77: Gas | C77: =IFERROR(__xludf.DUMMYFUNCTION("E77*-1"),2.4) -> 2.4 | D77: MBTA-550005057785-7570 | E77: -2.4
A78: 46012 | B78: Eating out | C78: 28.74 | D78: popeyes RDU | E78: -1.25
A79: 45568 | B79: Health | C79: =IFERROR(__xludf.DUMMYFUNCTION("E79*-1"),25.95) -> 25.95 | D79: MIT RECREATION -ONLINE | E79: -25.95
A80: 46010 | B80: Eating out | C80: 5.36 | D80: BASF lunch | E80: -1.25
A81: 45568 | B81: Health | C81: =IFERROR(__xludf.DUMMYFUNCTION("E81*-1"),3.95) -> 3.95 | D81: MIT RECREATION -ONLINE | E81: -3.95
A82: 46010 | B82: Household Goods | C82: =1.25*8 -> 10 | D82: laundry (lumped) | E82: -1.25
A83: 45568 | B83: Eating out | C83: =IFERROR(__xludf.DUMMYFUNCTION("E83*-1"),55.88) -> 55.88 | D83: TST*WAYPOINT | E83: -55.88
A84: 45567 | B84: Eating out | C84: =IFERROR(__xludf.DUMMYFUNCTION("E84*-1"),25.02) -> 25.02 | D84: CHICK-FIL-A #04205 | E84: -25.02
A85: 45567 | B85: Bills | C85: =IFERROR(__xludf.DUMMYFUNCTION("E85*-1"),81.2) -> 81.2 | D85: MIT PARKING &amp; TRANS | E85: -81.2
A86: 46010 | B86: Eating out | C86: 21.38 | D86: depth and green
A87: 46008 | B87: Eating out | C87: 27.61 | D87: CAVA
A88: 45587 | B88: Business School | C88: 25.82 | D88: Amazon.com*IO8E11KO3
A89: 46006 | B89: Groceries | C89: 115.07 | D89: whole foods
A90: 45585 | B90: Health | C90: 4.65 | D90: Amazon.com*W155A77R3
A91: 46005 | B91: Household Goods | C91: 114 | D91: aritaum - skincare
A92: 45582 | B92: Travel | C92: 54.28 | D92: Amazon.com*XR1269FL3
A93: 46005 | B93: Fun / Misc | C93: 51.68 | D93: movie tickets - RB fam
A94: 45581 | B94: Travel | C94: 39.66 | D94: AMAZON MKTPL*N96BU1HX3
A95: 45578 | B95: Groceries | C95: 44.44 | D95: Amazon.com*Z40R17LD3
A96: 46005 | B96: Eating out | C96: 6.1 | D96: starbucks
A97: 45572 | B97: Groceries | C97: 22 | D97: Whole Foods RVR 10113
... A121: 45997 | B121: Eating out | C121: 15.8 | D121: ready to fly grab and go

Sheet Janunary 2025
A4: Monthly Spending | G4: Monthly Overview | J4: Expenses over Time
A5: Category | B5: Budgeted | C5: Amount Spent | D5: Amount Remaining | E5: % Remaining | G5: Income
A6: Fixed | B6: 2663.68 | C6: =sumif($B$20:$C$582,A6,$C$20:$C$582) -> 1645.94 | D6: =B6-C6 -> 1017.74 | E6: =D6/B6 -> 0.38208043 | G6: Martin Paycheck | H6: 0
A7: Utilities | B7: 0 | C7: =sumif($B$20:$C$582,A7,$C$20:$C$582) -> 0 | D7: =B7-C7 -> 0 | E7: =D7/B7 -> #DIV/0! | G7: Rachel Paycheck | H7: 4200
A8: Bills | B8: 250 | C8: =sumif($B$20:$C$582,A8,$C$20:$C$582) -> 35.05 | D8: =B8-C8 -> 214.95 | E8: =D8/B8 -> 0.8598 | G8: Total | H8: =SUM(H6:H7) -> 4200
A9: Groceries | B9: 400 | C9: =sumif($B$20:$C$582,A9,$C$20:$C$582) -> 283.7 | D9: =B9-C9 -> 116.3 | E9: =D9/B9 -> 0.29075
A10: Eating out | B10: 400 | C10: =sumif($B$20:$C$582,A10,$C$20:$C$582) -> 833.22 | D10: =B10-C10 -> -433.22 | E10: =D10/B10 -> -1.08305 | G10: Monthly Expenses
A11: Household Goods | B11: 200 | C11: =sumif($B$20:$C$582,A11,$C$20:$C$582) -> 642.44 | D11: =B11-C11 -> -442.44 | E11: =D11/B11 -> -2.2122 | G11: Total Spent | H11: =sum(C17) -> 4677.46
A12: Travel | B12: 500 | C12: =sumif($B$20:$C$582,A12,$C$20:$C$582) -> 98.6 | D12: =B12-C12 -> 401.4 | E12: =D12/B12 -> 0.8028
A13: Gas | B13: 200 | C13: =sumif($B$20:$C$582,A13,$C$20:$C$582) -> 62.57 | D13: =B13-C13 -> 137.43 | E13: =D13/B13 -> 0.68715 | G13: Recurring Expenses
A14: Health | B14: 0 | C14: =sumif($B$20:$C$582,A14,$C$20:$C$582) -> 5.21 | D14: =B14-C14 -> -5.21 | E14: =D14/B14 -> #DIV/0! | G14: Car Insurance
A15: Fun / Misc | B15: 300 | C15: =sumif($B$20:$C$582,A15,$C$20:$C$582) -> 1070.73 | D15: =B15-C15 -> -770.73 | E15: =D15/B15 -> -2.5691
A16: Business School | B16: 0 | C16: =sumif($B$20:$C$582,A16,$C$20:$C$582) -> 0 | D16: =B16-C16 -> 0 | E16: =D16/B16 -> #DIV/0! | G16: Amount spent on Travel | H16: =SUMIF($B$20:$C$296,"Travel",$C$20:$C$296) -> 98.6
A17: Total | B17: =SUM(B6:B16) -> 4913.68 | C17: =SUM(C6:C16) -> 4677.46 | D17: =SUM(D6:D15) -> 236.22 | E17: =D17/B17 -> 0.048073949 | G17: Amount in Travel Bank | H17: =500-SUMIF($B$20:$C$296,"Travel",$C$20:$C$296)+'April 2024'!H17 -> 904.64
A19: Date | B19: Category | C19: Spent | D19: Note
A20: Monthly | B20: Fixed | C20: 1476 | D20: Rent
A23: Monthly | B23: Fixed | D23: Exercise
A24: Monthly | B24: Fixed | C24: 40 | D24: Car Insurance | G24: Credit balance (9/29)
A25: Monthly | B25: Fixed | C25: 2.87 | D25: Spotify - Martin | F25: RSB Chase | G25: =8.62+3758.03 -> 3766.65 | H25: 6k from 4668 card
A26: Monthly | B26: Fixed | C26: 2.99 | D26: Google One | F26: RSB Amex | G26: 0
A27: Monthly | B27: Fixed | C27: 5.83 | D27: One Drive | F27: RSB Barclay | G27: 965.33
A28: Monthly | B28: Fixed | C28: 6.25 | D28: MSFT | F28: ML Chase | G28: =274.97+19.17+184.41+1077.59+1829.28 -> 3385.42
A29: Monthly | B29: Fixed | C29: 112 | D29: Phone | F29: ML Amex | G29: =27.87 -> 27.87 | H29: only amex gold
F30: ML Barclay | G30: 1388.4
F31: TOTAL | G31: =SUM(G25:G30) -> 9533.67
F32: Rent | G32: 2900
G33: 8000
A34: 45684 | C34: 355.85 | D34: LEADER
A35: 45668 | B35: Groceries | C35: 159.98 | D35: COSTCO WHSE #1206
A36: 45680 | B36: Household Goods | C36: 127.48 | D36: UA.COM*888-727-6687 MD
A37: 45685 | B37: Household Goods | C37: 97.98 | D37: CIE MONT BLANC
A38: 45662 | B38: Travel | C38: 59.35 | D38: FLIX
A39: 45661 | B39: Household Goods | C39: 56.28 | D39: AMAZON MKTPL*ZP90O0JJ1
A40: 45684 | B40: Fun / Misc | C40: 55.36 | D40: BREVENT
A41: 45663 | B41: Fun / Misc | C41: 51.14 | D41: Intersport France
A42: 45666 | B42: Household Goods | C42: 43.11 | D42: AMAZON MKTPL*Z530Q2E12
A43: 45667 | B43: Fun / Misc | C43: 39.32 | D43: Intersport France
A44: 45684 | B44: Eating out | C44: 38.89 | D44: KORKE
A45: 45660 | B45: Groceries | C45: 38.01 | D45: Amazon.com*ZP6IX2M70
A46: 45658 | B46: Fun / Misc | C46: 34.8 | D46: ERACTOLL 365582154
... A95: 45665 | B95: Eating out | C95: 5.36 | D95: AplPay BASF CORPORATRESEARCH TRIA NC
A96: 45666 | B96: Eating out | C96: 5.36 | D96: AplPay BASF CORPORATRESEARCH TRIA NC | E96: -30
A97: 45681 | B97: Travel | C97: 5.39 | D97: AplPay AMZ*UXBEWTK3REAST RUTHERFORD NJ | E97: -10.69
A98: 45688 | B98: Fun / Misc | C98: 6.84 | D98: AplPay TFL TRAVEL CHTFL.GOV.UK/CP GB | E98: -81.99
A99: 45686 | B99: Eating out | C99: 7.35 | D99: caafe tartine | E99: -91.44
A100: 45686 | B100: Fun / Misc | C100: 8.19 | D100: Souveniers | E100: -120.75
A101: 45682 | B101: Fun / Misc | C101: 10 | D101: AplPay AIRALO SINGAPORE SG | E101: -1.75
A102: 45672 | B102: Fun / Misc | C102: 10.65 | D102: hulu | E102: -1.25
A103: 45675 | B103: Eating out | C103: 11.09 | D103: AplPay ORDER BAGELS,Raleigh NC | E103: -1.25
A104: 45658 | B104: Household Goods | C104: 13.28 | D104: AplPay SP ANOVA CULISAN FRANCISCO CA | E104: -9.6
A105: 45674 | B105: Eating out | C105: 14.98 | D105: AplPay 10078 CAVA KECAMBRIDGE MA | E105: -1.25
A106: 45686 | B106: Eating out | C106: 16.27 | D106: cham thai | E106: -2.9
A107: 45687 | B107: Fun / Misc | C107: 16.6 | D107: AplPay TFL TRAVEL CHTFL.GOV.UK/CP GB | E107: -30
... A124: 45686 | B124: Household Goods | C124: 104.95 | D124: PHARMACIE DU MONT BLCHAMONIX MONT BLANC HT | E124: -25.02
A125: 45681 | B125: Eating out | C125: =52.8+4.33+103.33 -> 160.46 | D125: chamonix venmos | E125: -81.2
A126: 45685 | B126: Fun / Misc | C126: 176.99 | D126: AplPay QC TERME CHAMCHAMONIX-MONT-BLANC FR
A127: 45668 | B127: Fun / Misc | C127: 330 | D127: SP ZBIOTICS SAN FRANCISCO CA

Sheet Feb 2025
A4: Monthly Spending | G4: Monthly Overview | J4: Expenses over Time
A5: Category | B5: Budgeted | C5: Amount Spent | D5: Amount Remaining | E5: % Remaining | G5: Income
A6: Fixed | B6: 2663.68 | C6: =sumif($B$20:$C$562,A6,$C$20:$C$562) -> 1732.69 | D6: =B6-C6 -> 930.99 | E6: =D6/B6 -> 0.3495127 | G6: Martin Paycheck | H6: 0
A7: Utilities | B7: 0 | C7: =sumif($B$20:$C$562,A7,$C$20:$C$562) -> 0 | D7: =B7-C7 -> 0 | E7: =D7/B7 -> #DIV/0! | G7: Rachel Paycheck | H7: 4200
A8: Bills | B8: 250 | C8: =sumif($B$20:$C$562,A8,$C$20:$C$562) -> 0 | D8: =B8-C8 -> 250 | E8: =D8/B8 -> 1 | G8: Total | H8: =SUM(H6:H7) -> 4200
A9: Groceries | B9: 400 | C9: =sumif($B$20:$C$562,A9,$C$20:$C$562) -> 750.21 | D9: =B9-C9 -> -350.21 | E9: =D9/B9 -> -0.875525
A10: Eating out | B10: 400 | C10: =sumif($B$20:$C$562,A10,$C$20:$C$562) -> 1233.69 | D10: =B10-C10 -> -833.69 | E10: =D10/B10 -> -2.084225 | G10: Monthly Expenses
A11: Household Goods | B11: 200 | C11: =sumif($B$20:$C$562,A11,$C$20:$C$562) -> 418.3 | D11: =B11-C11 -> -218.3 | E11: =D11/B11 -> -1.0915 | G11: Total Spent | H11: =sum(C17) -> 4843.64
A12: Travel | B12: 500 | C12: =sumif($B$20:$C$562,A12,$C$20:$C$562) -> 459.39 | D12: =B12-C12 -> 40.61 | E12: =D12/B12 -> 0.08122
A13: Gas | B13: 200 | C13: =sumif($B$20:$C$562,A13,$C$20:$C$562) -> 69.53 | D13: =B13-C13 -> 130.47 | E13: =D13/B13 -> 0.65235 | G13: Recurring Expenses
A14: Health | B14: 0 | C14: =sumif($B$20:$C$562,A14,$C$20:$C$562) -> 80 | D14: =B14-C14 -> -80 | E14: =D14/B14 -> #DIV/0! | G14: Car Insurance
A15: Fun / Misc | B15: 300 | C15: =sumif($B$20:$C$562,A15,$C$20:$C$562) -> 99.83 | D15: =B15-C15 -> 200.17 | E15: =D15/B15 -> 0.66723333
A16: Business School | B16: 0 | C16: =sumif($B$20:$C$562,A16,$C$20:$C$562) -> 0 | D16: =B16-C16 -> 0 | E16: =D16/B16 -> #DIV/0! | G16: Amount spent on Travel | H16: =SUMIF($B$20:$C$276,"Travel",$C$20:$C$276) -> 459.39
A17: Total | B17: =SUM(B6:B16) -> 4913.68 | C17: =SUM(C6:C16) -> 4843.64 | D17: =SUM(D6:D15) -> 70.04 | E17: =D17/B17 -> 0.014254082 | G17: Amount in Travel Bank | H17: =500-SUMIF($B$20:$C$276,"Travel",$C$20:$C$276)+'April 2024'!H17 -> 543.85
A19: Date | B19: Category | C19: Spent | D19: Note
A20: Monthly | B20: Fixed | C20: 1476 | D20: Rent
A23: Monthly | B23: Fixed | C23: 87 | D23: Exercise
A24: Monthly | B24: Fixed | C24: 40 | D24: Car Insurance | G24: Credit balance (9/29)
A25: Monthly | B25: Fixed | C25: 2.87 | D25: Spotify - Martin | F25: RSB Chase | G25: =8.62+3758.03 -> 3766.65 | H25: 6k from 4668 card
A26: Monthly | B26: Fixed | C26: 2.99 | D26: Google One | F26: RSB Amex | G26: 0
A27: Monthly | B27: Fixed | C27: 5.83 | D27: One Drive | F27: RSB Barclay | G27: 965.33
A28: Monthly | B28: Fixed | C28: 6 | D28: Amazon | F28: ML Chase | G28: =274.97+19.17+184.41+1077.59+1829.28 -> 3385.42
A29: Monthly | B29: Fixed | C29: 112 | D29: Phone | F29: ML Amex | G29: =27.87 -> 27.87 | H29: only amex gold
F30: ML Barclay | G30: 1388.4
F31: TOTAL | G31: =SUM(G25:G30) -> 9533.67
F32: Rent | G32: 2900
G33: 8000
A34: 45695 | B34: Groceries | C34: =633-85 -> 548 | D34: Costco
A35: 45700 | B35: Travel | C35: 388 | D35: BREEZE AIRWAU7F59J
A36: 45692 | B36: Eating out | C36: 349.81 | D36: JONGRO BBQ
A37: 45700 | B37: Household Goods | C37: 165.91 | D37: DERMSTORE DERMSTORE UNITED STATES
A38: 45701 | B38: Household Goods | C38: 132.75 | D38: HIGHSNOBIETY
A39: 45696 | B39: Eating out | C39: 109.65 | D39: H MART CARY LLC 1432CARY NC
A40: 45694 | B40: Eating out | C40: 109.39 | D40: NUMBER 1 PHO L.L.C CARY NC
A41: 2/8/0256 | B41: Groceries | C41: 101.79 | D41: costco
A42: 45690 | B42: Eating out | C42: 98.72 | D42: OKJA 436845560044108CARY NC
A43: 45689 | B43: Eating out | C43: 97.02 | D43: SUNDAY*Dishoom Shoreditch
A44: 45690 | B44: Travel | C44: 83.57 | D44: UBR* PENDING.UBER.COM
A45: 45701 | B45: Gas | C45: 67.13 | D45: 7-ELEVEN 41993 00074CARY NC
A46: 45689 | B46: Fun / Misc | C46: 50.5 | D46: justin baby gift
A47: 45690 | B47: Groceries | C47: 46.8 | D47: Amazon.com*ZC5R26261
A48: 45693 | B48: Health | C48: 40 | D48: DUKE OTOLARYNGOLOGY RALEIGH NC
A49: 45700 | B49: Health | C49: 40 | D49: DUKE OTOLARYNGOLOGY RALEIGH NC
A50: 45697 | B50: Groceries | C50: 38.37 | D50: Amazon.com*TX4YB0Z63
A51: 45699 | B51: Fun / Misc | C51: 33.23 | D51: The Paper Store
A52: 45703 | B52: Eating out | C52: 31.38 | D52: bos
A53: 45690 | B53: Eating out | C53: 31.11 | D53: AplPay BRIDGE BAR & HOUNSLOW GB
... A90: 45716 | B90: Fun / Misc | C90: 0.99 | D90: APPLE.COM/BILL
E105: -1.1
E106: -30
E107: -10.69
E108: -81.99
E109: -91.44
E110: -79.99
E111: -120.75
E112: -1.75
E113: -1.25
E114: -1.25
E115: -9.6
E116: -1.25
... E139: -81.2

Sheet March 2025
A4: Monthly Spending | G4: Monthly Overview | J4: Expenses over Time
A5: Category | B5: Budgeted | C5: Amount Spent | D5: Amount Remaining | E5: % Remaining | G5: Income
A6: Fixed | B6: 2663.68 | C6: =sumif($B$20:$C$543,A6,$C$20:$C$543) -> 1732.69 | D6: =B6-C6 -> 930.99 | E6: =D6/B6 -> 0.3495127 | G6: Martin Paycheck | H6: 0
A7: Utilities | B7: 0 | C7: =sumif($B$20:$C$543,A7,$C$20:$C$543) -> 0 | D7: =B7-C7 -> 0 | E7: =D7/B7 -> #DIV/0! | G7: Rachel Paycheck | H7: 3566
A8: Bills | B8: 250 | C8: =sumif($B$20:$C$543,A8,$C$20:$C$543) -> 0 | D8: =B8-C8 -> 250 | E8: =D8/B8 -> 1 | G8: Total | H8: =SUM(H6:H7) -> 3566
A9: Groceries | B9: 400 | C9: =sumif($B$20:$C$543,A9,$C$20:$C$543) -> 393.81 | D9: =B9-C9 -> 6.19 | E9: =D9/B9 -> 0.015475
A10: Eating out | B10: 400 | C10: =sumif($B$20:$C$543,A10,$C$20:$C$543) -> 3116.06 | D10: =B10-C10 -> -2716.06 | E10: =D10/B10 -> -6.79015 | G10: Monthly Expenses
A11: Household Goods | B11: 200 | C11: =sumif($B$20:$C$543,A11,$C$20:$C$543) -> 5277.44 | D11: =B11-C11 -> -5077.44 | E11: =D11/B11 -> -25.3872 | G11: Total Spent | H11: =sum(C17) -> 11737.64
A12: Travel | B12: 500 | C12: =sumif($B$20:$C$543,A12,$C$20:$C$543) -> 406.09 | D12: =B12-C12 -> 93.91 | E12: =D12/B12 -> 0.18782
A13: Gas | B13: 200 | C13: =sumif($B$20:$C$543,A13,$C$20:$C$543) -> 247.49 | D13: =B13-C13 -> -47.49 | E13: =D13/B13 -> -0.23745 | G13: Recurring Expenses
A14: Health | B14: 0 | C14: =sumif($B$20:$C$543,A14,$C$20:$C$543) -> 250.46 | D14: =B14-C14 -> -250.46 | E14: =D14/B14 -> #DIV/0! | G14: Car Insurance
A15: Fun / Misc | B15: 300 | C15: =sumif($B$20:$C$543,A15,$C$20:$C$543) -> 313.6 | D15: =B15-C15 -> -13.6 | E15: =D15/B15 -> -0.045333333
A16: Business School | B16: 0 | C16: =sumif($B$20:$C$543,A16,$C$20:$C$543) -> 0 | D16: =B16-C16 -> 0 | E16: =D16/B16 -> #DIV/0! | G16: Amount spent on Travel | H16: =SUMIF($B$20:$C$257,"Travel",$C$20:$C$257) -> 406.09
A17: Total | B17: =SUM(B6:B16) -> 4913.68 | C17: =SUM(C6:C16) -> 11737.64 | D17: =SUM(D6:D15) -> -6823.96 | E17: =D17/B17 -> -1.3887677 | G17: Amount in Travel Bank | H17: =500-SUMIF($B$20:$C$257,"Travel",$C$20:$C$257)+'April 2024'!H17 -> 597.15
A19: Date | B19: Category | C19: Spent | D19: Note
A20: Monthly | B20: Fixed | C20: 1476 | D20: Rent
A21: Monthly | B21: Fixed | C21: 87 | D21: Exercise
A22: Monthly | B22: Fixed | C22: 40 | D22: Car Insurance
A23: Monthly | B23: Fixed | C23: 2.87 | D23: Spotify - Martin
A24: Monthly | B24: Fixed | C24: 2.99 | D24: Google One
A25: Monthly | B25: Fixed | C25: 5.83 | D25: One Drive
A26: Monthly | B26: Fixed | C26: 6 | D26: Amazon
A27: Monthly | B27: Fixed | C27: 112 | D27: Phone
A32: 45718 | B32: Groceries | C32: =200 -> 200 | D32: COSTCO WHSE #0333
A33: 45718 | B33: Household Goods | C33: 10.61 | D33: AMAZON MKTPL*V62EI9PM3
A34: 45718 | B34: Groceries | C34: 9.99 | D34: Amazon Grocery Subscri
A35: 45718 | B35: Health | C35: 49 | D35: TRIANGLE FAMILY EYE CARE
A36: 45719 | B36: Eating out | C36: 16.65 | D36: SQ *KILLER POBOYS
A37: 45720 | B37: Household Goods | C37: 35.42 | D37: WALGREENS #4305
A38: 45720 | B38: Fun / Misc | C38: 80 | D38: TCKTWEB*BRADWALKERBRIA
A39: 45720 | B39: Eating out | C39: 30 | D39: PAT O BRIENS PATIO/HUR
A40: 45721 | B40: Eating out | C40: 93.77 | D40: ZESTY CREOLE
A41: 45721 | B41: Eating out | C41: 21.35 | D41: DINGTEA DOWNTOWN
A42: 45721 | B42: Eating out | C42: 52 | D42: ARNAUDS
A43: 45722 | B43: Eating out | C43: 103.34 | D43: MULAN TAIWANESE RESTAURAN
A44: 45722 | B44: Eating out | C44: 46.27 | D44: ZESTY CREOLE
... A95: 45739 | B95: Fun / Misc | C95: 8.01 | D95: AIRALO
A96: 45739 | B96: Eating out | C96: 13.36 | D96: ROLLERIE | E96: -1.1
A97: 45739 | B97: Fun / Misc | C97: 8.5 | D97: AIRALO | E97: -30
A98: 45739 | B98: Gas | C98: 24.91 | D98: UBR* PENDING.UBER.COM | E98: -10.69
A99: 45739 | B99: Eating out | C99: 5 | D99: EXPHORTALV | E99: -81.99
A100: 45739 | B100: Household Goods | C100: 1.25 | D100: FC FOWLER LAUNDRY ULTRA | E100: -91.44
A101: 45739 | B101: Eating out | C101: 27 | D101: SHAKE SHACK C25 BOS | E101: -79.99
A102: 45739 | B102: Household Goods | C102: 1.25 | D102: FC FOWLER LAUNDRY ULTRA | E102: -120.75
A103: 45739 | B103: Eating out | C103: 8.69 | D103: EL BAROGRAFO | E103: -1.75
A104: 45740 | B104: Gas | C104: 2.39 | D104: RENFE CERCANIAS TNA 28 5 | E104: -1.25
A105: 45740 | B105: Gas | C105: 9.23 | D105: METRO DE MADRID S.A. | E105: -1.25
A106: 45740 | B106: Gas | C106: 2.39 | D106: RENFE CERCANIAS TNA 28 5 | E106: -9.6
A107: 45740 | B107: Eating out | C107: 16.84 | D107: EXPCMONTE9 | E107: -1.25
... A130: 45743 | B130: Gas | C130: 4.77 | D130: RENFE CERCANIAS TNA 28 5 | E130: -81.2
A131: 45743 | B131: Eating out | C131: 36.83 | D131: PARKING PIZZA MARIMON
A132: 45743 | B132: Eating out | C132: 12.08 | D132: JOBROCO SL
A133: 45743 | B133: Fun / Misc | C133: 7.34 | D133: AIRALO
A134: 45744 | B134: Eating out | C134: 11.83 | D134: LAIETANA DE LLIBRETERIA
A135: 45744 | B135: Eating out | C135: 220.51 | D135: ARROSSERIA XATIVA BCN 194
A136: 45744 | B136: Eating out | C136: 4.05 | D136: EXPRESS MARINA 2
A137: 45746 | B137: Eating out | C137: 19.37 | D137: MCDONALDS AEROPUERTO PRAT
A138: 45746 | B138: Eating out | C138: 7.38 | D138: EL CORTE INGLES DIAGONAL
A139: 45746 | B139: Eating out | C139: 4.07 | D139: EL CORTE INGLES DIAGONAL
A140: 45746 | B140: Eating out | C140: 0.8 | D140: EL CORTE INGLES DIAGONAL
A141: 45746 | B141: Eating out | C141: 5.34 | D141: SORLI TRAVESSERA DE DALT
A142: 45746 | B142: Fun / Misc | C142: 32.75 | D142: SUP. EX. GRAN D
... A155: 45735 | B155: Health | C155: 201.46 | D155: DUKE HEALTH MYCHART DURHAM NC

Sheet April 2025
A4: Monthly Spending | G4: Monthly Overview | J4: Expenses over Time
A5: Category | B5: Budgeted | C5: Amount Spent | D5: Amount Remaining | E5: % Remaining | G5: Income
A6: Fixed | B6: 2663.68 | C6: =sumif($B$20:$C$554,A6,$C$20:$C$554) -> 1732.69 | D6: =B6-C6 -> 930.99 | E6: =D6/B6 -> 0.3495127 | G6: Martin Paycheck | H6: 0
A7: Utilities | B7: 0 | C7: =sumif($B$20:$C$554,A7,$C$20:$C$554) -> 0 | D7: =B7-C7 -> 0 | E7: =D7/B7 -> #DIV/0! | G7: Rachel Paycheck | H7: 3038
A8: Bills | B8: 250 | C8: =sumif($B$20:$C$554,A8,$C$20:$C$554) -> 4441.23 | D8: =B8-C8 -> -4191.23 | E8: =D8/B8 -> -16.76492 | G8: Total | H8: =SUM(H6:H7) -> 3038
A9: Groceries | B9: 400 | C9: =sumif($B$20:$C$554,A9,$C$20:$C$554) -> 838.37 | D9: =B9-C9 -> -438.37 | E9: =D9/B9 -> -1.095925
A10: Eating out | B10: 400 | C10: =sumif($B$20:$C$554,A10,$C$20:$C$554) -> 702.67375 | D10: =B10-C10 -> -302.67375 | E10: =D10/B10 -> -0.75668437 | G10: Monthly Expenses
A11: Household Goods | B11: 200 | C11: =sumif($B$20:$C$554,A11,$C$20:$C$554) -> -292.05 | D11: =B11-C11 -> 492.05 | E11: =D11/B11 -> 2.46025 | G11: Total Spent | H11: =sum(C17) -> 9264.2671
A12: Travel | B12: 500 | C12: =sumif($B$20:$C$554,A12,$C$20:$C$554) -> 285.64333 | D12: =B12-C12 -> 214.35667 | E12: =D12/B12 -> 0.42871333
A13: Gas | B13: 200 | C13: =sumif($B$20:$C$554,A13,$C$20:$C$554) -> 108.31 | D13: =B13-C13 -> 91.69 | E13: =D13/B13 -> 0.45845 | G13: Recurring Expenses
A14: Health | B14: 0 | C14: =sumif($B$20:$C$554,A14,$C$20:$C$554) -> 912.06 | D14: =B14-C14 -> -912.06 | E14: =D14/B14 -> #DIV/0! | G14: Car Insurance
A15: Fun / Misc | B15: 300 | C15: =sumif($B$20:$C$554,A15,$C$20:$C$554) -> 535.34 | D15: =B15-C15 -> -235.34 | E15: =D15/B15 -> -0.78446667
A16: Business School | B16: 0 | C16: =sumif($B$20:$C$554,A16,$C$20:$C$554) -> 0 | D16: =B16-C16 -> 0 | E16: =D16/B16 -> #DIV/0! | G16: Amount spent on Travel | H16: =SUMIF($B$20:$C$268,"Travel",$C$20:$C$268) -> 285.64333
A17: Total | B17: =SUM(B6:B16) -> 4913.68 | C17: =SUM(C6:C16) -> 9264.2671 | D17: =SUM(D6:D15) -> -4350.5871 | E17: =D17/B17 -> -0.88540301 | G17: Amount in Travel Bank | H17: =500-SUMIF($B$20:$C$268,"Travel",$C$20:$C$268)+'April 2024'!H17 -> 717.59667
A19: Date | B19: Category | C19: Spent | D19: Note
A20: Monthly | B20: Fixed | C20: 1476 | D20: Rent
A21: Monthly | B21: Fixed | C21: 87 | D21: Exercise
A22: Monthly | B22: Fixed | C22: 40 | D22: Car Insurance
A23: Monthly | B23: Fixed | C23: 2.87 | D23: Spotify - Martin
A24: Monthly | B24: Fixed | C24: 2.99 | D24: Google One
A25: Monthly | B25: Fixed | C25: 5.83 | D25: One Drive
A26: Monthly | B26: Fixed | C26: 6 | D26: Amazon
A27: Monthly | B27: Fixed | C27: 112 | D27: Phone
A32: 45748 | B32: Household Goods | C32: -699.47 | D32: Refund Globalblue.com
A33: 45749 | B33: Groceries | C33: 327.11 | D33: COSTCO WHSE #0333
A34: 45749 | B34: Gas | C34: 2.4 | D34: MBTA-550009347976-0515
A35: 45750 | B35: Eating out | C35: -2.16 | D35: Offer:Domino's
A36: 45750 | B36: Eating out | C36: 12.94 | D36: TST*TASTY BURGER - HARVA
A37: 45750 | B37: Household Goods | C37: -7.49 | D37: Amazon.com
A38: 45751 | B38: Household Goods | C38: 1.25 | D38: FC FOWLER LAUNDRY ULTRA
A39: 45751 | B39: Eating out | C39: 11.01 | D39: Whole Foods RVR 10113
A40: 45751 | B40: Household Goods | C40: 38.15 | D40: Amazon.com*V190J21X3
A41: 45753 | C41: 37.54 | D41: INTUIT *TURBOTAX
A42: 45753 | B42: Household Goods | C42: 10.61 | D42: AMAZON MKTPL*D82J11NU3
A43: 45753 | B43: Household Goods | C43: -2.89 | D43: Amazon.com
A44: 45754 | B44: Bills | C44: 25 | D44: INTUIT *TURBOTAX
A45: 45754 | B45: Eating out | C45: 34.01 | D45: DOMINO'S 3748
A46: 45754 | B46: Household Goods | C46: 12.75 | D46: Amazon.com*Q96ME1VZ3
A47: 45755 | B47: Household Goods | C47: 139.26 | D47: CRYSTAL TAILOR AND CLEAN
A48: 45755 | B48: Household Goods | C48: 90.84 | D48: CJ_OLIVE YOUNG
A49: 45756 | B49: Eating out | C49: 3 | D49: Nyx*Koury Vending LLC
A50: 45756 | C50: 1.99 | D50: GOOGLE *Google One
A51: 45756 | B51: Eating out | C51: 6.75 | D51: BASF CORPORATION CAFE
A52: 45756 | B52: Bills | C52: 4195 | D52: US TREAS TAX PYMT
A53: 45756 | B53: Bills | C53: 73.41 | D53: SERVICE FEE
A54: 45757 | B54: Household Goods | C54: 11.2 | D54: Amazon.com*899136KJ3
A55: 45757 | B55: Eating out | C55: 6.75 | D55: BASF CORPORATION CAFE
A56: 45757 | B56: Fun / Misc | C56: 30 | D56: SLOANGROUP* MITSLOAN/K
A57: 45757 | B57: Fun / Misc | C57: 125 | D57: SLOANGROUP* MITSLOAN/S
A58: 45758 | B58: Gas | C58: 2.25 | D58: PARKING METERS PILOT PROG
A59: 45758 | B59: Fun / Misc | C59: =25 -> 25 | D59: 4UP*BROOKLINE GOLF
A60: 45760 | B60: Eating out | C60: 0 | D60: TST*SUMIAO XIANG RESTAUR
A61: 45760 | B61: Eating out | C61: =173.79/8 -> 21.72375 | D61: TST*MY HAPPY HUNAN KITCH
A62: 45761 | B62: Fun / Misc | C62: =1012.02/3 -> 337.34 | D62: AIRBNB * HM5P34QRAK
A63: 45761 | B63: Gas | C63: 12.75 | D63: SPOTHERO 844-356-8054
A64: 45761 | B64: Gas | C64: 42.96 | D64: EXXON BULL MARKET 108
A65: 45761 | B65: Bills | C65: 3.91 | D65: PIRATE SHIP * POSTAGE
A66: 45761 | B66: Eating out | C66: 18.91 | D66: MCDONALD'S F17721
A67: 45761 | B67: Bills | C67: 3.91 | D67: PIRATE SHIP * POSTAGE
A68: 45762 | B68: Household Goods | C68: 8.53 | D68: AMAZON MKTPL*F95HE5DM3
A69: 45763 | B69: Groceries | C69: 80.8 | D69: Amazon.com*WM4845Z63
A70: 45763 | B70: Groceries | C70: 146.89 | D70: IC* COSTCO BY INSTACAR
A71: 45763 | B71: Health | C71: 128.16 | D71: TRIANGLE FAMILY EYE CARE
A72: 45763 | B72: Eating out | C72: 9.13 | D72: BASF CAFE
A73: 45764 | B73: Household Goods | C73: 1.25 | D73: FC FOWLER LAUNDRY ULTRA
A74: 45764 | B74: Household Goods | C74: 1.25 | D74: FC FOWLER LAUNDRY ULTRA
... A84: 45767 | B84: Household Goods | C84: -5.59 | D84: Amazon.com
A85: 45767 | B85: Groceries | C85: =17 -> 17 | D85: LS THE COUNTRY STORE
A86: 45767 | B86: Household Goods | C86: 31.33 | D86: TARGET.COM *
A87: 45767 | B87: Eating out | C87: =24 -> 24 | D87: TST* BB.Q CHICKEN USA - C
A88: 45768 | B88: Gas | C88: 5.34 | D88: EXXON MEMORIAL DRIVE A
A89: 45768 | B89: Gas | C89: 33.07 | D89: EXXON MEMORIAL DRIVE A
A90: 45769 | B90: Travel | C90: =231.03/3 -> 77.01 | D90: AVIS RENT-A-CAR
A91: 45769 | B91: Gas | C91: 4.99 | D91: UBER *ONE
A92: 45769 | B92: Eating out | C92: 17.93 | D92: McDonalds 1147
A93: 45769 | B93: Eating out | C93: 177.5 | D93: TST*SZECHUAN MOUNTAIN HO
A94: 45769 | B94: Eating out | C94: 8.55 | D94: HEYTEA ALLSTON
A95: 45769 | B95: Eating out | C95: 4.55 | D95: TST* FLOUR BAKERY + CAFE
A96: 45770 | B96: Travel | C96: 258.75 | D96: HYATT REGENCY CAMBRIDGE
A97: 45770 | B97: Travel | C97: -23.19 | D97: HYATT REGENCY CAMBRIDGE
A98: 45771 | B98: Eating out | C98: 8.69 | D98: BASF CORPORATION CAFE
A99: 45772 | B99: Travel | C99: -32.41 | D99: HYATT REGENCY CAMBRIDGE
A100: 45772 | B100: Eating out | C100: 21.39 | D100: RAISING CANES 0676 | E100: -1.1
A101: 45772 | B101: Eating out | C101: 8.69 | D101: BASF CORPORATION CAFE | E101: -30
A102: 45772 | B102: Eating out | C102: 8.5 | D102: TST*FULLSTEAM BREWERY AT | E102: -10.69
A103: 45774 | B103: Fun / Misc | C103: 18 | D103: BROOKLINE GOLF CLUB | E103: -81.99
A104: 45774 | B104: Eating out | C104: 7.43 | D104: TST*TEN ONE TEAHOUSE NEW | E104: -91.44
A105: 45774 | B105: Eating out | C105: =50 -> 50 | D105: TST*KOREAN GARDEN RESTAU | E105: -79.99
A106: 45774 | B106: Eating out | C106: 45.96 | D106: BB* BB.Q CHICKEN KENMO | E106: -120.75
A107: 45774 | B107: Eating out | C107: 120.67 | D107: NUMBER 1 PHO L.L.C | E107: -1.75
A108: 45775 | B108: Bills | C108: 0.99 | D108: APPLE.COM/BILL | E108: -1.25
A109: 45776 | B109: Household Goods | C109: 1.25 | D109: FC FOWLER LAUNDRY ULTRA | E109: -1.25
A110: 45776 | B110: Household Goods | C110: 1.25 | D110: FC FOWLER LAUNDRY ULTRA | E110: -9.6
A111: 45776 | B111: Household Goods | C111: 1.25 | D111: FC FOWLER LAUNDRY ULTRA | E111: -1.25
A112: 45776 | B112: Household Goods | C112: 1.25 | D112: FC FOWLER LAUNDRY ULTRA | E112: -1.25
A113: 45776 | B113: Household Goods | C113: 1.25 | D113: FC FOWLER LAUNDRY ULTRA | E113: -2.9
A114: 45776 | B114: Groceries | C114: 74.42 | D114: Amazon.com*NB0ZL3012 | E114: -30
A115: 45776 | B115: Groceries | C115: -17.84 | D115: Amazon.com | E115: -2.9
A116: 45776 | B116: Eating out | C116: 50.84 | D116: SASSOOL - CARY | E116: -2.75
A117: 45777 | B117: Travel | C117: =16.45/3 -> 5.4833333 | D117: ETOLLAVIS U350737155 | E117: -2.9
...

Sheet May 2025
A4: Monthly Spending | G4: Monthly Overview | J4: Expenses over Time
A5: Category | B5: Budgeted | C5: Amount Spent | D5: Amount Remaining | E5: % Remaining | G5: Income
A6: Fixed | B6: 2663.68 | C6: =sumif($B$20:$C$557,A6,$C$20:$C$557) -> 1772.3567 | D6: =B6-C6 -> 891.32333 | E6: =D6/B6 -> 0.33462103 | G6: Martin Paycheck | H6: 0
A7: Utilities | B7: 0 | C7: =sumif($B$20:$C$557,A7,$C$20:$C$557) -> 0 | D7: =B7-C7 -> 0 | E7: =D7/B7 -> #DIV/0! | G7: Rachel Paycheck | H7: 3038
A8: Bills | B8: 250 | C8: =sumif($B$20:$C$557,A8,$C$20:$C$557) -> 503.66 | D8: =B8-C8 -> -253.66 | E8: =D8/B8 -> -1.01464 | G8: Total | H8: =SUM(H6:H7) -> 3038
A9: Groceries | B9: 400 | C9: =sumif($B$20:$C$557,A9,$C$20:$C$557) -> 368.33 | D9: =B9-C9 -> 31.67 | E9: =D9/B9 -> 0.079175
A10: Eating out | B10: 400 | C10: =sumif($B$20:$C$557,A10,$C$20:$C$557) -> 664.37 | D10: =B10-C10 -> -264.37 | E10: =D10/B10 -> -0.660925 | G10: Monthly Expenses
A11: Household Goods | B11: 200 | C11: =sumif($B$20:$C$557,A11,$C$20:$C$557) -> 398.93 | D11: =B11-C11 -> -198.93 | E11: =D11/B11 -> -0.99465 | G11: Total Spent | H11: =sum(C17) -> 6048.5467
A12: Travel | B12: 500 | C12: =sumif($B$20:$C$557,A12,$C$20:$C$557) -> 1453.26 | D12: =B12-C12 -> -953.26 | E12: =D12/B12 -> -1.90652
A13: Gas | B13: 200 | C13: =sumif($B$20:$C$557,A13,$C$20:$C$557) -> 257.91 | D13: =B13-C13 -> -57.91 | E13: =D13/B13 -> -0.28955 | G13: Recurring Expenses
A14: Health | B14: 0 | C14: =sumif($B$20:$C$557,A14,$C$20:$C$557) -> 0 | D14: =B14-C14 -> 0 | E14: =D14/B14 -> #DIV/0! | G14: Car Insurance
A15: Fun / Misc | B15: 300 | C15: =sumif($B$20:$C$557,A15,$C$20:$C$557) -> 629.73 | D15: =B15-C15 -> -329.73 | E15: =D15/B15 -> -1.0991
A16: Business School | B16: 0 | C16: =sumif($B$20:$C$557,A16,$C$20:$C$557) -> 0 | D16: =B16-C16 -> 0 | E16: =D16/B16 -> #DIV/0! | G16: Amount spent on Travel | H16: =SUMIF($B$20:$C$271,"Travel",$C$20:$C$271) -> 1453.26
A17: Total | B17: =SUM(B6:B16) -> 4913.68 | C17: =SUM(C6:C16) -> 6048.5467 | D17: =SUM(D6:D15) -> -1134.8667 | E17: =D17/B17 -> -0.23096064 | G17: Amount in Travel Bank | H17: =500-SUMIF($B$20:$C$271,"Travel",$C$20:$C$271)+'April 2024'!H17 -> -450.02
A19: Date | B19: Category | C19: Spent | D19: Note
A20: Monthly | B20: Fixed | C20: 1476 | D20: Rent
A21: Monthly | B21: Fixed | C21: 90 | D21: Exercise
A22: Monthly | B22: Fixed | C22: =460/6 -> 76.666667 | D22: Car Insurance
A23: Monthly | B23: Fixed | C23: 2.87 | D23: Spotify - Martin
A24: Monthly | B24: Fixed | C24: 2.99 | D24: Google One
A25: Monthly | B25: Fixed | C25: 5.83 | D25: One Drive
A26: Monthly | B26: Fixed | C26: 6 | D26: Amazon
A27: Monthly | B27: Fixed | C27: 112 | D27: Phone
A30: Date | B30: Category | C30: Spent | D30: Note
A32: 45778 | B32: Groceries | C32: 36.45 | D32: AMAZON MKTPL*NB7IC47F2
A33: 45778 | B33: Eating out | C33: 0 | D33: TST*SUGAR &amp; SPICE - CAMB
A34: 45779 | B34: Eating out | C34: 0 | D34: EZCATER*LOTUS EXPRESS
A35: 45779 | B35: Eating out | C35: 0 | D35: SNACK* BANH MI HUONG Q
A36: 45779 | B36: Eating out | C36: 0 | D36: TST*SUGAR &amp; SPICE - CAMB
A37: 45779 | B37: Gas | C37: 2.4 | D37: MBTA-550016700415-9937
A38: 45779 | B38: Gas | C38: 2.4 | D38: MBTA-550016700415-9937
A39: 45779 | B39: Groceries | C39: 58.02 | D39: LOWE'S FOODS #1262
A40: 45779 | B40: Eating out | C40: 8.69 | D40: BASF CORPORATION CAFE
A41: 45781 | B41: Groceries | C41: 27.86 | D41: AMAZON MKTPL*NB49S2LN1
A42: 45781 | B42: Eating out | C42: 15.52 | D42: SCRIBANOS ITALIAN DELI
A43: 45781 | B43: Eating out | C43: 33.99 | D43: TST*DOHERTYS IRISH PUB -
... A50: 45784 | B50: Eating out | C50: 240.41 | D50: NEW WINGS KITCHEN
A51: 45784 | B51: Travel | C51: =5062.2/10+220 -> 726.22 | D51: DR airbnb + etc
A52: 45784 | B52: Fun / Misc | C52: 273.57 | D52: Vok baths Main CP
A53: 45785 | B53: Eating out | C53: 7.74 | D53: Sannir Landvaettir
A54: 45786 | B54: Fun / Misc | C54: 31 | D54: ROCK SPOT BROOKLINE
A55: 45786 | B55: Gas | C55: 7.76 | D55: Parka
A56: 45786 | B56: Eating out | C56: 19.25 | D56: Blue Lagoon SPA
A57: 45786 | B57: Gas | C57: 7.76 | D57: Parka
A58: 45788 | B58: Eating out | C58: 11.01 | D58: BUSKERS IRISH PUB
A59: 45788 | B59: Gas | C59: 6 | D59: LAZ PARKING L05192-CALE
A60: 45788 | B60: Eating out | C60: 9.99 | D60: CHINA STAR
A61: 45788 | B61: Groceries | C61: 40.1 | D61: Amazon.com*NW9986N92
A62: 45788 | B62: Household Goods | C62: 1.25 | D62: FC FOWLER LAUNDRY ULTRA
A63: 45788 | B63: Household Goods | C63: 1.25 | D63: FC FOWLER LAUNDRY ULTRA
... A117: 45806 | B117: Gas | C117: 128 | D117: SMARTRIP WASHINGTON DC
E118: -2.75
E119: -13.25
E120: -28.27
E121: -51.99
E122: -31.03
E123: -53.58
E124: -1.5
E125: -12.84
E126: -2.4
E127: -1.25
E128: -25.95
E129: -1.25
... E134: -81.2

Sheet June 2025
A4: Monthly Spending | G4: Monthly Overview | J4: Expenses over Time
A5: Category | B5: Budgeted | C5: Amount Spent | D5: Amount Remaining | E5: % Remaining | G5: Income
A6: Fixed | B6: 2663.68 | C6: =sumif($B$20:$C$570,A6,$C$20:$C$570) -> 1772.3567 | D6: =B6-C6 -> 891.32333 | E6: =D6/B6 -> 0.33462103 | G6: Martin Paycheck | H6: 0
A7: Utilities | B7: 0 | C7: =sumif($B$20:$C$570,A7,$C$20:$C$570) -> 0 | D7: =B7-C7 -> 0 | E7: =D7/B7 -> #DIV/0! | G7: Rachel Paycheck | H7: 3038
A8: Bills | B8: 250 | C8: =sumif($B$20:$C$570,A8,$C$20:$C$570) -> 147.98 | D8: =B8-C8 -> 102.02 | E8: =D8/B8 -> 0.40808 | G8: Total | H8: =SUM(H6:H7) -> 3038
A9: Groceries | B9: 400 | C9: =sumif($B$20:$C$570,A9,$C$20:$C$570) -> 882.56 | D9: =B9-C9 -> -482.56 | E9: =D9/B9 -> -1.2064
A10: Eating out | B10: 400 | C10: =sumif($B$20:$C$570,A10,$C$20:$C$570) -> 617.18 | D10: =B10-C10 -> -217.18 | E10: =D10/B10 -> -0.54295 | G10: Monthly Expenses
A11: Household Goods | B11: 200 | C11: =sumif($B$20:$C$570,A11,$C$20:$C$570) -> 1667.12 | D11: =B11-C11 -> -1467.12 | E11: =D11/B11 -> -7.3356 | G11: Total Spent | H11: =sum(C17) -> 6102.7867
A12: Travel | B12: 500 | C12: =sumif($B$20:$C$570,A12,$C$20:$C$570) -> 399.35 | D12: =B12-C12 -> 100.65 | E12: =D12/B12 -> 0.2013
A13: Gas | B13: 200 | C13: =sumif($B$20:$C$570,A13,$C$20:$C$570) -> 71.84 | D13: =B13-C13 -> 128.16 | E13: =D13/B13 -> 0.6408 | G13: Recurring Expenses
A14: Health | B14: 0 | C14: =sumif($B$20:$C$570,A14,$C$20:$C$570) -> 125.39 | D14: =B14-C14 -> -125.39 | E14: =D14/B14 -> #DIV/0! | G14: Car Insurance
A15: Fun / Misc | B15: 300 | C15: =sumif($B$20:$C$570,A15,$C$20:$C$570) -> 419.01 | D15: =B15-C15 -> -119.01 | E15: =D15/B15 -> -0.3967
A16: Business School | B16: 0 | C16: =sumif($B$20:$C$570,A16,$C$20:$C$570) -> 0 | D16: =B16-C16 -> 0 | E16: =D16/B16 -> #DIV/0! | G16: Amount spent on Travel | H16: =SUMIF($B$20:$C$284,"Travel",$C$20:$C$284) -> 399.35
A17: Total | B17: =SUM(B6:B16) -> 4913.68 | C17: =SUM(C6:C16) -> 6102.7867 | D17: =SUM(D6:D15) -> -1189.1067 | E17: =D17/B17 -> -0.24199921 | G17: Amount in Travel Bank | H17: =500-SUMIF($B$20:$C$284,"Travel",$C$20:$C$284)+'April 2024'!H17 -> 603.89
A19: Date | B19: Category | C19: Spent | D19: Note
A20: Monthly | B20: Fixed | C20: 1476 | D20: Rent
A21: Monthly | B21: Fixed | C21: 90 | D21: Exercise
A22: Monthly | B22: Fixed | C22: =460/6 -> 76.666667 | D22: Car Insurance
A23: Monthly | B23: Fixed | C23: 2.87 | D23: Spotify - Martin
A24: Monthly | B24: Fixed | C24: 2.99 | D24: Google One
A25: Monthly | B25: Fixed | C25: 5.83 | D25: One Drive
A26: Monthly | B26: Fixed | C26: 6 | D26: Amazon
A27: Monthly | B27: Fixed | C27: 112 | D27: Phone
A30: Date | B30: Category | C30: Spent | D30: Note
A32: 45832 | B32: Eating out | C32: 60 | D32: sharon bach dinner
A33: 45833 | B33: Fun / Misc | C33: 365.25 | D33: sharon bach - total
A34: 45835 | B34: Household Goods | C34: 96 | D34: haircut
A35: 45809 | B35: Household Goods | C35: 63.59 | D35: Amazon.com*NN4779K70
A36: 45809 | B36: Travel | C36: 231.35 | D36: AIRBNB * TAFR8HYY
A37: 45810 | B37: Eating out | C37: 4.34 | D37: HUDSON ST1806
A38: 45810 | B38: Eating out | C38: 23.67 | D38: Wagamama USA LLC
A39: 45810 | B39: Groceries | C39: 503.61 | D39: COSTCO WHSE #0334
A40: 45810 | B40: Groceries | C40: 5.81 | D40: COSTCO WHSE #0334
A41: 45810 | B41: Eating out | C41: 64.41 | D41: YE LOY INC
A42: 45811 | B42: Bills | C42: 2.99 | D42: APPLE.COM/BILL
A43: 45811 | B43: Health | C43: 125.39 | D43: ONELIFE FITNESS BALLSTON
... A59: 45830 | B59: Gas | C59: 4.99 | D59: UBER *ONE MEMBERSHIP
A60: 45831 | C60: 244 | D60: UNIVERSAL NORTH AMERICA | E60: Rental - home insurance
A61: 45832 | B61: Eating out | C61: 9.3 | D61: AMKCAPITAL ONE C2
A62: 45833 | B62: Fun / Misc | C62: 5 | D62: movie tickets
A63: 45833 | B63: Eating out | C63: 9.65 | D63: AMKCAPITAL ONE C2
A64: 45834 | B64: Eating out | C64: 11.65 | D64: AMK CAPITAL ONE C1
A65: 45835 | B65: Eating out | C65: 9.15 | D65: AMK CAPITAL ONE C3
A66: 45837 | B66: Groceries | C66: 325.08 | D66: COSTCO WHSE #0233
A67: 45837 | B67: Bills | C67: 0.99 | D67: APPLE.COM/BILL
A68: 45815 | B68: Eating out | C68: 18 | D68: eden center lunch
A69: 45815 | B69: Eating out | C69: 75 | D69: gyukaku
B70: Groceries | C70: -267 | D70: groceries - howard
B71: Household Goods | C71: 145.15 | D71: shoes
B72: Household Goods | C72: 80 | D72: R&B jeans
B73: Household Goods | C73: 273 | D73: rachel's clothes + shoes
B74: Travel | C74: 168 | D74: sharons wedding
B75: Groceries | C75: 49
B76: Household Goods | C76: 6.19 | D76: toothpaste
B77: Eating out | C77: 105
B78: Eating out | C78: 18
B79: Bills | C79: 144 | D79: car check + oil change
B80: Household Goods | C80: 52.54 | D80: clarks shoes
B81: Eating out | C81: 52.54 | D81: lots of transactions consolidated
B82: Gas | C82: 45 | D82: gas
A83: 45810 | B83: Household Goods | C83: 328.17 | D83: Amazon.com*NN98V4YW1
A84: 45811 | B84: Household Goods | C84: 76.66 | D84: Amazon.com*N615P6490
A85: 45811 | B85: Household Goods | C85: 14.82 | D85: AMAZON MKTPL*N69IH2FP0
A86: 45811 | B86: Household Goods | C86: 31.06 | D86: AMAZON MKTPL*N65IH1F00
A87: 45812 | B87: Household Goods | C87: 3.96 | D87: AMAZON MKTPL*N62I343J0
A88: 45816 | B88: Household Goods | C88: 14.47 | D88: AMAZON MKTPL*N60OY0YX1
A89: 45817 | B89: Groceries | C89: 63.63 | D89: Amazon.com*NH4VN2Z90
A90: 45824 | B90: Groceries | C90: 93.73 | D90: Whole Foods ARL 10042
A91: 45831 | B91: Groceries | C91: 59.41 | D91: Amazon.com*NQ8FJ2Z92
A92: 45832 | B92: Household Goods | C92: 8.15 | D92: Amazon.com*NO0KS4SX1
A93: 45832 | B93: Household Goods | C93: -4.03 | D93: Amazon.com
A94: 45833 | B94: Household Goods | C94: 56.77 | D94: AMAZON MKTPL*NO6PJ1YS1
... A98: 45838 | B98: Groceries | C98: 9.99 | D98: Amazon Grocery Subscri
E113: -1.1
E114: -30
E115: -10.69
E116: -81.99
E117: -91.44
E118: -79.99
E119: -120.75
E120: -1.75
E121: -1.25
E122: -1.25
E123: -9.6
E124: -1.25
... E147: -81.2

Sheet July 2025
A4: Monthly Spending | G4: Monthly Overview | J4: Expenses over Time
A5: Category | B5: Budgeted | C5: Amount Spent | D5: Amount Remaining | E5: % Remaining | G5: Income
A6: Fixed | B6: 2663.68 | C6: =sumif($B$20:$C$548,A6,$C$20:$C$548) -> 1772.3567 | D6: =B6-C6 -> 891.32333 | E6: =D6/B6 -> 0.33462103 | G6: Martin Paycheck | H6: 0
A7: Utilities | B7: 0 | C7: =sumif($B$20:$C$548,A7,$C$20:$C$548) -> 0 | D7: =B7-C7 -> 0 | E7: =D7/B7 -> #DIV/0! | G7: Rachel Paycheck | H7: 3038
A8: Bills | B8: 250 | C8: =sumif($B$20:$C$548,A8,$C$20:$C$548) -> 0 | D8: =B8-C8 -> 250 | E8: =D8/B8 -> 1 | G8: Total | H8: =SUM(H6:H7) -> 3038
A9: Groceries | B9: 400 | C9: =sumif($B$20:$C$548,A9,$C$20:$C$548) -> 183.51 | D9: =B9-C9 -> 216.49 | E9: =D9/B9 -> 0.541225
A10: Eating out | B10: 400 | C10: =sumif($B$20:$C$548,A10,$C$20:$C$548) -> 782.76 | D10: =B10-C10 -> -382.76 | E10: =D10/B10 -> -0.9569 | G10: Monthly Expenses
A11: Household Goods | B11: 200 | C11: =sumif($B$20:$C$548,A11,$C$20:$C$548) -> 519.19 | D11: =B11-C11 -> -319.19 | E11: =D11/B11 -> -1.59595 | G11: Total Spent | H11: =sum(C17) -> 3870.2367
A12: Travel | B12: 500 | C12: =sumif($B$20:$C$548,A12,$C$20:$C$548) -> 67 | D12: =B12-C12 -> 433 | E12: =D12/B12 -> 0.866
A13: Gas | B13: 200 | C13: =sumif($B$20:$C$548,A13,$C$20:$C$548) -> 6 | D13: =B13-C13 -> 194 | E13: =D13/B13 -> 0.97 | G13: Recurring Expenses
A14: Health | B14: 0 | C14: =sumif($B$20:$C$548,A14,$C$20:$C$548) -> 138.36 | D14: =B14-C14 -> -138.36 | E14: =D14/B14 -> #DIV/0! | G14: Car Insurance
A15: Fun / Misc | B15: 300 | C15: =sumif($B$20:$C$548,A15,$C$20:$C$548) -> 401.06 | D15: =B15-C15 -> -101.06 | E15: =D15/B15 -> -0.33686667
A16: Business School | B16: 0 | C16: =sumif($B$20:$C$548,A16,$C$20:$C$548) -> 0 | D16: =B16-C16 -> 0 | E16: =D16/B16 -> #DIV/0! | G16: Amount spent on Travel | H16: =SUMIF($B$20:$C$262,"Travel",$C$20:$C$262) -> 67
A17: Total | B17: =SUM(B6:B16) -> 4913.68 | C17: =SUM(C6:C16) -> 3870.2367 | D17: =SUM(D6:D15) -> 1043.4433 | E17: =D17/B17 -> 0.21235476 | G17: Amount in Travel Bank | H17: =500-SUMIF($B$20:$C$262,"Travel",$C$20:$C$262)+'April 2024'!H17 -> 936.24
A19: Date | B19: Category | C19: Spent | D19: Note
A20: Monthly | B20: Fixed | C20: 1476 | D20: Rent
A21: Monthly | B21: Fixed | C21: 90 | D21: Exercise
A22: Monthly | B22: Fixed | C22: =460/6 -> 76.666667 | D22: Car Insurance
A23: Monthly | B23: Fixed | C23: 2.87 | D23: Spotify - Martin
A24: Monthly | B24: Fixed | C24: 2.99 | D24: Google One
A25: Monthly | B25: Fixed | C25: 5.83 | D25: One Drive
A26: Monthly | B26: Fixed | C26: 6 | D26: Amazon
A27: Monthly | B27: Fixed | C27: 112 | D27: Phone
A30: Date | B30: Category | C30: Spent | D30: Note
A32: 45852 | B32: Health | C32: 20 | D32: massage tip
A33: 45840 | B33: Eating out | C33: 11.45 | D33: AMK CAPITAL ONE C3
A34: 45840 | B34: Eating out | C34: 9.89 | D34: AMK CAPITAL ONE C1
A35: 45840 | B35: Groceries | C35: 23.52 | D35: WEEE INC.
A36: 45841 | B36: Eating out | C36: 9.65 | D36: AMKCAPITAL ONE C2
A37: 45841 | B37: Health | C37: 47.99 | D37: BALLSTON FITNESS BALLSTO
A38: 45842 | B38: Gas | C38: 6 | D38: SMARTRIP WASHINGTON DC
A39: 45842 | B39: Eating out | C39: 4.73 | D39: CVS/PHARMACY #01833
A40: 45844 | B40: Groceries | C40: 64.99 | D40: WWW COSTCO COM
A41: 45844 | B41: Eating out | C41: 23.09 | D41: TST*HOT LOLAS
A42: 45844 | B42: Eating out | C42: 2.59 | D42: CVS/PHARMACY #01341
A43: 45844 | B43: Household Goods | C43: 25 | D43: Amazon.com*N33GD3B21
... A61: 45849 | B61: Eating out | C61: 85 | D61: venmo - kevin
B62: Household Goods | C62: 34 | D62: rachel clothes
B63: Eating out | C63: 16.23 | D63: eden center
B64: Eating out | C64: 103 | D64: consolidated transactions
A65: 45839 | B65: Household Goods | C65: -5.34 | D65: Amazon.com
A66: 45844 | B66: Groceries | C66: 27.54 | D66: Whole Foods PST 10135
A67: 45847 | B67: Household Goods | C67: 5.81 | D67: Amazon.com*NL9A01TI0
A68: 45849 | B68: Household Goods | C68: 0.01 | D68: AMZ*Woot LLC
A69: 45851 | B69: Household Goods | C69: 13.4 | D69: AMAZON MKTPL*NR5BT1FE0
A70: 45852 | B70: Household Goods | C70: -13.12 | D70: Amazon.com
A71: 45852 | B71: Groceries | C71: 66.41 | D71: Amazon.com*RN6SV9XR3
A72: 45853 | B72: Household Goods | C72: 401.74 | D72: Amazon.com*NR20943N1
A73: 45853 | B73: Household Goods | C73: 31.75 | D73: AMAZON MKTPL*NR10G9X30
A74: 45856 | B74: Household Goods | C74: -7.06 | D74: Amazon.com
B75: travel | C75: 67 | D75: jetblue plane
B76: Household Goods | C76: 33 | D76: martin haircut
E91: -1.1
E92: -30
E93: -10.69
E94: -81.99
E95: -91.44
E96: -79.99
E97: -120.75
E98: -1.75
E99: -1.25
E100: -1.25
E101: -9.6
E102: -1.25
... E125: -81.2

Sheet August 2025
A4: Monthly Spending | G4: Monthly Overview | J4: Expenses over Time
A5: Category | B5: Budgeted | C5: Amount Spent | D5: Amount Remaining | E5: % Remaining | G5: Income
A6: Fixed | B6: 2663.68 | C6: =sumif($B$20:$C$569,A6,$C$20:$C$569) -> 1772.3567 | D6: =B6-C6 -> 891.32333 | E6: =D6/B6 -> 0.33462103 | G6: Martin Paycheck | H6: 0
A7: Utilities | B7: 0 | C7: =sumif($B$20:$C$569,A7,$C$20:$C$569) -> 0 | D7: =B7-C7 -> 0 | E7: =D7/B7 -> #DIV/0! | G7: Rachel Paycheck | H7: 3038
A8: Bills | B8: 250 | C8: =sumif($B$20:$C$569,A8,$C$20:$C$569) -> 0 | D8: =B8-C8 -> 250 | E8: =D8/B8 -> 1 | G8: Total | H8: =SUM(H6:H7) -> 3038
A9: Groceries | B9: 400 | C9: =sumif($B$20:$C$569,A9,$C$20:$C$569) -> 0 | D9: =B9-C9 -> 400 | E9: =D9/B9 -> 1
A10: Eating out | B10: 400 | C10: =sumif($B$20:$C$569,A10,$C$20:$C$569) -> 0 | D10: =B10-C10 -> 400 | E10: =D10/B10 -> 1 | G10: Monthly Expenses
A11: Household Goods | B11: 200 | C11: =sumif($B$20:$C$569,A11,$C$20:$C$569) -> 0 | D11: =B11-C11 -> 200 | E11: =D11/B11 -> 1 | G11: Total Spent | H11: =sum(C17) -> 1772.3567
A12: Travel | B12: 500 | C12: =sumif($B$20:$C$569,A12,$C$20:$C$569) -> 0 | D12: =B12-C12 -> 500 | E12: =D12/B12 -> 1
A13: Gas | B13: 200 | C13: =sumif($B$20:$C$569,A13,$C$20:$C$569) -> 0 | D13: =B13-C13 -> 200 | E13: =D13/B13 -> 1 | G13: Recurring Expenses
A14: Health | B14: 0 | C14: =sumif($B$20:$C$569,A14,$C$20:$C$569) -> 0 | D14: =B14-C14 -> 0 | E14: =D14/B14 -> #DIV/0! | G14: Car Insurance
A15: Fun / Misc | B15: 300 | C15: =sumif($B$20:$C$569,A15,$C$20:$C$569) -> 0 | D15: =B15-C15 -> 300 | E15: =D15/B15 -> 1
A16: Business School | B16: 0 | C16: =sumif($B$20:$C$569,A16,$C$20:$C$569) -> 0 | D16: =B16-C16 -> 0 | E16: =D16/B16 -> #DIV/0! | G16: Amount spent on Travel | H16: =SUMIF($B$20:$C$283,"Travel",$C$20:$C$283) -> 0
A17: Total | B17: =SUM(B6:B16) -> 4913.68 | C17: =SUM(C6:C16) -> 1772.3567 | D17: =SUM(D6:D15) -> 3141.3233 | E17: =D17/B17 -> 0.63930157 | G17: Amount in Travel Bank | H17: =500-SUMIF($B$20:$C$283,"Travel",$C$20:$C$283)+'April 2024'!H17 -> 1003.24
A19: Date | B19: Category | C19: Spent | D19: Note
A20: Monthly | B20: Fixed | C20: 1476 | D20: Rent
A21: Monthly | B21: Fixed | C21: 90 | D21: Exercise
A22: Monthly | B22: Fixed | C22: =460/6 -> 76.666667 | D22: Car Insurance
A23: Monthly | B23: Fixed | C23: 2.87 | D23: Spotify - Martin
A24: Monthly | B24: Fixed | C24: 2.99 | D24: Google One
A25: Monthly | B25: Fixed | C25: 5.83 | D25: One Drive
A26: Monthly | B26: Fixed | C26: 6 | D26: Amazon
A27: Monthly | B27: Fixed | C27: 112 | D27: Phone
A30: Date | B30: Category | C30: Spent | D30: Note
E112: -1.1
E113: -30
E114: -10.69
E115: -81.99
E116: -91.44
E117: -79.99
E118: -120.75
E119: -1.75
E120: -1.25
E121: -1.25
E122: -9.6
E123: -1.25
... E146: -81.2

Sheet Financial Planning
A1: Total Annual Income | B1: =120000+148700 -> 268700 | E1: Overview
A2: Monthly Take home | B2: ='MartinRachel Pay Stub'!B20*2+'MartinRachel Pay Stub'!E20*2 -> 9280.96 | E2: 45108 | F2: 45139 | G2: 45170 | H2: 45200 | I2: 45231 | J2: 45261 | K2: 45292 | L2: 45323 | M2: 45352 | N2: 45383 | O2: 45413 | P2: 45444 | Q2: 45474 | R2: 45505 | S2: Sept 2024
A3: Monthly Budget | B3: ='July 2023 '!B16 -> 4750 | D3: Income | E3: =sum('July 2023 '!$H$6:$H$7) -> 9280.96 | F3: =sum('Aug 2023'!$H$6:$H$7) -> 9377.86 | G3: =sum('Sept 2023'!$H$6:$H$7) -> 9169 | H3: =sum('Oct 2023'!$H$6:$H$7) -> 10476 | I3: =sum('Nov 2023'!$H$6:$H$7) -> 15504 | J3: =sum(3702,2649,3702,2261.29) -> 12314.29 | K3: =sum(1473*2+2607*2+4500) -> 12660 | L3: ='Feb 2024'!H8 -> 8286 | M3: ='March 2024'!$H$8 -> 8868 | N3: ='April 2024'!$H$8 -> 9200 | O3: ='May 2024'!$H$8 -> 12024 | P3: ='June 2024'!$H$8 -> 12927 | Q3: ='July 2024'!$H$8 -> 12900 | R3: ='Aug 2024'!$H$8 -> 12900
A4: Monthly Savings | B4: =B2-B3 -> 4530.96 | D4: Spent | E4: ='July 2023 '!$H$10 -> 5549.63 | F4: ='Aug 2023'!$H$10 -> 5352.45 | G4: ='Sept 2023'!$H$10 -> 5661.46 | H4: ='Oct 2023'!$H$10 -> 6435.75 | I4: ='Nov 2023'!$H$10 -> 10830.42 | J4: ='Dec 2023'!C16 -> 7536.32 | K4: ='Jan 2024'!H10 -> 7230.99 | L4: ='Feb 2024'!H11 -> 6377.04 | M4: ='March 2024'!H11 -> 9041.8767 | N4: ='April 2024'!$H$11 -> 13059.367 | O4: ='May 2024'!$H$11 -> 6570.3467 | P4: ='June 2024'!$H$11 -> 8363.7167 | Q4: ='July 2024'!$H$11 -> 6564.97 | R4: ='Aug 2024'!$H$11 -> 8643.1595
A5: ESPP Returns | B5: ='MartinRachel Pay Stub'!B18*2*12*1.1 -> 16356.912 | D5: Saved | E5: =E3-E4 -> 3731.33 | F5: =F3-F4 -> 4025.41 | G5: =G3-G4 -> 3507.54 | H5: =H3-H4 -> 4040.25 | I5: =I3-I4 -> 4673.58 | J5: =J3-J4 -> 4777.97 | K5: =K3-K4 -> 5429.01 | L5: =L3-L4 -> 1908.96 | ... R5: =R3-R4 -> 4256.8405
A6: Estimated Annual Savings | B6: =B4*12+B5 -> 70728.432 | D6: From Ma | I6: 1600 | J6: 5600 | K6: 10000 | N6: 10000 | O6: 8500 | P6: 9300 | Q6: 8500 | R6: 8000 | S6: 5000
A7: Projected Annual Savings | B7: =average(E5:K5)*12+B5 -> 68102.781
A8: Actual Savings YTD | B8: =sum(E5:K5)+sum(J8:O8) -> 31168.84 | D8: Travel Bank | E8: ='July 2023 '!H16 -> 500 | F8: ='Aug 2023'!H16 -> 746.4 | G8: ='Sept 2023'!H16 -> 1225.8 | H8: ='Oct 2023'!H16 -> 659.7 | I8: ='Nov 2023'!H16 -> -614.34 | J8: ='Dec 2023'!H16 -> -135.34 | K8: ='Jan 2024'!H16 -> -75.34 | L8: ='Feb 2024'!H17 -> 150.46 | M8: ='March 2024'!$H$17 -> 181.28 | N8: ='April 2024'!$H$17 -> 503.24 | O8: ='May 2024'!$H$17 -> 359.45 | P8: ='June 2024'!$H$17 -> 859.45 | Q8: ='July 2024'!$H$17 -> 749.49
A9: Untouchable Savings | B9: =SUM(B10:B13) -> 69000 | D9: ESPP Payout | I9: 8511
A10: Martin 401k | B10: 22500
A11: Rachel 401k | B11: 22500
A12: Martin After Tax | B12: 20000
A13: Rachel After Tax | B13: 4000

Sheet Travelbank Rules
B2: Included in Travel Bank | C2: Not included in Travel Bank
B3: Airfare | C3: Concerts
B4: Hotels | C4: Museum Admission
B5: Big Tickets | C5: Food
B6: Car Rental | C6: Local Transit (Bus, Metro, Uber)
B7: 1/2 transit to airport | C7: 1/2 transit to airpot

Sheet MartinRachel Pay Stub
A4: Pre - Roth 401k | H4: After - Roth 401k
A5: Martin | D5: Rachel | H5: Martin | K5: Rachel
A6: Earnings | B6: 6195 | D6: Earnings | E6: 5000 | H6: Earnings | I6: 6195 | K6: Earnings | L6: 5000
A7: Pre-Tax Deductions | B7: =sum(B8:B11) -> 264.3 | D7: Pre-tax Deductions | E7: =sum(E8:E12) -> 750 | H7: Pre-Tax Deductions | I7: =sum(I8:I11) -> 264.3 | K7: Pre-tax Deductions | L7: =sum(L8:L12) -> 750
A8: HSA | B8: 139 | H8: HSA | I8: 139
A9: Dental | B9: 15 | H9: Dental | I9: 15
A10: HDHP | B10: 103 | H10: HDHP | I10: 103
A11: Vision | B11: 7.3 | H11: Vision | I11: 7.3
A12: 401k | B12: 929 | C12: 0.15 | D12: 401k | E12: =0.15*E6 -> 750 | F12: 0.15 | H12: 401k | I12: 929 | J12: 0.15 | K12: 401k | L12: =0.15*L6 -> 750 | M12: 0.15
A13: Taxes | B13: =SUM(B14:B16) -> 1402.9 | D13: Taxes | E13: =SUM(E14:E16) -> 785.45 | H13: Taxes | I13: =SUM(I14:I16) -> 1402.9 | K13: Taxes | L13: =SUM(L14:L16) -> 785.45
A14: W/H | B14: 949 | D14: W/H | E14: 297.31 | H14: W/H | I14: 949 | K14: W/H | L14: 297.31
A15: FICA EE | B15: 367.86 | D15: FICA EE | E15: 418.61 | H15: FICA EE | I15: 367.86 | K15: FICA EE | L15: 418.61
A16: MWT EE | B16: 86.04 | D16: MWT EE | E16: 69.53 | H16: MWT EE | I16: 86.04 | K16: MWT EE | L16: 69.53
A17: Post Tax Deductions | B17: =sum(B18:B19) -> 1672.87 | E17: =sum(E18:E19) -> 750 | H17: Post Tax Deductions | I17: =sum(I18:I19) -> 1672.87 | L17: =sum(L18:L19) -> 750
A18: ESPP | B18: 619.58 | H18: ESPP | I18: 619.58
A19: After Tax | B19: 1053.29 | C19: -0.17 | E19: =E6*0.15 -> 750 | F19: -0.15 | H19: After Tax | I19: 1053.29 | J19: -0.17 | L19: =L6*0.15 -> 750 | M19: -0.15
A20: Net Income | B20: =B6-sum(B8:B12,B14:B16,B18:B19) -> 1925.93 | E20: =E6-sum(E8:E12,E14:E16,E18:E19) -> 2714.55 | H20: Net Income | I20: =I6-sum(I8:I12,I14:I16,I18:I19) -> 1925.93 | L20: =L6-sum(L8:L12,L14:L16,L18:L19) -> 2714.55
H21: Net Income /month | I21: =1719*2 -> 3438 | L21: =2763*2 -> 5526 | M21: from paystub (end sept)

Sheet Churn Fees
A1: Date | B1: Item | C1: Amount | F1: Tracker
A2: 45138 | B2: AF Biz Plat | C2: 695 | F2: Rent - Eric | G2: 2650.7
A3: 45138 | B3: Apartment Fee | C3: =2.25%*2054 -> 46.215 | F3: Rent - Houston | G3: 2124.74
A4: 45139 | B4: Apartment Fee | C4: 53.2 | F4: US Bank | G4: 3000
A5: 45139 | B5: Phone Fee | C5: -120
A6: 45139 | B6: United Airlines | C6: -200
A7: 45165 | B7: Apartment Fee | C7: 46
A8: 45165 | B8: Referral Tax | C8: 200
A9: 2024 | B9: United Airliesn | C9: -200
A10: Sign up Bonus | C10: =175*1.1*10 -> 1925
A11: Net | C11: =C10-sum(C2:C9) -> 1404.585
A14: Date | B14: Item | C14: Amount
A15: 45197 | B15: AF Biz Plat | C15: 295
A16: 45197 | B16: Apartment Fees
A23: Sign up Bonus | C23: =175*1.1*10 -> 1925
A24: Net | C24: =C23-sum(C15:C22) -> 1630

Sheet Hidden list and Figures
A3: Fixed | B3: =sum(Budget!C38:C40) -> #REF! | D3: Monday | E3: Week 1 | F3: 0.01 | G3: 1
A4: Bills | B4: =Sum(Budget!C45:C49) -> #REF! | D4: Tuesday | E4: Week 2 | F4: 0.02 | G4: 2
A5: Groceries | B5: =sum(Budget!F38:F47) -> #REF! | D5: Wednesday | E5: Week 3 | F5: 0.03 | G5: 3
A6: Eating out | B6: =SUM(Budget!C59) -> #REF! | D6: Thursday | E6: Week 4 | F6: 0.04 | G6: 4
A7: Household Goods | D7: Friday | F7: 0.05 | G7: 5
A8: Travel | D8: Saturday | F8: 0.06 | G8: 6
A9: Gas | D9: Sunday | F9: 0.07 | G9: 7
A10: Health
A11: Business School | F11: 0.08 | G11: 8
A12: Fun / Misc | F12: 0.09 | G12: 9
F13: 0.1 | G13: 10
F14: 0.11 | G14: 11
F15: 0.12 | G15: 12
C16: Current Savings | D16: =B21 -> 2668 | F16: 0.13 | G16: 13
C17: Goal | D17: =B22-B21 -> -622 | F17: 0.14 | G17: 14
A18: Monthly | F18: 0.15 | G18: 15
A19: Weekly | F19: 0.16 | G19: 16
A20: Bi-Weekly | F20: 0.17 | G20: 17
A21: ='Large Purchase Calculator'!C12 -> 43192 | B21: =DATEDIF(A21,A22,"D") -> 2668 | F21: 0.18 | G21: 18
A22: =Now() -> 45860.887 | B22: =DATEDIF(A21,A23,"D") -> 2046 | F22: 0.19 | G22: 19
A23: =DATE(YEAR('Large Purchase Calculator'!C12),MONTH('Large Purchase Calculator'!C12)+'Large Purchase Calculator'!B10,YEAR('Large Purchase Calculator'!C12)) -> 45238 | B23: =B21/B22 -> 1.3040078 | F23: 0.2 | G23: 20
F24: 0.21 | G24: 21
F25: 0.22 | G25: 22
F26: 0.23 | G26: 23
F27: 0.24 | G27: 24
F28: 0.25 | G28: 25
F29: 0.26 | G29: 26
F30: 0.27 | G30: 27
A31: =(300*52)/12 -> 1300 | F31: 0.28 | G31: 28
A32: =330*4 -> 1320 | F32: 0.29 | G32: 29
F33: 0.3
F34: 0.31
F35: 0.32
F36: 0.33
F37: 0.34
F38: 0.35
F39: 0.36
F40: 0.37
F41: 0.38
F42: 0.39
F43: 0.4
F44: 0.41
... F77: 0.74

Sheet Credit Card
A2: Credit Card
B4: I dont have a credit card payment | D4: TRUE
D6: Card 1 | E6: Card 2 | F6: Card 3
B7: Balance Owed: | D7: 10000 | E7: 2000 | F7: 10000
B8: Interest rate: | D8: 0.1 | E8: 0.1 | F8: 0.1
B9: Minimum Monthly Payment: | D9: 23 | E9: 35 | F9: 35
B12: Months to Pay off with Minimum Payment:
B13: =D6 -> Card 1 | D13: =E6 -> Card 2 | E13: =F6 -> Card 3
B14: =IFERROR(__xludf.DUMMYFUNCTION("IF(B20=TRUE, iferror((ROUNDUP(NPER(D8/12,-B22,D7,0),0)),""N/A""),iferror((ROUNDUP(NPER(D8/12,-D9,D7,0),0)),""N/A"") )"),"N/A") -> N/A | D14: =IFERROR(__xludf.DUMMYFUNCTION("IF(D20=TRUE, iferror((ROUNDUP(NPER(E8/12,-D22,E7,0),0)),""N/A""),iferror((ROUNDUP(NPER(E8/12,-E9,E7,0),0)),""N/A"") )"),78.0) -> 78 | E14: =IFERROR(__xludf.DUMMYFUNCTION("IF(E20=TRUE, iferror((ROUNDUP(NPER(F8/12,-E22,F7,0),0)),""N/A""),iferror((ROUNDUP(NPER(F8/12,-F9,F7,0),0)),""N/A"") )"),"N/A") -> N/A
B15: Total Interest Accrued Using Minimum Payment
B16: =D6 -> Card 1 | D16: =E6 -> Card 2 | E16: =F6 -> Card 3
B17: =IFERROR(__xludf.DUMMYFUNCTION("IF(B20=TRUE, (iferror(((NPER(D8/12,-B22,D7,0)*B22)-D7),""N/A"")),(iferror(((NPER(D8/12,-D9,D7,0)*D9)-D7),""N/A"")))"),"N/A") -> N/A | D17: =IFERROR(__xludf.DUMMYFUNCTION("IF(D20=TRUE, (iferror(((NPER(E8/12,-D22,E7,0)*D22)-E7),""N/A"")),(iferror(((NPER(E8/12,-E9,E7,0)*E9)-E7),""N/A"")))"),727.1344165813198) -> 727.13442 | E17: =IFERROR(__xludf.DUMMYFUNCTION("IF(E20=TRUE, (iferror(((NPER(F8/12,-E22,F7,0)*E22)-F7),""N/A"")),(iferror(((NPER(F8/12,-F9,F7,0)*F9)-F7),""N/A"")))"),"N/A") -> N/A
B18: Are you paying more than the minimum payment?
B19: =D6 -> Card 1 | D19: =E6 -> Card 2 | E19: =F6 -> Card 3
B20: TRUE | D20: FALSE | E20: FALSE
B21: =IF(B20=TRUE,"How much are you paying monthly?",IF(D20=TRUE ,"How much are you paying monthly?",IF(E20=TRUE,"How much are you paying monthly?"," "))) -> How much are you paying monthly?
B22: 20 | D22: 0 | E22: 0
B25: Your payments will be added and adjusted in your budget automatically! Once youve filled this out, please go check your budget!
B30: =SUM((IF(B20=TRUE,B22,D9)),(IF(D20=TRUE,D22,E9)),(If(E20=TRUE,E22,F9))) -> 90

Sheet Large Purchase Calculator
A2: Large Purchase Calculator
B5: Item:
B6: Cool Thing
B7: Price
B8: 300
B9: Months until purchase
B10: 1
B12: Date started Saving: | C12: 43192
B13: Monthly Saving amount:
B14: =B8/B10 -> 300
B15: TRUE | C15: Adjust Budget?
A25: =if(B15=TRUE,"!", " " ) -> ! | B25: =if(B15=TRUE,"Your budget has been automatically adjusted to add this expense! please go check your budget!", " " ) -> Your budget has been automatically adjusted to add this expense! please go check your budget! | E25: =if(B15=TRUE,"!", " " ) -> !

Sheet Copy of Sheet1
B2: Rachel Income | C2: Martin Income
A3: Gross | B3: 120000 | C3: 148700 | E3: =0.05*(C3-C4) -> 6310
A4: 401k Contributions | B4: 22500 | C4: 22500 | D4: Monthly Paycheck | E4: =E3/24 -> 262.91667
A5: HSA Contribution | B5: 0 | C5: 3360
A6: Health Insurance | B6: 0 | C6: 3000 | E6: Owed Amount | F6: Actual Paying
A7: Tax | B7: =(B3-B4)*0.22 -> 21450 | C7: =(C3-C4)*0.22 -> 27764 | D7: Tax Difference | E7: =C7/24 -> 1156.8333 | F7: 1400
A8: ESPP | C8: 14000
A9: After Tax 401k | C9: 17000 | D9: After Tax 401k Excess | E9: =8000/24 -> 333.33333
A11: Money Remaining | B11: =B3-sum(B4:B8) -> 76050 | C11: =C3-sum(C4:C10) -> 61076
A12: Monthly Income | B12: =B11/12 -> 6337.5 | C12: =C11/12 -> 5089.6667
A13: Biweekly Paycheck | B13: =B12/2 -> 3168.75 | C13: =C12/2 -> 2544.8333
A15: Actual Take Home | B15: =B13 -> 3168.75 | C15: 1700
A17: Monthly Money In | B17: 9700 | C17: money left :( | E17: Emergency Fund Target Amount | G17: =(sum(B18:B25)-B24)*6 -> 25200
A18: Rent | B18: 2100 | C18: =B17-B18 -> 7600
A19: Utilities | B19: 200 | C19: =C18-B19 -> 7400
A20: Car Insurance | B20: 100 | C20: =C19-B20 -> 7300
A21: Groceries | B21: 600 | C21: =C20-B21 -> 6700
A22: Eating Out | B22: 600 | C22: =C21-B22 -> 6100
A23: Gas | B23: 400 | C23: =C22-B23 -> 5700
A24: Martin Rachel Travel Fund | B24: 500 | C24: =C23-B24 -> 5200
A25: Household | B25: 200 | C25: =C24-B25 -> 5000
A26: Misc | B26: 200 | C26: =C25-B26 -> 4800
A28: House Downpayment
A30: House Cost | B30: 600000 | C30: 500000 | D30: 600000 | E30: 800000 | F30: 1000000
A31: Downpayment | B31: =B30*0.2 -> 120000 | C31: =C30*0.2 -> 100000 | D31: =D30*0.15 -> 90000 | E31: =E30*0.2 -> 160000 | F31: =F30*0.2 -> 200000
A32: Existing Savings | E32: 88000 | F32: 88000
A33: Monthly Savings | B33: =B31/24 -> 5000 | C33: =C31/24 -> 4166.6667 | D33: =D31/24 -> 3750 | E33: =(E31-E32)/24 -> 3000 | F33: =(F31-F32)/24 -> 4666.6667

Sheet Hidden Test Sheet
A4: Income | B4: =Budget!D34 -> #REF!
A5: Expenses | B5: =Budget!C61 -> #REF!
A6: Flex Spending | B6: =Budget!C6 -> #REF! | F6: =IFERROR(__xludf.DUMMYFUNCTION("SPARKLINE(B5,{""charttype"",""column"";""ymin"", 0; ""ymax"",MAX(B4);""firstcolor"",""#334960""})"),"#REF!") -> #REF!
A7: Daily Spending | B7: =Budget!B8 -> #REF!
H12: =IFERROR(__xludf.DUMMYFUNCTION("SPARKLINE(B4:B5, {""charttype"",""column""})"),"#REF!") -> #REF!
